Workbook

Sheet Présentation
A1: Format | B1: Devis
A2: Version | B2: 1
A4: AFF-2026-014 — Contrôle d’accès du site de Lyon
A6: Entreprise | B6: Exemple Industrie
A7: Client | B7: Client Exemple
A8: Révision | B8: Chiffrage v2 (en cours)
A9: Structure | B9: Structure principale
A10: Année de référence | B10: 2026
A11: Devise | B11: EUR
A12: Exporté le | B12: 2026-10-22 14:05
A14: Ventilation par nature de coût, aux taux de l’année de référence, avant inflation
A15: Nature | B15: Montant | C15: Part
A16: Main-d’œuvre | B16: =Devis!E13 -> 0 | C16: =IF(B20=0,0,B16/B20) -> 0
A17: Fournitures | B17: =Devis!F13 -> 0 | C17: =IF(B20=0,0,B17/B20) -> 0
A18: Sous-traitance | B18: =Devis!G13 -> 0 | C18: =IF(B20=0,0,B18/B20) -> 0
A19: Provisions pour risques | B19: =Devis!H13 -> 0 | C19: =IF(B20=0,0,B19/B20) -> 0
A20: Total | B20: =SUM(B16:B19) -> 0
A22: Montant Waterfall, inflation comprise | B22: =Devis!M13 -> 0
A23: Celui des lignes exportées : le montant inflation comprise d’une ligne ajoutée ou modifiée dans Excel n’est connu qu’après l’import.
A25: © 2026 Exemple Industrie — Généré par Waterfall le 2026-10-22 14:05 — logiciel libre sous licence AGPL-3.0 — www.waterfall-project.pro

Sheet Devis
A1: Devis — AFF-2026-014 Contrôle d’accès du site de Lyon
A2: Aux taux de l’année de référence, avant inflation. « Inclus » n’est pas lu à l’import.
A5: N° | B5: Lot ou poste | C5: Inclus | D5: Niveau | E5: Main-d’œuvre | F5: Fournitures | G5: Sous-traitance | H5: Provisions pour risques | I5: Heures I810 | J5: Heures I329 | K5: Heures I1M2 | L5: Total | M5: Montant Waterfall
A6: 1 | B6: Contrôle d’accès | D6: lot | E6: =SUM(E7:E9) -> 0 | F6: =SUM(F7:F9) -> 0 | G6: =SUM(G7:G9) -> 0 | H6: =SUM(H7:H9) -> 0 | I6: =SUM(I7:I9) -> 0 | J6: =SUM(J7:J9) -> 0 | K6: =SUM(K7:K9) -> 0 | L6: =SUM(L7:L9) -> 0 | M6: =SUM(M7:M9) -> 0
A7: 1.1 | B7: Centrale et logiciel | C7: Oui | D7: onglet | E7: =IF($C$7="Oui",SUMIFS(Lignes_1_1[[Montant]],Lignes_1_1[[Nature]],"Main-d’œuvre"),0) -> 0 | F7: =IF($C$7="Oui",SUMIFS(Lignes_1_1[[Montant]],Lignes_1_1[[Nature]],"Fournitures"),0) -> 0 | G7: =IF($C$7="Oui",SUMIFS(Lignes_1_1[[Montant]],Lignes_1_1[[Nature]],"Sous-traitance"),0) -> 0 | H7: =IF($C$7="Oui",SUMIFS(Lignes_1_1[[Montant]],Lignes_1_1[[Nature]],"Provisions pour risques"),0) -> 0 | I7: =IF($C$7="Oui",SUMIFS(Lignes_1_1[[Heures totales]],Lignes_1_1[[Code comptable]],"I810"),0) -> 0 | J7: =IF($C$7="Oui",SUMIFS(Lignes_1_1[[Heures totales]],Lignes_1_1[[Code comptable]],"I329"),0) -> 0 | K7: =IF($C$7="Oui",SUMIFS(Lignes_1_1[[Heures totales]],Lignes_1_1[[Code comptable]],"I1M2"),0) -> 0 | L7: =IF($C$7="Oui",SUM(Lignes_1_1[[Montant]]),0) -> 0 | M7: =IF($C$7="Oui",SUM(Lignes_1_1[[Montant Waterfall]]),0) -> 0
A8: 1.2 | B8: Lecteurs et câblage | C8: Oui | D8: onglet | E8: =IF($C$8="Oui",SUMIFS(Lignes_1_2[[Montant]],Lignes_1_2[[Nature]],"Main-d’œuvre"),0) -> 0 | F8: =IF($C$8="Oui",SUMIFS(Lignes_1_2[[Montant]],Lignes_1_2[[Nature]],"Fournitures"),0) -> 0 | G8: =IF($C$8="Oui",SUMIFS(Lignes_1_2[[Montant]],Lignes_1_2[[Nature]],"Sous-traitance"),0) -> 0 | H8: =IF($C$8="Oui",SUMIFS(Lignes_1_2[[Montant]],Lignes_1_2[[Nature]],"Provisions pour risques"),0) -> 0 | I8: =IF($C$8="Oui",SUMIFS(Lignes_1_2[[Heures totales]],Lignes_1_2[[Code comptable]],"I810"),0) -> 0 | J8: =IF($C$8="Oui",SUMIFS(Lignes_1_2[[Heures totales]],Lignes_1_2[[Code comptable]],"I329"),0) -> 0 | K8: =IF($C$8="Oui",SUMIFS(Lignes_1_2[[Heures totales]],Lignes_1_2[[Code comptable]],"I1M2"),0) -> 0 | L8: =IF($C$8="Oui",SUM(Lignes_1_2[[Montant]]),0) -> 0 | M8: =IF($C$8="Oui",SUM(Lignes_1_2[[Montant Waterfall]]),0) -> 0
A9: 1 | B9: Contrôle d’accès, hors postes | C9: Oui | D9: onglet | E9: =IF($C$9="Oui",SUMIFS(Lignes_1[[Montant]],Lignes_1[[Nature]],"Main-d’œuvre"),0) -> 0 | F9: =IF($C$9="Oui",SUMIFS(Lignes_1[[Montant]],Lignes_1[[Nature]],"Fournitures"),0) -> 0 | G9: =IF($C$9="Oui",SUMIFS(Lignes_1[[Montant]],Lignes_1[[Nature]],"Sous-traitance"),0) -> 0 | H9: =IF($C$9="Oui",SUMIFS(Lignes_1[[Montant]],Lignes_1[[Nature]],"Provisions pour risques"),0) -> 0 | I9: =IF($C$9="Oui",SUMIFS(Lignes_1[[Heures totales]],Lignes_1[[Code comptable]],"I810"),0) -> 0 | J9: =IF($C$9="Oui",SUMIFS(Lignes_1[[Heures totales]],Lignes_1[[Code comptable]],"I329"),0) -> 0 | K9: =IF($C$9="Oui",SUMIFS(Lignes_1[[Heures totales]],Lignes_1[[Code comptable]],"I1M2"),0) -> 0 | L9: =IF($C$9="Oui",SUM(Lignes_1[[Montant]]),0) -> 0 | M9: =IF($C$9="Oui",SUM(Lignes_1[[Montant Waterfall]]),0) -> 0
A10: 2 | B10: Mise en service | D10: lot | E10: =SUM(E11:E11) -> 0 | F10: =SUM(F11:F11) -> 0 | G10: =SUM(G11:G11) -> 0 | H10: =SUM(H11:H11) -> 0 | I10: =SUM(I11:I11) -> 0 | J10: =SUM(J11:J11) -> 0 | K10: =SUM(K11:K11) -> 0 | L10: =SUM(L11:L11) -> 0 | M10: =SUM(M11:M11) -> 0
A11: 2.1 | B11: Essais sur site | C11: Oui | D11: onglet | E11: =IF($C$11="Oui",SUMIFS(Lignes_2_1[[Montant]],Lignes_2_1[[Nature]],"Main-d’œuvre"),0) -> 0 | F11: =IF($C$11="Oui",SUMIFS(Lignes_2_1[[Montant]],Lignes_2_1[[Nature]],"Fournitures"),0) -> 0 | G11: =IF($C$11="Oui",SUMIFS(Lignes_2_1[[Montant]],Lignes_2_1[[Nature]],"Sous-traitance"),0) -> 0 | H11: =IF($C$11="Oui",SUMIFS(Lignes_2_1[[Montant]],Lignes_2_1[[Nature]],"Provisions pour risques"),0) -> 0 | I11: =IF($C$11="Oui",SUMIFS(Lignes_2_1[[Heures totales]],Lignes_2_1[[Code comptable]],"I810"),0) -> 0 | J11: =IF($C$11="Oui",SUMIFS(Lignes_2_1[[Heures totales]],Lignes_2_1[[Code comptable]],"I329"),0) -> 0 | K11: =IF($C$11="Oui",SUMIFS(Lignes_2_1[[Heures totales]],Lignes_2_1[[Code comptable]],"I1M2"),0) -> 0 | L11: =IF($C$11="Oui",SUM(Lignes_2_1[[Montant]]),0) -> 0 | M11: =IF($C$11="Oui",SUM(Lignes_2_1[[Montant Waterfall]]),0) -> 0
B12: Hors lot | C12: Oui | D12: onglet | E12: =IF($C$12="Oui",SUMIFS(Lignes_hors_lot[[Montant]],Lignes_hors_lot[[Nature]],"Main-d’œuvre"),0) -> 0 | F12: =IF($C$12="Oui",SUMIFS(Lignes_hors_lot[[Montant]],Lignes_hors_lot[[Nature]],"Fournitures"),0) -> 0 | G12: =IF($C$12="Oui",SUMIFS(Lignes_hors_lot[[Montant]],Lignes_hors_lot[[Nature]],"Sous-traitance"),0) -> 0 | H12: =IF($C$12="Oui",SUMIFS(Lignes_hors_lot[[Montant]],Lignes_hors_lot[[Nature]],"Provisions pour risques"),0) -> 0 | I12: =IF($C$12="Oui",SUMIFS(Lignes_hors_lot[[Heures totales]],Lignes_hors_lot[[Code comptable]],"I810"),0) -> 0 | J12: =IF($C$12="Oui",SUMIFS(Lignes_hors_lot[[Heures totales]],Lignes_hors_lot[[Code comptable]],"I329"),0) -> 0 | K12: =IF($C$12="Oui",SUMIFS(Lignes_hors_lot[[Heures totales]],Lignes_hors_lot[[Code comptable]],"I1M2"),0) -> 0 | L12: =IF($C$12="Oui",SUM(Lignes_hors_lot[[Montant]]),0) -> 0 | M12: =IF($C$12="Oui",SUM(Lignes_hors_lot[[Montant Waterfall]]),0) -> 0
B13: Total | E13: =SUMIFS(E6:E12,$D$6:$D$12,"onglet") -> 0 | F13: =SUMIFS(F6:F12,$D$6:$D$12,"onglet") -> 0 | G13: =SUMIFS(G6:G12,$D$6:$D$12,"onglet") -> 0 | H13: =SUMIFS(H6:H12,$D$6:$D$12,"onglet") -> 0 | I13: =SUMIFS(I6:I12,$D$6:$D$12,"onglet") -> 0 | J13: =SUMIFS(J6:J12,$D$6:$D$12,"onglet") -> 0 | K13: =SUMIFS(K6:K12,$D$6:$D$12,"onglet") -> 0 | L13: =SUMIFS(L6:L12,$D$6:$D$12,"onglet") -> 0 | M13: =SUMIFS(M6:M12,$D$6:$D$12,"onglet") -> 0

Sheet 1.1 Centrale et logiciel
A1: Tâche | B1: Description de la tâche | C1: Rôle ou catégorie | D1: Désignation | E1: Quantité | F1: Heures | G1: Débours unitaire | H1: Délai de paiement (j) | I1: Sous-projet | J1: Nature | K1: Code comptable | L1: Service | M1: Taux horaire | N1: Heures totales | O1: Main-d’œuvre | P1: Débours | Q1: Montant | R1: Montant Waterfall | S1: ID ligne | T1: Type
A2: 1.1.1 Management | B2: =IF(Lignes_1_1[[#This Row],[Tâche]]="","",IFERROR(INDEX(Taches[[Description]],MATCH(Lignes_1_1[[#This Row],[Tâche]],Taches[[Entrée]],0)),"")) -> 0 | C2: Responsable d’affaire A1 (RA-A1) | E2: 5 | F2: 7.4 | H2: 0 | I2: SP-PRE | J2: =IF(Lignes_1_1[[#This Row],[Rôle ou catégorie]]="","",IFERROR(INDEX(Referentiel[[Nature]],MATCH(Lignes_1_1[[#This Row],[Rôle ou catégorie]],Referentiel[[Entrée]],0)),"?")) -> 0 | K2: =IF(Lignes_1_1[[#This Row],[Rôle ou catégorie]]="","",IFERROR(INDEX(Referentiel[[Code comptable]],MATCH(Lignes_1_1[[#This Row],[Rôle ou catégorie]],Referentiel[[Entrée]],0)),"?")) -> 0 | L2: =IF(Lignes_1_1[[#This Row],[Rôle ou catégorie]]="","",IFERROR(INDEX(Referentiel[[Service]],MATCH(Lignes_1_1[[#This Row],[Rôle ou catégorie]],Referentiel[[Entrée]],0)),"?")&"") -> 0 | M2: =IF(Lignes_1_1[[#This Row],[Rôle ou catégorie]]="","",IFERROR(INDEX(Referentiel[[Taux horaire]],MATCH(Lignes_1_1[[#This Row],[Rôle ou catégorie]],Referentiel[[Entrée]],0)),"?")) -> 0 | N2: =IF(Lignes_1_1[[#This Row],[Rôle ou catégorie]]="","",IF(Lignes_1_1[[#This Row],[Type]]="Main-d’œuvre",Lignes_1_1[[#This Row],[Quantité]]*Lignes_1_1[[#This Row],[Heures]],0)) -> 0 | O2: =IF(Lignes_1_1[[#This Row],[Rôle ou catégorie]]="","",IF(Lignes_1_1[[#This Row],[Type]]="Main-d’œuvre",Lignes_1_1[[#This Row],[Quantité]]*Lignes_1_1[[#This Row],[Heures]]*Lignes_1_1[[#This Row],[Taux horaire]],0)) -> 0 | P2: =IF(Lignes_1_1[[#This Row],[Rôle ou catégorie]]="","",IF(OR(Lignes_1_1[[#This Row],[Type]]="Hors main-d’œuvre",Lignes_1_1[[#This Row],[Type]]="Provision"),Lignes_1_1[[#This Row],[Quantité]]*Lignes_1_1[[#This Row],[Débours unitaire]],0)) -> 0 | Q2: =IF(Lignes_1_1[[#This Row],[Rôle ou catégorie]]="","",Lignes_1_1[[#This Row],[Main-d’œuvre]]+Lignes_1_1[[#This Row],[Débours]]) -> 0 | R2: 3700 | S2: l-0101 | T2: =IF(Lignes_1_1[[#This Row],[Rôle ou catégorie]]="","",IFERROR(INDEX(Referentiel[[Type de nature]],MATCH(Lignes_1_1[[#This Row],[Rôle ou catégorie]],Referentiel[[Entrée]],0)),"?")) -> 0
A3: 1.1.2 Développement du logiciel | B3: =IF(Lignes_1_1[[#This Row],[Tâche]]="","",IFERROR(INDEX(Taches[[Description]],MATCH(Lignes_1_1[[#This Row],[Tâche]],Taches[[Entrée]],0)),"")) -> 0 | C3: Architecte logiciel (ARCH-LOG) | E3: 20 | F3: 7.4 | H3: 0 | I3: SP-PRE | J3: =IF(Lignes_1_1[[#This Row],[Rôle ou catégorie]]="","",IFERROR(INDEX(Referentiel[[Nature]],MATCH(Lignes_1_1[[#This Row],[Rôle ou catégorie]],Referentiel[[Entrée]],0)),"?")) -> 0 | K3: =IF(Lignes_1_1[[#This Row],[Rôle ou catégorie]]="","",IFERROR(INDEX(Referentiel[[Code comptable]],MATCH(Lignes_1_1[[#This Row],[Rôle ou catégorie]],Referentiel[[Entrée]],0)),"?")) -> 0 | L3: =IF(Lignes_1_1[[#This Row],[Rôle ou catégorie]]="","",IFERROR(INDEX(Referentiel[[Service]],MATCH(Lignes_1_1[[#This Row],[Rôle ou catégorie]],Referentiel[[Entrée]],0)),"?")&"") -> 0 | M3: =IF(Lignes_1_1[[#This Row],[Rôle ou catégorie]]="","",IFERROR(INDEX(Referentiel[[Taux horaire]],MATCH(Lignes_1_1[[#This Row],[Rôle ou catégorie]],Referentiel[[Entrée]],0)),"?")) -> 0 | N3: =IF(Lignes_1_1[[#This Row],[Rôle ou catégorie]]="","",IF(Lignes_1_1[[#This Row],[Type]]="Main-d’œuvre",Lignes_1_1[[#This Row],[Quantité]]*Lignes_1_1[[#This Row],[Heures]],0)) -> 0 | O3: =IF(Lignes_1_1[[#This Row],[Rôle ou catégorie]]="","",IF(Lignes_1_1[[#This Row],[Type]]="Main-d’œuvre",Lignes_1_1[[#This Row],[Quantité]]*Lignes_1_1[[#This Row],[Heures]]*Lignes_1_1[[#This Row],[Taux horaire]],0)) -> 0 | P3: =IF(Lignes_1_1[[#This Row],[Rôle ou catégorie]]="","",IF(OR(Lignes_1_1[[#This Row],[Type]]="Hors main-d’œuvre",Lignes_1_1[[#This Row],[Type]]="Provision"),Lignes_1_1[[#This Row],[Quantité]]*Lignes_1_1[[#This Row],[Débours unitaire]],0)) -> 0 | Q3: =IF(Lignes_1_1[[#This Row],[Rôle ou catégorie]]="","",Lignes_1_1[[#This Row],[Main-d’œuvre]]+Lignes_1_1[[#This Row],[Débours]]) -> 0 | R3: 11840 | S3: l-0102 | T3: =IF(Lignes_1_1[[#This Row],[Rôle ou catégorie]]="","",IFERROR(INDEX(Referentiel[[Type de nature]],MATCH(Lignes_1_1[[#This Row],[Rôle ou catégorie]],Referentiel[[Entrée]],0)),"?")) -> 0
A4: 1.1.2 Développement du logiciel | B4: =IF(Lignes_1_1[[#This Row],[Tâche]]="","",IFERROR(INDEX(Taches[[Description]],MATCH(Lignes_1_1[[#This Row],[Tâche]],Taches[[Entrée]],0)),"")) -> 0 | C4: Développeur (DEV) | E4: 60 | F4: 7.4 | H4: 0 | I4: SP-PRE | J4: =IF(Lignes_1_1[[#This Row],[Rôle ou catégorie]]="","",IFERROR(INDEX(Referentiel[[Nature]],MATCH(Lignes_1_1[[#This Row],[Rôle ou catégorie]],Referentiel[[Entrée]],0)),"?")) -> 0 | K4: =IF(Lignes_1_1[[#This Row],[Rôle ou catégorie]]="","",IFERROR(INDEX(Referentiel[[Code comptable]],MATCH(Lignes_1_1[[#This Row],[Rôle ou catégorie]],Referentiel[[Entrée]],0)),"?")) -> 0 | L4: =IF(Lignes_1_1[[#This Row],[Rôle ou catégorie]]="","",IFERROR(INDEX(Referentiel[[Service]],MATCH(Lignes_1_1[[#This Row],[Rôle ou catégorie]],Referentiel[[Entrée]],0)),"?")&"") -> 0 | M4: =IF(Lignes_1_1[[#This Row],[Rôle ou catégorie]]="","",IFERROR(INDEX(Referentiel[[Taux horaire]],MATCH(Lignes_1_1[[#This Row],[Rôle ou catégorie]],Referentiel[[Entrée]],0)),"?")) -> 0 | N4: =IF(Lignes_1_1[[#This Row],[Rôle ou catégorie]]="","",IF(Lignes_1_1[[#This Row],[Type]]="Main-d’œuvre",Lignes_1_1[[#This Row],[Quantité]]*Lignes_1_1[[#This Row],[Heures]],0)) -> 0 | O4: =IF(Lignes_1_1[[#This Row],[Rôle ou catégorie]]="","",IF(Lignes_1_1[[#This Row],[Type]]="Main-d’œuvre",Lignes_1_1[[#This Row],[Quantité]]*Lignes_1_1[[#This Row],[Heures]]*Lignes_1_1[[#This Row],[Taux horaire]],0)) -> 0 | P4: =IF(Lignes_1_1[[#This Row],[Rôle ou catégorie]]="","",IF(OR(Lignes_1_1[[#This Row],[Type]]="Hors main-d’œuvre",Lignes_1_1[[#This Row],[Type]]="Provision"),Lignes_1_1[[#This Row],[Quantité]]*Lignes_1_1[[#This Row],[Débours unitaire]],0)) -> 0 | Q4: =IF(Lignes_1_1[[#This Row],[Rôle ou catégorie]]="","",Lignes_1_1[[#This Row],[Main-d’œuvre]]+Lignes_1_1[[#This Row],[Débours]]) -> 0 | R4: 26640 | S4: l-0103 | T4: =IF(Lignes_1_1[[#This Row],[Rôle ou catégorie]]="","",IFERROR(INDEX(Referentiel[[Type de nature]],MATCH(Lignes_1_1[[#This Row],[Rôle ou catégorie]],Referentiel[[Entrée]],0)),"?")) -> 0
A5: 1.1.3 Carte d’interface | B5: =IF(Lignes_1_1[[#This Row],[Tâche]]="","",IFERROR(INDEX(Taches[[Description]],MATCH(Lignes_1_1[[#This Row],[Tâche]],Taches[[Entrée]],0)),"")) -> 0 | C5: Ingénieur carte (ING-CARTE) | E5: 15 | F5: 7.4 | H5: 0 | I5: SP-PRE | J5: =IF(Lignes_1_1[[#This Row],[Rôle ou catégorie]]="","",IFERROR(INDEX(Referentiel[[Nature]],MATCH(Lignes_1_1[[#This Row],[Rôle ou catégorie]],Referentiel[[Entrée]],0)),"?")) -> 0 | K5: =IF(Lignes_1_1[[#This Row],[Rôle ou catégorie]]="","",IFERROR(INDEX(Referentiel[[Code comptable]],MATCH(Lignes_1_1[[#This Row],[Rôle ou catégorie]],Referentiel[[Entrée]],0)),"?")) -> 0 | L5: =IF(Lignes_1_1[[#This Row],[Rôle ou catégorie]]="","",IFERROR(INDEX(Referentiel[[Service]],MATCH(Lignes_1_1[[#This Row],[Rôle ou catégorie]],Referentiel[[Entrée]],0)),"?")&"") -> 0 | M5: =IF(Lignes_1_1[[#This Row],[Rôle ou catégorie]]="","",IFERROR(INDEX(Referentiel[[Taux horaire]],MATCH(Lignes_1_1[[#This Row],[Rôle ou catégorie]],Referentiel[[Entrée]],0)),"?")) -> 0 | N5: =IF(Lignes_1_1[[#This Row],[Rôle ou catégorie]]="","",IF(Lignes_1_1[[#This Row],[Type]]="Main-d’œuvre",Lignes_1_1[[#This Row],[Quantité]]*Lignes_1_1[[#This Row],[Heures]],0)) -> 0 | O5: =IF(Lignes_1_1[[#This Row],[Rôle ou catégorie]]="","",IF(Lignes_1_1[[#This Row],[Type]]="Main-d’œuvre",Lignes_1_1[[#This Row],[Quantité]]*Lignes_1_1[[#This Row],[Heures]]*Lignes_1_1[[#This Row],[Taux horaire]],0)) -> 0 | P5: =IF(Lignes_1_1[[#This Row],[Rôle ou catégorie]]="","",IF(OR(Lignes_1_1[[#This Row],[Type]]="Hors main-d’œuvre",Lignes_1_1[[#This Row],[Type]]="Provision"),Lignes_1_1[[#This Row],[Quantité]]*Lignes_1_1[[#This Row],[Débours unitaire]],0)) -> 0 | Q5: =IF(Lignes_1_1[[#This Row],[Rôle ou catégorie]]="","",Lignes_1_1[[#This Row],[Main-d’œuvre]]+Lignes_1_1[[#This Row],[Débours]]) -> 0 | R5: 6660 | S5: l-0104 | T5: =IF(Lignes_1_1[[#This Row],[Rôle ou catégorie]]="","",IFERROR(INDEX(Referentiel[[Type de nature]],MATCH(Lignes_1_1[[#This Row],[Rôle ou catégorie]],Referentiel[[Entrée]],0)),"?")) -> 0
A6: 1.1.3 Carte d’interface | B6: =IF(Lignes_1_1[[#This Row],[Tâche]]="","",IFERROR(INDEX(Taches[[Description]],MATCH(Lignes_1_1[[#This Row],[Tâche]],Taches[[Entrée]],0)),"")) -> 0 | C6: Anti-intrusion (fo-AINT) | D6: Détecteurs | E6: 5 | G6: 20 | H6: 30 | I6: SP-MAT | J6: =IF(Lignes_1_1[[#This Row],[Rôle ou catégorie]]="","",IFERROR(INDEX(Referentiel[[Nature]],MATCH(Lignes_1_1[[#This Row],[Rôle ou catégorie]],Referentiel[[Entrée]],0)),"?")) -> 0 | K6: =IF(Lignes_1_1[[#This Row],[Rôle ou catégorie]]="","",IFERROR(INDEX(Referentiel[[Code comptable]],MATCH(Lignes_1_1[[#This Row],[Rôle ou catégorie]],Referentiel[[Entrée]],0)),"?")) -> 0 | L6: =IF(Lignes_1_1[[#This Row],[Rôle ou catégorie]]="","",IFERROR(INDEX(Referentiel[[Service]],MATCH(Lignes_1_1[[#This Row],[Rôle ou catégorie]],Referentiel[[Entrée]],0)),"?")&"") -> 0 | M6: =IF(Lignes_1_1[[#This Row],[Rôle ou catégorie]]="","",IFERROR(INDEX(Referentiel[[Taux horaire]],MATCH(Lignes_1_1[[#This Row],[Rôle ou catégorie]],Referentiel[[Entrée]],0)),"?")) -> 0 | N6: =IF(Lignes_1_1[[#This Row],[Rôle ou catégorie]]="","",IF(Lignes_1_1[[#This Row],[Type]]="Main-d’œuvre",Lignes_1_1[[#This Row],[Quantité]]*Lignes_1_1[[#This Row],[Heures]],0)) -> 0 | O6: =IF(Lignes_1_1[[#This Row],[Rôle ou catégorie]]="","",IF(Lignes_1_1[[#This Row],[Type]]="Main-d’œuvre",Lignes_1_1[[#This Row],[Quantité]]*Lignes_1_1[[#This Row],[Heures]]*Lignes_1_1[[#This Row],[Taux horaire]],0)) -> 0 | P6: =IF(Lignes_1_1[[#This Row],[Rôle ou catégorie]]="","",IF(OR(Lignes_1_1[[#This Row],[Type]]="Hors main-d’œuvre",Lignes_1_1[[#This Row],[Type]]="Provision"),Lignes_1_1[[#This Row],[Quantité]]*Lignes_1_1[[#This Row],[Débours unitaire]],0)) -> 0 | Q6: =IF(Lignes_1_1[[#This Row],[Rôle ou catégorie]]="","",Lignes_1_1[[#This Row],[Main-d’œuvre]]+Lignes_1_1[[#This Row],[Débours]]) -> 0 | R6: 100 | S6: l-0105 | T6: =IF(Lignes_1_1[[#This Row],[Rôle ou catégorie]]="","",IFERROR(INDEX(Referentiel[[Type de nature]],MATCH(Lignes_1_1[[#This Row],[Rôle ou catégorie]],Referentiel[[Entrée]],0)),"?")) -> 0
B7: =IF(Lignes_1_1[[#This Row],[Tâche]]="","",IFERROR(INDEX(Taches[[Description]],MATCH(Lignes_1_1[[#This Row],[Tâche]],Taches[[Entrée]],0)),"")) -> 0 | J7: =IF(Lignes_1_1[[#This Row],[Rôle ou catégorie]]="","",IFERROR(INDEX(Referentiel[[Nature]],MATCH(Lignes_1_1[[#This Row],[Rôle ou catégorie]],Referentiel[[Entrée]],0)),"?")) -> 0 | K7: =IF(Lignes_1_1[[#This Row],[Rôle ou catégorie]]="","",IFERROR(INDEX(Referentiel[[Code comptable]],MATCH(Lignes_1_1[[#This Row],[Rôle ou catégorie]],Referentiel[[Entrée]],0)),"?")) -> 0 | L7: =IF(Lignes_1_1[[#This Row],[Rôle ou catégorie]]="","",IFERROR(INDEX(Referentiel[[Service]],MATCH(Lignes_1_1[[#This Row],[Rôle ou catégorie]],Referentiel[[Entrée]],0)),"?")&"") -> 0 | M7: =IF(Lignes_1_1[[#This Row],[Rôle ou catégorie]]="","",IFERROR(INDEX(Referentiel[[Taux horaire]],MATCH(Lignes_1_1[[#This Row],[Rôle ou catégorie]],Referentiel[[Entrée]],0)),"?")) -> 0 | N7: =IF(Lignes_1_1[[#This Row],[Rôle ou catégorie]]="","",IF(Lignes_1_1[[#This Row],[Type]]="Main-d’œuvre",Lignes_1_1[[#This Row],[Quantité]]*Lignes_1_1[[#This Row],[Heures]],0)) -> 0 | O7: =IF(Lignes_1_1[[#This Row],[Rôle ou catégorie]]="","",IF(Lignes_1_1[[#This Row],[Type]]="Main-d’œuvre",Lignes_1_1[[#This Row],[Quantité]]*Lignes_1_1[[#This Row],[Heures]]*Lignes_1_1[[#This Row],[Taux horaire]],0)) -> 0 | P7: =IF(Lignes_1_1[[#This Row],[Rôle ou catégorie]]="","",IF(OR(Lignes_1_1[[#This Row],[Type]]="Hors main-d’œuvre",Lignes_1_1[[#This Row],[Type]]="Provision"),Lignes_1_1[[#This Row],[Quantité]]*Lignes_1_1[[#This Row],[Débours unitaire]],0)) -> 0 | Q7: =IF(Lignes_1_1[[#This Row],[Rôle ou catégorie]]="","",Lignes_1_1[[#This Row],[Main-d’œuvre]]+Lignes_1_1[[#This Row],[Débours]]) -> 0 | T7: =IF(Lignes_1_1[[#This Row],[Rôle ou catégorie]]="","",IFERROR(INDEX(Referentiel[[Type de nature]],MATCH(Lignes_1_1[[#This Row],[Rôle ou catégorie]],Referentiel[[Entrée]],0)),"?")) -> 0
B8: =IF(Lignes_1_1[[#This Row],[Tâche]]="","",IFERROR(INDEX(Taches[[Description]],MATCH(Lignes_1_1[[#This Row],[Tâche]],Taches[[Entrée]],0)),"")) -> 0 | J8: =IF(Lignes_1_1[[#This Row],[Rôle ou catégorie]]="","",IFERROR(INDEX(Referentiel[[Nature]],MATCH(Lignes_1_1[[#This Row],[Rôle ou catégorie]],Referentiel[[Entrée]],0)),"?")) -> 0 | K8: =IF(Lignes_1_1[[#This Row],[Rôle ou catégorie]]="","",IFERROR(INDEX(Referentiel[[Code comptable]],MATCH(Lignes_1_1[[#This Row],[Rôle ou catégorie]],Referentiel[[Entrée]],0)),"?")) -> 0 | L8: =IF(Lignes_1_1[[#This Row],[Rôle ou catégorie]]="","",IFERROR(INDEX(Referentiel[[Service]],MATCH(Lignes_1_1[[#This Row],[Rôle ou catégorie]],Referentiel[[Entrée]],0)),"?")&"") -> 0 | M8: =IF(Lignes_1_1[[#This Row],[Rôle ou catégorie]]="","",IFERROR(INDEX(Referentiel[[Taux horaire]],MATCH(Lignes_1_1[[#This Row],[Rôle ou catégorie]],Referentiel[[Entrée]],0)),"?")) -> 0 | N8: =IF(Lignes_1_1[[#This Row],[Rôle ou catégorie]]="","",IF(Lignes_1_1[[#This Row],[Type]]="Main-d’œuvre",Lignes_1_1[[#This Row],[Quantité]]*Lignes_1_1[[#This Row],[Heures]],0)) -> 0 | O8: =IF(Lignes_1_1[[#This Row],[Rôle ou catégorie]]="","",IF(Lignes_1_1[[#This Row],[Type]]="Main-d’œuvre",Lignes_1_1[[#This Row],[Quantité]]*Lignes_1_1[[#This Row],[Heures]]*Lignes_1_1[[#This Row],[Taux horaire]],0)) -> 0 | P8: =IF(Lignes_1_1[[#This Row],[Rôle ou catégorie]]="","",IF(OR(Lignes_1_1[[#This Row],[Type]]="Hors main-d’œuvre",Lignes_1_1[[#This Row],[Type]]="Provision"),Lignes_1_1[[#This Row],[Quantité]]*Lignes_1_1[[#This Row],[Débours unitaire]],0)) -> 0 | Q8: =IF(Lignes_1_1[[#This Row],[Rôle ou catégorie]]="","",Lignes_1_1[[#This Row],[Main-d’œuvre]]+Lignes_1_1[[#This Row],[Débours]]) -> 0 | T8: =IF(Lignes_1_1[[#This Row],[Rôle ou catégorie]]="","",IFERROR(INDEX(Referentiel[[Type de nature]],MATCH(Lignes_1_1[[#This Row],[Rôle ou catégorie]],Referentiel[[Entrée]],0)),"?")) -> 0
B9: =IF(Lignes_1_1[[#This Row],[Tâche]]="","",IFERROR(INDEX(Taches[[Description]],MATCH(Lignes_1_1[[#This Row],[Tâche]],Taches[[Entrée]],0)),"")) -> 0 | J9: =IF(Lignes_1_1[[#This Row],[Rôle ou catégorie]]="","",IFERROR(INDEX(Referentiel[[Nature]],MATCH(Lignes_1_1[[#This Row],[Rôle ou catégorie]],Referentiel[[Entrée]],0)),"?")) -> 0 | K9: =IF(Lignes_1_1[[#This Row],[Rôle ou catégorie]]="","",IFERROR(INDEX(Referentiel[[Code comptable]],MATCH(Lignes_1_1[[#This Row],[Rôle ou catégorie]],Referentiel[[Entrée]],0)),"?")) -> 0 | L9: =IF(Lignes_1_1[[#This Row],[Rôle ou catégorie]]="","",IFERROR(INDEX(Referentiel[[Service]],MATCH(Lignes_1_1[[#This Row],[Rôle ou catégorie]],Referentiel[[Entrée]],0)),"?")&"") -> 0 | M9: =IF(Lignes_1_1[[#This Row],[Rôle ou catégorie]]="","",IFERROR(INDEX(Referentiel[[Taux horaire]],MATCH(Lignes_1_1[[#This Row],[Rôle ou catégorie]],Referentiel[[Entrée]],0)),"?")) -> 0 | N9: =IF(Lignes_1_1[[#This Row],[Rôle ou catégorie]]="","",IF(Lignes_1_1[[#This Row],[Type]]="Main-d’œuvre",Lignes_1_1[[#This Row],[Quantité]]*Lignes_1_1[[#This Row],[Heures]],0)) -> 0 | O9: =IF(Lignes_1_1[[#This Row],[Rôle ou catégorie]]="","",IF(Lignes_1_1[[#This Row],[Type]]="Main-d’œuvre",Lignes_1_1[[#This Row],[Quantité]]*Lignes_1_1[[#This Row],[Heures]]*Lignes_1_1[[#This Row],[Taux horaire]],0)) -> 0 | P9: =IF(Lignes_1_1[[#This Row],[Rôle ou catégorie]]="","",IF(OR(Lignes_1_1[[#This Row],[Type]]="Hors main-d’œuvre",Lignes_1_1[[#This Row],[Type]]="Provision"),Lignes_1_1[[#This Row],[Quantité]]*Lignes_1_1[[#This Row],[Débours unitaire]],0)) -> 0 | Q9: =IF(Lignes_1_1[[#This Row],[Rôle ou catégorie]]="","",Lignes_1_1[[#This Row],[Main-d’œuvre]]+Lignes_1_1[[#This Row],[Débours]]) -> 0 | T9: =IF(Lignes_1_1[[#This Row],[Rôle ou catégorie]]="","",IFERROR(INDEX(Referentiel[[Type de nature]],MATCH(Lignes_1_1[[#This Row],[Rôle ou catégorie]],Referentiel[[Entrée]],0)),"?")) -> 0
B10: =IF(Lignes_1_1[[#This Row],[Tâche]]="","",IFERROR(INDEX(Taches[[Description]],MATCH(Lignes_1_1[[#This Row],[Tâche]],Taches[[Entrée]],0)),"")) -> 0 | J10: =IF(Lignes_1_1[[#This Row],[Rôle ou catégorie]]="","",IFERROR(INDEX(Referentiel[[Nature]],MATCH(Lignes_1_1[[#This Row],[Rôle ou catégorie]],Referentiel[[Entrée]],0)),"?")) -> 0 | K10: =IF(Lignes_1_1[[#This Row],[Rôle ou catégorie]]="","",IFERROR(INDEX(Referentiel[[Code comptable]],MATCH(Lignes_1_1[[#This Row],[Rôle ou catégorie]],Referentiel[[Entrée]],0)),"?")) -> 0 | L10: =IF(Lignes_1_1[[#This Row],[Rôle ou catégorie]]="","",IFERROR(INDEX(Referentiel[[Service]],MATCH(Lignes_1_1[[#This Row],[Rôle ou catégorie]],Referentiel[[Entrée]],0)),"?")&"") -> 0 | M10: =IF(Lignes_1_1[[#This Row],[Rôle ou catégorie]]="","",IFERROR(INDEX(Referentiel[[Taux horaire]],MATCH(Lignes_1_1[[#This Row],[Rôle ou catégorie]],Referentiel[[Entrée]],0)),"?")) -> 0 | N10: =IF(Lignes_1_1[[#This Row],[Rôle ou catégorie]]="","",IF(Lignes_1_1[[#This Row],[Type]]="Main-d’œuvre",Lignes_1_1[[#This Row],[Quantité]]*Lignes_1_1[[#This Row],[Heures]],0)) -> 0 | O10: =IF(Lignes_1_1[[#This Row],[Rôle ou catégorie]]="","",IF(Lignes_1_1[[#This Row],[Type]]="Main-d’œuvre",Lignes_1_1[[#This Row],[Quantité]]*Lignes_1_1[[#This Row],[Heures]]*Lignes_1_1[[#This Row],[Taux horaire]],0)) -> 0 | P10: =IF(Lignes_1_1[[#This Row],[Rôle ou catégorie]]="","",IF(OR(Lignes_1_1[[#This Row],[Type]]="Hors main-d’œuvre",Lignes_1_1[[#This Row],[Type]]="Provision"),Lignes_1_1[[#This Row],[Quantité]]*Lignes_1_1[[#This Row],[Débours unitaire]],0)) -> 0 | Q10: =IF(Lignes_1_1[[#This Row],[Rôle ou catégorie]]="","",Lignes_1_1[[#This Row],[Main-d’œuvre]]+Lignes_1_1[[#This Row],[Débours]]) -> 0 | T10: =IF(Lignes_1_1[[#This Row],[Rôle ou catégorie]]="","",IFERROR(INDEX(Referentiel[[Type de nature]],MATCH(Lignes_1_1[[#This Row],[Rôle ou catégorie]],Referentiel[[Entrée]],0)),"?")) -> 0
B11: =IF(Lignes_1_1[[#This Row],[Tâche]]="","",IFERROR(INDEX(Taches[[Description]],MATCH(Lignes_1_1[[#This Row],[Tâche]],Taches[[Entrée]],0)),"")) -> 0 | J11: =IF(Lignes_1_1[[#This Row],[Rôle ou catégorie]]="","",IFERROR(INDEX(Referentiel[[Nature]],MATCH(Lignes_1_1[[#This Row],[Rôle ou catégorie]],Referentiel[[Entrée]],0)),"?")) -> 0 | K11: =IF(Lignes_1_1[[#This Row],[Rôle ou catégorie]]="","",IFERROR(INDEX(Referentiel[[Code comptable]],MATCH(Lignes_1_1[[#This Row],[Rôle ou catégorie]],Referentiel[[Entrée]],0)),"?")) -> 0 | L11: =IF(Lignes_1_1[[#This Row],[Rôle ou catégorie]]="","",IFERROR(INDEX(Referentiel[[Service]],MATCH(Lignes_1_1[[#This Row],[Rôle ou catégorie]],Referentiel[[Entrée]],0)),"?")&"") -> 0 | M11: =IF(Lignes_1_1[[#This Row],[Rôle ou catégorie]]="","",IFERROR(INDEX(Referentiel[[Taux horaire]],MATCH(Lignes_1_1[[#This Row],[Rôle ou catégorie]],Referentiel[[Entrée]],0)),"?")) -> 0 | N11: =IF(Lignes_1_1[[#This Row],[Rôle ou catégorie]]="","",IF(Lignes_1_1[[#This Row],[Type]]="Main-d’œuvre",Lignes_1_1[[#This Row],[Quantité]]*Lignes_1_1[[#This Row],[Heures]],0)) -> 0 | O11: =IF(Lignes_1_1[[#This Row],[Rôle ou catégorie]]="","",IF(Lignes_1_1[[#This Row],[Type]]="Main-d’œuvre",Lignes_1_1[[#This Row],[Quantité]]*Lignes_1_1[[#This Row],[Heures]]*Lignes_1_1[[#This Row],[Taux horaire]],0)) -> 0 | P11: =IF(Lignes_1_1[[#This Row],[Rôle ou catégorie]]="","",IF(OR(Lignes_1_1[[#This Row],[Type]]="Hors main-d’œuvre",Lignes_1_1[[#This Row],[Type]]="Provision"),Lignes_1_1[[#This Row],[Quantité]]*Lignes_1_1[[#This Row],[Débours unitaire]],0)) -> 0 | Q11: =IF(Lignes_1_1[[#This Row],[Rôle ou catégorie]]="","",Lignes_1_1[[#This Row],[Main-d’œuvre]]+Lignes_1_1[[#This Row],[Débours]]) -> 0 | T11: =IF(Lignes_1_1[[#This Row],[Rôle ou catégorie]]="","",IFERROR(INDEX(Referentiel[[Type de nature]],MATCH(Lignes_1_1[[#This Row],[Rôle ou catégorie]],Referentiel[[Entrée]],0)),"?")) -> 0
B12: =IF(Lignes_1_1[[#This Row],[Tâche]]="","",IFERROR(INDEX(Taches[[Description]],MATCH(Lignes_1_1[[#This Row],[Tâche]],Taches[[Entrée]],0)),"")) -> 0 | J12: =IF(Lignes_1_1[[#This Row],[Rôle ou catégorie]]="","",IFERROR(INDEX(Referentiel[[Nature]],MATCH(Lignes_1_1[[#This Row],[Rôle ou catégorie]],Referentiel[[Entrée]],0)),"?")) -> 0 | K12: =IF(Lignes_1_1[[#This Row],[Rôle ou catégorie]]="","",IFERROR(INDEX(Referentiel[[Code comptable]],MATCH(Lignes_1_1[[#This Row],[Rôle ou catégorie]],Referentiel[[Entrée]],0)),"?")) -> 0 | L12: =IF(Lignes_1_1[[#This Row],[Rôle ou catégorie]]="","",IFERROR(INDEX(Referentiel[[Service]],MATCH(Lignes_1_1[[#This Row],[Rôle ou catégorie]],Referentiel[[Entrée]],0)),"?")&"") -> 0 | M12: =IF(Lignes_1_1[[#This Row],[Rôle ou catégorie]]="","",IFERROR(INDEX(Referentiel[[Taux horaire]],MATCH(Lignes_1_1[[#This Row],[Rôle ou catégorie]],Referentiel[[Entrée]],0)),"?")) -> 0 | N12: =IF(Lignes_1_1[[#This Row],[Rôle ou catégorie]]="","",IF(Lignes_1_1[[#This Row],[Type]]="Main-d’œuvre",Lignes_1_1[[#This Row],[Quantité]]*Lignes_1_1[[#This Row],[Heures]],0)) -> 0 | O12: =IF(Lignes_1_1[[#This Row],[Rôle ou catégorie]]="","",IF(Lignes_1_1[[#This Row],[Type]]="Main-d’œuvre",Lignes_1_1[[#This Row],[Quantité]]*Lignes_1_1[[#This Row],[Heures]]*Lignes_1_1[[#This Row],[Taux horaire]],0)) -> 0 | P12: =IF(Lignes_1_1[[#This Row],[Rôle ou catégorie]]="","",IF(OR(Lignes_1_1[[#This Row],[Type]]="Hors main-d’œuvre",Lignes_1_1[[#This Row],[Type]]="Provision"),Lignes_1_1[[#This Row],[Quantité]]*Lignes_1_1[[#This Row],[Débours unitaire]],0)) -> 0 | Q12: =IF(Lignes_1_1[[#This Row],[Rôle ou catégorie]]="","",Lignes_1_1[[#This Row],[Main-d’œuvre]]+Lignes_1_1[[#This Row],[Débours]]) -> 0 | T12: =IF(Lignes_1_1[[#This Row],[Rôle ou catégorie]]="","",IFERROR(INDEX(Referentiel[[Type de nature]],MATCH(Lignes_1_1[[#This Row],[Rôle ou catégorie]],Referentiel[[Entrée]],0)),"?")) -> 0
B13: =IF(Lignes_1_1[[#This Row],[Tâche]]="","",IFERROR(INDEX(Taches[[Description]],MATCH(Lignes_1_1[[#This Row],[Tâche]],Taches[[Entrée]],0)),"")) -> 0 | J13: =IF(Lignes_1_1[[#This Row],[Rôle ou catégorie]]="","",IFERROR(INDEX(Referentiel[[Nature]],MATCH(Lignes_1_1[[#This Row],[Rôle ou catégorie]],Referentiel[[Entrée]],0)),"?")) -> 0 | K13: =IF(Lignes_1_1[[#This Row],[Rôle ou catégorie]]="","",IFERROR(INDEX(Referentiel[[Code comptable]],MATCH(Lignes_1_1[[#This Row],[Rôle ou catégorie]],Referentiel[[Entrée]],0)),"?")) -> 0 | L13: =IF(Lignes_1_1[[#This Row],[Rôle ou catégorie]]="","",IFERROR(INDEX(Referentiel[[Service]],MATCH(Lignes_1_1[[#This Row],[Rôle ou catégorie]],Referentiel[[Entrée]],0)),"?")&"") -> 0 | M13: =IF(Lignes_1_1[[#This Row],[Rôle ou catégorie]]="","",IFERROR(INDEX(Referentiel[[Taux horaire]],MATCH(Lignes_1_1[[#This Row],[Rôle ou catégorie]],Referentiel[[Entrée]],0)),"?")) -> 0 | N13: =IF(Lignes_1_1[[#This Row],[Rôle ou catégorie]]="","",IF(Lignes_1_1[[#This Row],[Type]]="Main-d’œuvre",Lignes_1_1[[#This Row],[Quantité]]*Lignes_1_1[[#This Row],[Heures]],0)) -> 0 | O13: =IF(Lignes_1_1[[#This Row],[Rôle ou catégorie]]="","",IF(Lignes_1_1[[#This Row],[Type]]="Main-d’œuvre",Lignes_1_1[[#This Row],[Quantité]]*Lignes_1_1[[#This Row],[Heures]]*Lignes_1_1[[#This Row],[Taux horaire]],0)) -> 0 | P13: =IF(Lignes_1_1[[#This Row],[Rôle ou catégorie]]="","",IF(OR(Lignes_1_1[[#This Row],[Type]]="Hors main-d’œuvre",Lignes_1_1[[#This Row],[Type]]="Provision"),Lignes_1_1[[#This Row],[Quantité]]*Lignes_1_1[[#This Row],[Débours unitaire]],0)) -> 0 | Q13: =IF(Lignes_1_1[[#This Row],[Rôle ou catégorie]]="","",Lignes_1_1[[#This Row],[Main-d’œuvre]]+Lignes_1_1[[#This Row],[Débours]]) -> 0 | T13: =IF(Lignes_1_1[[#This Row],[Rôle ou catégorie]]="","",IFERROR(INDEX(Referentiel[[Type de nature]],MATCH(Lignes_1_1[[#This Row],[Rôle ou catégorie]],Referentiel[[Entrée]],0)),"?")) -> 0
B14: =IF(Lignes_1_1[[#This Row],[Tâche]]="","",IFERROR(INDEX(Taches[[Description]],MATCH(Lignes_1_1[[#This Row],[Tâche]],Taches[[Entrée]],0)),"")) -> 0 | J14: =IF(Lignes_1_1[[#This Row],[Rôle ou catégorie]]="","",IFERROR(INDEX(Referentiel[[Nature]],MATCH(Lignes_1_1[[#This Row],[Rôle ou catégorie]],Referentiel[[Entrée]],0)),"?")) -> 0 | K14: =IF(Lignes_1_1[[#This Row],[Rôle ou catégorie]]="","",IFERROR(INDEX(Referentiel[[Code comptable]],MATCH(Lignes_1_1[[#This Row],[Rôle ou catégorie]],Referentiel[[Entrée]],0)),"?")) -> 0 | L14: =IF(Lignes_1_1[[#This Row],[Rôle ou catégorie]]="","",IFERROR(INDEX(Referentiel[[Service]],MATCH(Lignes_1_1[[#This Row],[Rôle ou catégorie]],Referentiel[[Entrée]],0)),"?")&"") -> 0 | M14: =IF(Lignes_1_1[[#This Row],[Rôle ou catégorie]]="","",IFERROR(INDEX(Referentiel[[Taux horaire]],MATCH(Lignes_1_1[[#This Row],[Rôle ou catégorie]],Referentiel[[Entrée]],0)),"?")) -> 0 | N14: =IF(Lignes_1_1[[#This Row],[Rôle ou catégorie]]="","",IF(Lignes_1_1[[#This Row],[Type]]="Main-d’œuvre",Lignes_1_1[[#This Row],[Quantité]]*Lignes_1_1[[#This Row],[Heures]],0)) -> 0 | O14: =IF(Lignes_1_1[[#This Row],[Rôle ou catégorie]]="","",IF(Lignes_1_1[[#This Row],[Type]]="Main-d’œuvre",Lignes_1_1[[#This Row],[Quantité]]*Lignes_1_1[[#This Row],[Heures]]*Lignes_1_1[[#This Row],[Taux horaire]],0)) -> 0 | P14: =IF(Lignes_1_1[[#This Row],[Rôle ou catégorie]]="","",IF(OR(Lignes_1_1[[#This Row],[Type]]="Hors main-d’œuvre",Lignes_1_1[[#This Row],[Type]]="Provision"),Lignes_1_1[[#This Row],[Quantité]]*Lignes_1_1[[#This Row],[Débours unitaire]],0)) -> 0 | Q14: =IF(Lignes_1_1[[#This Row],[Rôle ou catégorie]]="","",Lignes_1_1[[#This Row],[Main-d’œuvre]]+Lignes_1_1[[#This Row],[Débours]]) -> 0 | T14: =IF(Lignes_1_1[[#This Row],[Rôle ou catégorie]]="","",IFERROR(INDEX(Referentiel[[Type de nature]],MATCH(Lignes_1_1[[#This Row],[Rôle ou catégorie]],Referentiel[[Entrée]],0)),"?")) -> 0
B15: =IF(Lignes_1_1[[#This Row],[Tâche]]="","",IFERROR(INDEX(Taches[[Description]],MATCH(Lignes_1_1[[#This Row],[Tâche]],Taches[[Entrée]],0)),"")) -> 0 | J15: =IF(Lignes_1_1[[#This Row],[Rôle ou catégorie]]="","",IFERROR(INDEX(Referentiel[[Nature]],MATCH(Lignes_1_1[[#This Row],[Rôle ou catégorie]],Referentiel[[Entrée]],0)),"?")) -> 0 | K15: =IF(Lignes_1_1[[#This Row],[Rôle ou catégorie]]="","",IFERROR(INDEX(Referentiel[[Code comptable]],MATCH(Lignes_1_1[[#This Row],[Rôle ou catégorie]],Referentiel[[Entrée]],0)),"?")) -> 0 | L15: =IF(Lignes_1_1[[#This Row],[Rôle ou catégorie]]="","",IFERROR(INDEX(Referentiel[[Service]],MATCH(Lignes_1_1[[#This Row],[Rôle ou catégorie]],Referentiel[[Entrée]],0)),"?")&"") -> 0 | M15: =IF(Lignes_1_1[[#This Row],[Rôle ou catégorie]]="","",IFERROR(INDEX(Referentiel[[Taux horaire]],MATCH(Lignes_1_1[[#This Row],[Rôle ou catégorie]],Referentiel[[Entrée]],0)),"?")) -> 0 | N15: =IF(Lignes_1_1[[#This Row],[Rôle ou catégorie]]="","",IF(Lignes_1_1[[#This Row],[Type]]="Main-d’œuvre",Lignes_1_1[[#This Row],[Quantité]]*Lignes_1_1[[#This Row],[Heures]],0)) -> 0 | O15: =IF(Lignes_1_1[[#This Row],[Rôle ou catégorie]]="","",IF(Lignes_1_1[[#This Row],[Type]]="Main-d’œuvre",Lignes_1_1[[#This Row],[Quantité]]*Lignes_1_1[[#This Row],[Heures]]*Lignes_1_1[[#This Row],[Taux horaire]],0)) -> 0 | P15: =IF(Lignes_1_1[[#This Row],[Rôle ou catégorie]]="","",IF(OR(Lignes_1_1[[#This Row],[Type]]="Hors main-d’œuvre",Lignes_1_1[[#This Row],[Type]]="Provision"),Lignes_1_1[[#This Row],[Quantité]]*Lignes_1_1[[#This Row],[Débours unitaire]],0)) -> 0 | Q15: =IF(Lignes_1_1[[#This Row],[Rôle ou catégorie]]="","",Lignes_1_1[[#This Row],[Main-d’œuvre]]+Lignes_1_1[[#This Row],[Débours]]) -> 0 | T15: =IF(Lignes_1_1[[#This Row],[Rôle ou catégorie]]="","",IFERROR(INDEX(Referentiel[[Type de nature]],MATCH(Lignes_1_1[[#This Row],[Rôle ou catégorie]],Referentiel[[Entrée]],0)),"?")) -> 0
B16: =IF(Lignes_1_1[[#This Row],[Tâche]]="","",IFERROR(INDEX(Taches[[Description]],MATCH(Lignes_1_1[[#This Row],[Tâche]],Taches[[Entrée]],0)),"")) -> 0 | J16: =IF(Lignes_1_1[[#This Row],[Rôle ou catégorie]]="","",IFERROR(INDEX(Referentiel[[Nature]],MATCH(Lignes_1_1[[#This Row],[Rôle ou catégorie]],Referentiel[[Entrée]],0)),"?")) -> 0 | K16: =IF(Lignes_1_1[[#This Row],[Rôle ou catégorie]]="","",IFERROR(INDEX(Referentiel[[Code comptable]],MATCH(Lignes_1_1[[#This Row],[Rôle ou catégorie]],Referentiel[[Entrée]],0)),"?")) -> 0 | L16: =IF(Lignes_1_1[[#This Row],[Rôle ou catégorie]]="","",IFERROR(INDEX(Referentiel[[Service]],MATCH(Lignes_1_1[[#This Row],[Rôle ou catégorie]],Referentiel[[Entrée]],0)),"?")&"") -> 0 | M16: =IF(Lignes_1_1[[#This Row],[Rôle ou catégorie]]="","",IFERROR(INDEX(Referentiel[[Taux horaire]],MATCH(Lignes_1_1[[#This Row],[Rôle ou catégorie]],Referentiel[[Entrée]],0)),"?")) -> 0 | N16: =IF(Lignes_1_1[[#This Row],[Rôle ou catégorie]]="","",IF(Lignes_1_1[[#This Row],[Type]]="Main-d’œuvre",Lignes_1_1[[#This Row],[Quantité]]*Lignes_1_1[[#This Row],[Heures]],0)) -> 0 | O16: =IF(Lignes_1_1[[#This Row],[Rôle ou catégorie]]="","",IF(Lignes_1_1[[#This Row],[Type]]="Main-d’œuvre",Lignes_1_1[[#This Row],[Quantité]]*Lignes_1_1[[#This Row],[Heures]]*Lignes_1_1[[#This Row],[Taux horaire]],0)) -> 0 | P16: =IF(Lignes_1_1[[#This Row],[Rôle ou catégorie]]="","",IF(OR(Lignes_1_1[[#This Row],[Type]]="Hors main-d’œuvre",Lignes_1_1[[#This Row],[Type]]="Provision"),Lignes_1_1[[#This Row],[Quantité]]*Lignes_1_1[[#This Row],[Débours unitaire]],0)) -> 0 | Q16: =IF(Lignes_1_1[[#This Row],[Rôle ou catégorie]]="","",Lignes_1_1[[#This Row],[Main-d’œuvre]]+Lignes_1_1[[#This Row],[Débours]]) -> 0 | T16: =IF(Lignes_1_1[[#This Row],[Rôle ou catégorie]]="","",IFERROR(INDEX(Referentiel[[Type de nature]],MATCH(Lignes_1_1[[#This Row],[Rôle ou catégorie]],Referentiel[[Entrée]],0)),"?")) -> 0
B17: =IF(Lignes_1_1[[#This Row],[Tâche]]="","",IFERROR(INDEX(Taches[[Description]],MATCH(Lignes_1_1[[#This Row],[Tâche]],Taches[[Entrée]],0)),"")) -> 0 | J17: =IF(Lignes_1_1[[#This Row],[Rôle ou catégorie]]="","",IFERROR(INDEX(Referentiel[[Nature]],MATCH(Lignes_1_1[[#This Row],[Rôle ou catégorie]],Referentiel[[Entrée]],0)),"?")) -> 0 | K17: =IF(Lignes_1_1[[#This Row],[Rôle ou catégorie]]="","",IFERROR(INDEX(Referentiel[[Code comptable]],MATCH(Lignes_1_1[[#This Row],[Rôle ou catégorie]],Referentiel[[Entrée]],0)),"?")) -> 0 | L17: =IF(Lignes_1_1[[#This Row],[Rôle ou catégorie]]="","",IFERROR(INDEX(Referentiel[[Service]],MATCH(Lignes_1_1[[#This Row],[Rôle ou catégorie]],Referentiel[[Entrée]],0)),"?")&"") -> 0 | M17: =IF(Lignes_1_1[[#This Row],[Rôle ou catégorie]]="","",IFERROR(INDEX(Referentiel[[Taux horaire]],MATCH(Lignes_1_1[[#This Row],[Rôle ou catégorie]],Referentiel[[Entrée]],0)),"?")) -> 0 | N17: =IF(Lignes_1_1[[#This Row],[Rôle ou catégorie]]="","",IF(Lignes_1_1[[#This Row],[Type]]="Main-d’œuvre",Lignes_1_1[[#This Row],[Quantité]]*Lignes_1_1[[#This Row],[Heures]],0)) -> 0 | O17: =IF(Lignes_1_1[[#This Row],[Rôle ou catégorie]]="","",IF(Lignes_1_1[[#This Row],[Type]]="Main-d’œuvre",Lignes_1_1[[#This Row],[Quantité]]*Lignes_1_1[[#This Row],[Heures]]*Lignes_1_1[[#This Row],[Taux horaire]],0)) -> 0 | P17: =IF(Lignes_1_1[[#This Row],[Rôle ou catégorie]]="","",IF(OR(Lignes_1_1[[#This Row],[Type]]="Hors main-d’œuvre",Lignes_1_1[[#This Row],[Type]]="Provision"),Lignes_1_1[[#This Row],[Quantité]]*Lignes_1_1[[#This Row],[Débours unitaire]],0)) -> 0 | Q17: =IF(Lignes_1_1[[#This Row],[Rôle ou catégorie]]="","",Lignes_1_1[[#This Row],[Main-d’œuvre]]+Lignes_1_1[[#This Row],[Débours]]) -> 0 | T17: =IF(Lignes_1_1[[#This Row],[Rôle ou catégorie]]="","",IFERROR(INDEX(Referentiel[[Type de nature]],MATCH(Lignes_1_1[[#This Row],[Rôle ou catégorie]],Referentiel[[Entrée]],0)),"?")) -> 0
B18: =IF(Lignes_1_1[[#This Row],[Tâche]]="","",IFERROR(INDEX(Taches[[Description]],MATCH(Lignes_1_1[[#This Row],[Tâche]],Taches[[Entrée]],0)),"")) -> 0 | J18: =IF(Lignes_1_1[[#This Row],[Rôle ou catégorie]]="","",IFERROR(INDEX(Referentiel[[Nature]],MATCH(Lignes_1_1[[#This Row],[Rôle ou catégorie]],Referentiel[[Entrée]],0)),"?")) -> 0 | K18: =IF(Lignes_1_1[[#This Row],[Rôle ou catégorie]]="","",IFERROR(INDEX(Referentiel[[Code comptable]],MATCH(Lignes_1_1[[#This Row],[Rôle ou catégorie]],Referentiel[[Entrée]],0)),"?")) -> 0 | L18: =IF(Lignes_1_1[[#This Row],[Rôle ou catégorie]]="","",IFERROR(INDEX(Referentiel[[Service]],MATCH(Lignes_1_1[[#This Row],[Rôle ou catégorie]],Referentiel[[Entrée]],0)),"?")&"") -> 0 | M18: =IF(Lignes_1_1[[#This Row],[Rôle ou catégorie]]="","",IFERROR(INDEX(Referentiel[[Taux horaire]],MATCH(Lignes_1_1[[#This Row],[Rôle ou catégorie]],Referentiel[[Entrée]],0)),"?")) -> 0 | N18: =IF(Lignes_1_1[[#This Row],[Rôle ou catégorie]]="","",IF(Lignes_1_1[[#This Row],[Type]]="Main-d’œuvre",Lignes_1_1[[#This Row],[Quantité]]*Lignes_1_1[[#This Row],[Heures]],0)) -> 0 | O18: =IF(Lignes_1_1[[#This Row],[Rôle ou catégorie]]="","",IF(Lignes_1_1[[#This Row],[Type]]="Main-d’œuvre",Lignes_1_1[[#This Row],[Quantité]]*Lignes_1_1[[#This Row],[Heures]]*Lignes_1_1[[#This Row],[Taux horaire]],0)) -> 0 | P18: =IF(Lignes_1_1[[#This Row],[Rôle ou catégorie]]="","",IF(OR(Lignes_1_1[[#This Row],[Type]]="Hors main-d’œuvre",Lignes_1_1[[#This Row],[Type]]="Provision"),Lignes_1_1[[#This Row],[Quantité]]*Lignes_1_1[[#This Row],[Débours unitaire]],0)) -> 0 | Q18: =IF(Lignes_1_1[[#This Row],[Rôle ou catégorie]]="","",Lignes_1_1[[#This Row],[Main-d’œuvre]]+Lignes_1_1[[#This Row],[Débours]]) -> 0 | T18: =IF(Lignes_1_1[[#This Row],[Rôle ou catégorie]]="","",IFERROR(INDEX(Referentiel[[Type de nature]],MATCH(Lignes_1_1[[#This Row],[Rôle ou catégorie]],Referentiel[[Entrée]],0)),"?")) -> 0
... B36: =IF(Lignes_1_1[[#This Row],[Tâche]]="","",IFERROR(INDEX(Taches[[Description]],MATCH(Lignes_1_1[[#This Row],[Tâche]],Taches[[Entrée]],0)),"")) -> 0 | J36: =IF(Lignes_1_1[[#This Row],[Rôle ou catégorie]]="","",IFERROR(INDEX(Referentiel[[Nature]],MATCH(Lignes_1_1[[#This Row],[Rôle ou catégorie]],Referentiel[[Entrée]],0)),"?")) -> 0 | K36: =IF(Lignes_1_1[[#This Row],[Rôle ou catégorie]]="","",IFERROR(INDEX(Referentiel[[Code comptable]],MATCH(Lignes_1_1[[#This Row],[Rôle ou catégorie]],Referentiel[[Entrée]],0)),"?")) -> 0 | L36: =IF(Lignes_1_1[[#This Row],[Rôle ou catégorie]]="","",IFERROR(INDEX(Referentiel[[Service]],MATCH(Lignes_1_1[[#This Row],[Rôle ou catégorie]],Referentiel[[Entrée]],0)),"?")&"") -> 0 | M36: =IF(Lignes_1_1[[#This Row],[Rôle ou catégorie]]="","",IFERROR(INDEX(Referentiel[[Taux horaire]],MATCH(Lignes_1_1[[#This Row],[Rôle ou catégorie]],Referentiel[[Entrée]],0)),"?")) -> 0 | N36: =IF(Lignes_1_1[[#This Row],[Rôle ou catégorie]]="","",IF(Lignes_1_1[[#This Row],[Type]]="Main-d’œuvre",Lignes_1_1[[#This Row],[Quantité]]*Lignes_1_1[[#This Row],[Heures]],0)) -> 0 | O36: =IF(Lignes_1_1[[#This Row],[Rôle ou catégorie]]="","",IF(Lignes_1_1[[#This Row],[Type]]="Main-d’œuvre",Lignes_1_1[[#This Row],[Quantité]]*Lignes_1_1[[#This Row],[Heures]]*Lignes_1_1[[#This Row],[Taux horaire]],0)) -> 0 | P36: =IF(Lignes_1_1[[#This Row],[Rôle ou catégorie]]="","",IF(OR(Lignes_1_1[[#This Row],[Type]]="Hors main-d’œuvre",Lignes_1_1[[#This Row],[Type]]="Provision"),Lignes_1_1[[#This Row],[Quantité]]*Lignes_1_1[[#This Row],[Débours unitaire]],0)) -> 0 | Q36: =IF(Lignes_1_1[[#This Row],[Rôle ou catégorie]]="","",Lignes_1_1[[#This Row],[Main-d’œuvre]]+Lignes_1_1[[#This Row],[Débours]]) -> 0 | T36: =IF(Lignes_1_1[[#This Row],[Rôle ou catégorie]]="","",IFERROR(INDEX(Referentiel[[Type de nature]],MATCH(Lignes_1_1[[#This Row],[Rôle ou catégorie]],Referentiel[[Entrée]],0)),"?")) -> 0
A37: Total | N37: =SUBTOTAL(109,Lignes_1_1[[Heures totales]]) -> 0 | O37: =SUBTOTAL(109,Lignes_1_1[[Main-d’œuvre]]) -> 0 | P37: =SUBTOTAL(109,Lignes_1_1[[Débours]]) -> 0 | Q37: =SUBTOTAL(109,Lignes_1_1[[Montant]]) -> 0 | R37: =SUBTOTAL(109,Lignes_1_1[[Montant Waterfall]]) -> 0

Sheet 1.2 Lecteurs et câblage
A1: Tâche | B1: Description de la tâche | C1: Rôle ou catégorie | D1: Désignation | E1: Quantité | F1: Heures | G1: Débours unitaire | H1: Délai de paiement (j) | I1: Sous-projet | J1: Nature | K1: Code comptable | L1: Service | M1: Taux horaire | N1: Heures totales | O1: Main-d’œuvre | P1: Débours | Q1: Montant | R1: Montant Waterfall | S1: ID ligne | T1: Type
A2: 1.2.1 Approvisionnement des lecteurs | B2: =IF(Lignes_1_2[[#This Row],[Tâche]]="","",IFERROR(INDEX(Taches[[Description]],MATCH(Lignes_1_2[[#This Row],[Tâche]],Taches[[Entrée]],0)),"")) -> 0 | C2: Appareillage (fo-APPA) | D2: Lecteurs de badges | E2: 40 | G2: 180 | H2: 45 | I2: SP-MAT | J2: =IF(Lignes_1_2[[#This Row],[Rôle ou catégorie]]="","",IFERROR(INDEX(Referentiel[[Nature]],MATCH(Lignes_1_2[[#This Row],[Rôle ou catégorie]],Referentiel[[Entrée]],0)),"?")) -> 0 | K2: =IF(Lignes_1_2[[#This Row],[Rôle ou catégorie]]="","",IFERROR(INDEX(Referentiel[[Code comptable]],MATCH(Lignes_1_2[[#This Row],[Rôle ou catégorie]],Referentiel[[Entrée]],0)),"?")) -> 0 | L2: =IF(Lignes_1_2[[#This Row],[Rôle ou catégorie]]="","",IFERROR(INDEX(Referentiel[[Service]],MATCH(Lignes_1_2[[#This Row],[Rôle ou catégorie]],Referentiel[[Entrée]],0)),"?")&"") -> 0 | M2: =IF(Lignes_1_2[[#This Row],[Rôle ou catégorie]]="","",IFERROR(INDEX(Referentiel[[Taux horaire]],MATCH(Lignes_1_2[[#This Row],[Rôle ou catégorie]],Referentiel[[Entrée]],0)),"?")) -> 0 | N2: =IF(Lignes_1_2[[#This Row],[Rôle ou catégorie]]="","",IF(Lignes_1_2[[#This Row],[Type]]="Main-d’œuvre",Lignes_1_2[[#This Row],[Quantité]]*Lignes_1_2[[#This Row],[Heures]],0)) -> 0 | O2: =IF(Lignes_1_2[[#This Row],[Rôle ou catégorie]]="","",IF(Lignes_1_2[[#This Row],[Type]]="Main-d’œuvre",Lignes_1_2[[#This Row],[Quantité]]*Lignes_1_2[[#This Row],[Heures]]*Lignes_1_2[[#This Row],[Taux horaire]],0)) -> 0 | P2: =IF(Lignes_1_2[[#This Row],[Rôle ou catégorie]]="","",IF(OR(Lignes_1_2[[#This Row],[Type]]="Hors main-d’œuvre",Lignes_1_2[[#This Row],[Type]]="Provision"),Lignes_1_2[[#This Row],[Quantité]]*Lignes_1_2[[#This Row],[Débours unitaire]],0)) -> 0 | Q2: =IF(Lignes_1_2[[#This Row],[Rôle ou catégorie]]="","",Lignes_1_2[[#This Row],[Main-d’œuvre]]+Lignes_1_2[[#This Row],[Débours]]) -> 0 | R2: 7344 | S2: l-0201 | T2: =IF(Lignes_1_2[[#This Row],[Rôle ou catégorie]]="","",IFERROR(INDEX(Referentiel[[Type de nature]],MATCH(Lignes_1_2[[#This Row],[Rôle ou catégorie]],Referentiel[[Entrée]],0)),"?")) -> 0
A3: 1.2.1 Approvisionnement des lecteurs | B3: =IF(Lignes_1_2[[#This Row],[Tâche]]="","",IFERROR(INDEX(Taches[[Description]],MATCH(Lignes_1_2[[#This Row],[Tâche]],Taches[[Entrée]],0)),"")) -> 0 | C3: Provision pour risques (PRV) | D3: Provision — Retard de livraison des lecteurs | E3: 1 | G3: 1500 | J3: =IF(Lignes_1_2[[#This Row],[Rôle ou catégorie]]="","",IFERROR(INDEX(Referentiel[[Nature]],MATCH(Lignes_1_2[[#This Row],[Rôle ou catégorie]],Referentiel[[Entrée]],0)),"?")) -> 0 | K3: =IF(Lignes_1_2[[#This Row],[Rôle ou catégorie]]="","",IFERROR(INDEX(Referentiel[[Code comptable]],MATCH(Lignes_1_2[[#This Row],[Rôle ou catégorie]],Referentiel[[Entrée]],0)),"?")) -> 0 | L3: =IF(Lignes_1_2[[#This Row],[Rôle ou catégorie]]="","",IFERROR(INDEX(Referentiel[[Service]],MATCH(Lignes_1_2[[#This Row],[Rôle ou catégorie]],Referentiel[[Entrée]],0)),"?")&"") -> 0 | M3: =IF(Lignes_1_2[[#This Row],[Rôle ou catégorie]]="","",IFERROR(INDEX(Referentiel[[Taux horaire]],MATCH(Lignes_1_2[[#This Row],[Rôle ou catégorie]],Referentiel[[Entrée]],0)),"?")) -> 0 | N3: =IF(Lignes_1_2[[#This Row],[Rôle ou catégorie]]="","",IF(Lignes_1_2[[#This Row],[Type]]="Main-d’œuvre",Lignes_1_2[[#This Row],[Quantité]]*Lignes_1_2[[#This Row],[Heures]],0)) -> 0 | O3: =IF(Lignes_1_2[[#This Row],[Rôle ou catégorie]]="","",IF(Lignes_1_2[[#This Row],[Type]]="Main-d’œuvre",Lignes_1_2[[#This Row],[Quantité]]*Lignes_1_2[[#This Row],[Heures]]*Lignes_1_2[[#This Row],[Taux horaire]],0)) -> 0 | P3: =IF(Lignes_1_2[[#This Row],[Rôle ou catégorie]]="","",IF(OR(Lignes_1_2[[#This Row],[Type]]="Hors main-d’œuvre",Lignes_1_2[[#This Row],[Type]]="Provision"),Lignes_1_2[[#This Row],[Quantité]]*Lignes_1_2[[#This Row],[Débours unitaire]],0)) -> 0 | Q3: =IF(Lignes_1_2[[#This Row],[Rôle ou catégorie]]="","",Lignes_1_2[[#This Row],[Main-d’œuvre]]+Lignes_1_2[[#This Row],[Débours]]) -> 0 | R3: 1530 | S3: l-0202 | T3: =IF(Lignes_1_2[[#This Row],[Rôle ou catégorie]]="","",IFERROR(INDEX(Referentiel[[Type de nature]],MATCH(Lignes_1_2[[#This Row],[Rôle ou catégorie]],Referentiel[[Entrée]],0)),"?")) -> 0
A4: 1.2.2 Câblage | B4: =IF(Lignes_1_2[[#This Row],[Tâche]]="","",IFERROR(INDEX(Taches[[Description]],MATCH(Lignes_1_2[[#This Row],[Tâche]],Taches[[Entrée]],0)),"")) -> 0 | C4: Pose sur site (st-POSE) | E4: 1 | G4: 8500 | H4: 60 | I4: SP-PRE | J4: =IF(Lignes_1_2[[#This Row],[Rôle ou catégorie]]="","",IFERROR(INDEX(Referentiel[[Nature]],MATCH(Lignes_1_2[[#This Row],[Rôle ou catégorie]],Referentiel[[Entrée]],0)),"?")) -> 0 | K4: =IF(Lignes_1_2[[#This Row],[Rôle ou catégorie]]="","",IFERROR(INDEX(Referentiel[[Code comptable]],MATCH(Lignes_1_2[[#This Row],[Rôle ou catégorie]],Referentiel[[Entrée]],0)),"?")) -> 0 | L4: =IF(Lignes_1_2[[#This Row],[Rôle ou catégorie]]="","",IFERROR(INDEX(Referentiel[[Service]],MATCH(Lignes_1_2[[#This Row],[Rôle ou catégorie]],Referentiel[[Entrée]],0)),"?")&"") -> 0 | M4: =IF(Lignes_1_2[[#This Row],[Rôle ou catégorie]]="","",IFERROR(INDEX(Referentiel[[Taux horaire]],MATCH(Lignes_1_2[[#This Row],[Rôle ou catégorie]],Referentiel[[Entrée]],0)),"?")) -> 0 | N4: =IF(Lignes_1_2[[#This Row],[Rôle ou catégorie]]="","",IF(Lignes_1_2[[#This Row],[Type]]="Main-d’œuvre",Lignes_1_2[[#This Row],[Quantité]]*Lignes_1_2[[#This Row],[Heures]],0)) -> 0 | O4: =IF(Lignes_1_2[[#This Row],[Rôle ou catégorie]]="","",IF(Lignes_1_2[[#This Row],[Type]]="Main-d’œuvre",Lignes_1_2[[#This Row],[Quantité]]*Lignes_1_2[[#This Row],[Heures]]*Lignes_1_2[[#This Row],[Taux horaire]],0)) -> 0 | P4: =IF(Lignes_1_2[[#This Row],[Rôle ou catégorie]]="","",IF(OR(Lignes_1_2[[#This Row],[Type]]="Hors main-d’œuvre",Lignes_1_2[[#This Row],[Type]]="Provision"),Lignes_1_2[[#This Row],[Quantité]]*Lignes_1_2[[#This Row],[Débours unitaire]],0)) -> 0 | Q4: =IF(Lignes_1_2[[#This Row],[Rôle ou catégorie]]="","",Lignes_1_2[[#This Row],[Main-d’œuvre]]+Lignes_1_2[[#This Row],[Débours]]) -> 0 | R4: 8670 | S4: l-0203 | T4: =IF(Lignes_1_2[[#This Row],[Rôle ou catégorie]]="","",IFERROR(INDEX(Referentiel[[Type de nature]],MATCH(Lignes_1_2[[#This Row],[Rôle ou catégorie]],Referentiel[[Entrée]],0)),"?")) -> 0
B5: =IF(Lignes_1_2[[#This Row],[Tâche]]="","",IFERROR(INDEX(Taches[[Description]],MATCH(Lignes_1_2[[#This Row],[Tâche]],Taches[[Entrée]],0)),"")) -> 0 | J5: =IF(Lignes_1_2[[#This Row],[Rôle ou catégorie]]="","",IFERROR(INDEX(Referentiel[[Nature]],MATCH(Lignes_1_2[[#This Row],[Rôle ou catégorie]],Referentiel[[Entrée]],0)),"?")) -> 0 | K5: =IF(Lignes_1_2[[#This Row],[Rôle ou catégorie]]="","",IFERROR(INDEX(Referentiel[[Code comptable]],MATCH(Lignes_1_2[[#This Row],[Rôle ou catégorie]],Referentiel[[Entrée]],0)),"?")) -> 0 | L5: =IF(Lignes_1_2[[#This Row],[Rôle ou catégorie]]="","",IFERROR(INDEX(Referentiel[[Service]],MATCH(Lignes_1_2[[#This Row],[Rôle ou catégorie]],Referentiel[[Entrée]],0)),"?")&"") -> 0 | M5: =IF(Lignes_1_2[[#This Row],[Rôle ou catégorie]]="","",IFERROR(INDEX(Referentiel[[Taux horaire]],MATCH(Lignes_1_2[[#This Row],[Rôle ou catégorie]],Referentiel[[Entrée]],0)),"?")) -> 0 | N5: =IF(Lignes_1_2[[#This Row],[Rôle ou catégorie]]="","",IF(Lignes_1_2[[#This Row],[Type]]="Main-d’œuvre",Lignes_1_2[[#This Row],[Quantité]]*Lignes_1_2[[#This Row],[Heures]],0)) -> 0 | O5: =IF(Lignes_1_2[[#This Row],[Rôle ou catégorie]]="","",IF(Lignes_1_2[[#This Row],[Type]]="Main-d’œuvre",Lignes_1_2[[#This Row],[Quantité]]*Lignes_1_2[[#This Row],[Heures]]*Lignes_1_2[[#This Row],[Taux horaire]],0)) -> 0 | P5: =IF(Lignes_1_2[[#This Row],[Rôle ou catégorie]]="","",IF(OR(Lignes_1_2[[#This Row],[Type]]="Hors main-d’œuvre",Lignes_1_2[[#This Row],[Type]]="Provision"),Lignes_1_2[[#This Row],[Quantité]]*Lignes_1_2[[#This Row],[Débours unitaire]],0)) -> 0 | Q5: =IF(Lignes_1_2[[#This Row],[Rôle ou catégorie]]="","",Lignes_1_2[[#This Row],[Main-d’œuvre]]+Lignes_1_2[[#This Row],[Débours]]) -> 0 | T5: =IF(Lignes_1_2[[#This Row],[Rôle ou catégorie]]="","",IFERROR(INDEX(Referentiel[[Type de nature]],MATCH(Lignes_1_2[[#This Row],[Rôle ou catégorie]],Referentiel[[Entrée]],0)),"?")) -> 0
B6: =IF(Lignes_1_2[[#This Row],[Tâche]]="","",IFERROR(INDEX(Taches[[Description]],MATCH(Lignes_1_2[[#This Row],[Tâche]],Taches[[Entrée]],0)),"")) -> 0 | J6: =IF(Lignes_1_2[[#This Row],[Rôle ou catégorie]]="","",IFERROR(INDEX(Referentiel[[Nature]],MATCH(Lignes_1_2[[#This Row],[Rôle ou catégorie]],Referentiel[[Entrée]],0)),"?")) -> 0 | K6: =IF(Lignes_1_2[[#This Row],[Rôle ou catégorie]]="","",IFERROR(INDEX(Referentiel[[Code comptable]],MATCH(Lignes_1_2[[#This Row],[Rôle ou catégorie]],Referentiel[[Entrée]],0)),"?")) -> 0 | L6: =IF(Lignes_1_2[[#This Row],[Rôle ou catégorie]]="","",IFERROR(INDEX(Referentiel[[Service]],MATCH(Lignes_1_2[[#This Row],[Rôle ou catégorie]],Referentiel[[Entrée]],0)),"?")&"") -> 0 | M6: =IF(Lignes_1_2[[#This Row],[Rôle ou catégorie]]="","",IFERROR(INDEX(Referentiel[[Taux horaire]],MATCH(Lignes_1_2[[#This Row],[Rôle ou catégorie]],Referentiel[[Entrée]],0)),"?")) -> 0 | N6: =IF(Lignes_1_2[[#This Row],[Rôle ou catégorie]]="","",IF(Lignes_1_2[[#This Row],[Type]]="Main-d’œuvre",Lignes_1_2[[#This Row],[Quantité]]*Lignes_1_2[[#This Row],[Heures]],0)) -> 0 | O6: =IF(Lignes_1_2[[#This Row],[Rôle ou catégorie]]="","",IF(Lignes_1_2[[#This Row],[Type]]="Main-d’œuvre",Lignes_1_2[[#This Row],[Quantité]]*Lignes_1_2[[#This Row],[Heures]]*Lignes_1_2[[#This Row],[Taux horaire]],0)) -> 0 | P6: =IF(Lignes_1_2[[#This Row],[Rôle ou catégorie]]="","",IF(OR(Lignes_1_2[[#This Row],[Type]]="Hors main-d’œuvre",Lignes_1_2[[#This Row],[Type]]="Provision"),Lignes_1_2[[#This Row],[Quantité]]*Lignes_1_2[[#This Row],[Débours unitaire]],0)) -> 0 | Q6: =IF(Lignes_1_2[[#This Row],[Rôle ou catégorie]]="","",Lignes_1_2[[#This Row],[Main-d’œuvre]]+Lignes_1_2[[#This Row],[Débours]]) -> 0 | T6: =IF(Lignes_1_2[[#This Row],[Rôle ou catégorie]]="","",IFERROR(INDEX(Referentiel[[Type de nature]],MATCH(Lignes_1_2[[#This Row],[Rôle ou catégorie]],Referentiel[[Entrée]],0)),"?")) -> 0
B7: =IF(Lignes_1_2[[#This Row],[Tâche]]="","",IFERROR(INDEX(Taches[[Description]],MATCH(Lignes_1_2[[#This Row],[Tâche]],Taches[[Entrée]],0)),"")) -> 0 | J7: =IF(Lignes_1_2[[#This Row],[Rôle ou catégorie]]="","",IFERROR(INDEX(Referentiel[[Nature]],MATCH(Lignes_1_2[[#This Row],[Rôle ou catégorie]],Referentiel[[Entrée]],0)),"?")) -> 0 | K7: =IF(Lignes_1_2[[#This Row],[Rôle ou catégorie]]="","",IFERROR(INDEX(Referentiel[[Code comptable]],MATCH(Lignes_1_2[[#This Row],[Rôle ou catégorie]],Referentiel[[Entrée]],0)),"?")) -> 0 | L7: =IF(Lignes_1_2[[#This Row],[Rôle ou catégorie]]="","",IFERROR(INDEX(Referentiel[[Service]],MATCH(Lignes_1_2[[#This Row],[Rôle ou catégorie]],Referentiel[[Entrée]],0)),"?")&"") -> 0 | M7: =IF(Lignes_1_2[[#This Row],[Rôle ou catégorie]]="","",IFERROR(INDEX(Referentiel[[Taux horaire]],MATCH(Lignes_1_2[[#This Row],[Rôle ou catégorie]],Referentiel[[Entrée]],0)),"?")) -> 0 | N7: =IF(Lignes_1_2[[#This Row],[Rôle ou catégorie]]="","",IF(Lignes_1_2[[#This Row],[Type]]="Main-d’œuvre",Lignes_1_2[[#This Row],[Quantité]]*Lignes_1_2[[#This Row],[Heures]],0)) -> 0 | O7: =IF(Lignes_1_2[[#This Row],[Rôle ou catégorie]]="","",IF(Lignes_1_2[[#This Row],[Type]]="Main-d’œuvre",Lignes_1_2[[#This Row],[Quantité]]*Lignes_1_2[[#This Row],[Heures]]*Lignes_1_2[[#This Row],[Taux horaire]],0)) -> 0 | P7: =IF(Lignes_1_2[[#This Row],[Rôle ou catégorie]]="","",IF(OR(Lignes_1_2[[#This Row],[Type]]="Hors main-d’œuvre",Lignes_1_2[[#This Row],[Type]]="Provision"),Lignes_1_2[[#This Row],[Quantité]]*Lignes_1_2[[#This Row],[Débours unitaire]],0)) -> 0 | Q7: =IF(Lignes_1_2[[#This Row],[Rôle ou catégorie]]="","",Lignes_1_2[[#This Row],[Main-d’œuvre]]+Lignes_1_2[[#This Row],[Débours]]) -> 0 | T7: =IF(Lignes_1_2[[#This Row],[Rôle ou catégorie]]="","",IFERROR(INDEX(Referentiel[[Type de nature]],MATCH(Lignes_1_2[[#This Row],[Rôle ou catégorie]],Referentiel[[Entrée]],0)),"?")) -> 0
B8: =IF(Lignes_1_2[[#This Row],[Tâche]]="","",IFERROR(INDEX(Taches[[Description]],MATCH(Lignes_1_2[[#This Row],[Tâche]],Taches[[Entrée]],0)),"")) -> 0 | J8: =IF(Lignes_1_2[[#This Row],[Rôle ou catégorie]]="","",IFERROR(INDEX(Referentiel[[Nature]],MATCH(Lignes_1_2[[#This Row],[Rôle ou catégorie]],Referentiel[[Entrée]],0)),"?")) -> 0 | K8: =IF(Lignes_1_2[[#This Row],[Rôle ou catégorie]]="","",IFERROR(INDEX(Referentiel[[Code comptable]],MATCH(Lignes_1_2[[#This Row],[Rôle ou catégorie]],Referentiel[[Entrée]],0)),"?")) -> 0 | L8: =IF(Lignes_1_2[[#This Row],[Rôle ou catégorie]]="","",IFERROR(INDEX(Referentiel[[Service]],MATCH(Lignes_1_2[[#This Row],[Rôle ou catégorie]],Referentiel[[Entrée]],0)),"?")&"") -> 0 | M8: =IF(Lignes_1_2[[#This Row],[Rôle ou catégorie]]="","",IFERROR(INDEX(Referentiel[[Taux horaire]],MATCH(Lignes_1_2[[#This Row],[Rôle ou catégorie]],Referentiel[[Entrée]],0)),"?")) -> 0 | N8: =IF(Lignes_1_2[[#This Row],[Rôle ou catégorie]]="","",IF(Lignes_1_2[[#This Row],[Type]]="Main-d’œuvre",Lignes_1_2[[#This Row],[Quantité]]*Lignes_1_2[[#This Row],[Heures]],0)) -> 0 | O8: =IF(Lignes_1_2[[#This Row],[Rôle ou catégorie]]="","",IF(Lignes_1_2[[#This Row],[Type]]="Main-d’œuvre",Lignes_1_2[[#This Row],[Quantité]]*Lignes_1_2[[#This Row],[Heures]]*Lignes_1_2[[#This Row],[Taux horaire]],0)) -> 0 | P8: =IF(Lignes_1_2[[#This Row],[Rôle ou catégorie]]="","",IF(OR(Lignes_1_2[[#This Row],[Type]]="Hors main-d’œuvre",Lignes_1_2[[#This Row],[Type]]="Provision"),Lignes_1_2[[#This Row],[Quantité]]*Lignes_1_2[[#This Row],[Débours unitaire]],0)) -> 0 | Q8: =IF(Lignes_1_2[[#This Row],[Rôle ou catégorie]]="","",Lignes_1_2[[#This Row],[Main-d’œuvre]]+Lignes_1_2[[#This Row],[Débours]]) -> 0 | T8: =IF(Lignes_1_2[[#This Row],[Rôle ou catégorie]]="","",IFERROR(INDEX(Referentiel[[Type de nature]],MATCH(Lignes_1_2[[#This Row],[Rôle ou catégorie]],Referentiel[[Entrée]],0)),"?")) -> 0
B9: =IF(Lignes_1_2[[#This Row],[Tâche]]="","",IFERROR(INDEX(Taches[[Description]],MATCH(Lignes_1_2[[#This Row],[Tâche]],Taches[[Entrée]],0)),"")) -> 0 | J9: =IF(Lignes_1_2[[#This Row],[Rôle ou catégorie]]="","",IFERROR(INDEX(Referentiel[[Nature]],MATCH(Lignes_1_2[[#This Row],[Rôle ou catégorie]],Referentiel[[Entrée]],0)),"?")) -> 0 | K9: =IF(Lignes_1_2[[#This Row],[Rôle ou catégorie]]="","",IFERROR(INDEX(Referentiel[[Code comptable]],MATCH(Lignes_1_2[[#This Row],[Rôle ou catégorie]],Referentiel[[Entrée]],0)),"?")) -> 0 | L9: =IF(Lignes_1_2[[#This Row],[Rôle ou catégorie]]="","",IFERROR(INDEX(Referentiel[[Service]],MATCH(Lignes_1_2[[#This Row],[Rôle ou catégorie]],Referentiel[[Entrée]],0)),"?")&"") -> 0 | M9: =IF(Lignes_1_2[[#This Row],[Rôle ou catégorie]]="","",IFERROR(INDEX(Referentiel[[Taux horaire]],MATCH(Lignes_1_2[[#This Row],[Rôle ou catégorie]],Referentiel[[Entrée]],0)),"?")) -> 0 | N9: =IF(Lignes_1_2[[#This Row],[Rôle ou catégorie]]="","",IF(Lignes_1_2[[#This Row],[Type]]="Main-d’œuvre",Lignes_1_2[[#This Row],[Quantité]]*Lignes_1_2[[#This Row],[Heures]],0)) -> 0 | O9: =IF(Lignes_1_2[[#This Row],[Rôle ou catégorie]]="","",IF(Lignes_1_2[[#This Row],[Type]]="Main-d’œuvre",Lignes_1_2[[#This Row],[Quantité]]*Lignes_1_2[[#This Row],[Heures]]*Lignes_1_2[[#This Row],[Taux horaire]],0)) -> 0 | P9: =IF(Lignes_1_2[[#This Row],[Rôle ou catégorie]]="","",IF(OR(Lignes_1_2[[#This Row],[Type]]="Hors main-d’œuvre",Lignes_1_2[[#This Row],[Type]]="Provision"),Lignes_1_2[[#This Row],[Quantité]]*Lignes_1_2[[#This Row],[Débours unitaire]],0)) -> 0 | Q9: =IF(Lignes_1_2[[#This Row],[Rôle ou catégorie]]="","",Lignes_1_2[[#This Row],[Main-d’œuvre]]+Lignes_1_2[[#This Row],[Débours]]) -> 0 | T9: =IF(Lignes_1_2[[#This Row],[Rôle ou catégorie]]="","",IFERROR(INDEX(Referentiel[[Type de nature]],MATCH(Lignes_1_2[[#This Row],[Rôle ou catégorie]],Referentiel[[Entrée]],0)),"?")) -> 0
B10: =IF(Lignes_1_2[[#This Row],[Tâche]]="","",IFERROR(INDEX(Taches[[Description]],MATCH(Lignes_1_2[[#This Row],[Tâche]],Taches[[Entrée]],0)),"")) -> 0 | J10: =IF(Lignes_1_2[[#This Row],[Rôle ou catégorie]]="","",IFERROR(INDEX(Referentiel[[Nature]],MATCH(Lignes_1_2[[#This Row],[Rôle ou catégorie]],Referentiel[[Entrée]],0)),"?")) -> 0 | K10: =IF(Lignes_1_2[[#This Row],[Rôle ou catégorie]]="","",IFERROR(INDEX(Referentiel[[Code comptable]],MATCH(Lignes_1_2[[#This Row],[Rôle ou catégorie]],Referentiel[[Entrée]],0)),"?")) -> 0 | L10: =IF(Lignes_1_2[[#This Row],[Rôle ou catégorie]]="","",IFERROR(INDEX(Referentiel[[Service]],MATCH(Lignes_1_2[[#This Row],[Rôle ou catégorie]],Referentiel[[Entrée]],0)),"?")&"") -> 0 | M10: =IF(Lignes_1_2[[#This Row],[Rôle ou catégorie]]="","",IFERROR(INDEX(Referentiel[[Taux horaire]],MATCH(Lignes_1_2[[#This Row],[Rôle ou catégorie]],Referentiel[[Entrée]],0)),"?")) -> 0 | N10: =IF(Lignes_1_2[[#This Row],[Rôle ou catégorie]]="","",IF(Lignes_1_2[[#This Row],[Type]]="Main-d’œuvre",Lignes_1_2[[#This Row],[Quantité]]*Lignes_1_2[[#This Row],[Heures]],0)) -> 0 | O10: =IF(Lignes_1_2[[#This Row],[Rôle ou catégorie]]="","",IF(Lignes_1_2[[#This Row],[Type]]="Main-d’œuvre",Lignes_1_2[[#This Row],[Quantité]]*Lignes_1_2[[#This Row],[Heures]]*Lignes_1_2[[#This Row],[Taux horaire]],0)) -> 0 | P10: =IF(Lignes_1_2[[#This Row],[Rôle ou catégorie]]="","",IF(OR(Lignes_1_2[[#This Row],[Type]]="Hors main-d’œuvre",Lignes_1_2[[#This Row],[Type]]="Provision"),Lignes_1_2[[#This Row],[Quantité]]*Lignes_1_2[[#This Row],[Débours unitaire]],0)) -> 0 | Q10: =IF(Lignes_1_2[[#This Row],[Rôle ou catégorie]]="","",Lignes_1_2[[#This Row],[Main-d’œuvre]]+Lignes_1_2[[#This Row],[Débours]]) -> 0 | T10: =IF(Lignes_1_2[[#This Row],[Rôle ou catégorie]]="","",IFERROR(INDEX(Referentiel[[Type de nature]],MATCH(Lignes_1_2[[#This Row],[Rôle ou catégorie]],Referentiel[[Entrée]],0)),"?")) -> 0
B11: =IF(Lignes_1_2[[#This Row],[Tâche]]="","",IFERROR(INDEX(Taches[[Description]],MATCH(Lignes_1_2[[#This Row],[Tâche]],Taches[[Entrée]],0)),"")) -> 0 | J11: =IF(Lignes_1_2[[#This Row],[Rôle ou catégorie]]="","",IFERROR(INDEX(Referentiel[[Nature]],MATCH(Lignes_1_2[[#This Row],[Rôle ou catégorie]],Referentiel[[Entrée]],0)),"?")) -> 0 | K11: =IF(Lignes_1_2[[#This Row],[Rôle ou catégorie]]="","",IFERROR(INDEX(Referentiel[[Code comptable]],MATCH(Lignes_1_2[[#This Row],[Rôle ou catégorie]],Referentiel[[Entrée]],0)),"?")) -> 0 | L11: =IF(Lignes_1_2[[#This Row],[Rôle ou catégorie]]="","",IFERROR(INDEX(Referentiel[[Service]],MATCH(Lignes_1_2[[#This Row],[Rôle ou catégorie]],Referentiel[[Entrée]],0)),"?")&"") -> 0 | M11: =IF(Lignes_1_2[[#This Row],[Rôle ou catégorie]]="","",IFERROR(INDEX(Referentiel[[Taux horaire]],MATCH(Lignes_1_2[[#This Row],[Rôle ou catégorie]],Referentiel[[Entrée]],0)),"?")) -> 0 | N11: =IF(Lignes_1_2[[#This Row],[Rôle ou catégorie]]="","",IF(Lignes_1_2[[#This Row],[Type]]="Main-d’œuvre",Lignes_1_2[[#This Row],[Quantité]]*Lignes_1_2[[#This Row],[Heures]],0)) -> 0 | O11: =IF(Lignes_1_2[[#This Row],[Rôle ou catégorie]]="","",IF(Lignes_1_2[[#This Row],[Type]]="Main-d’œuvre",Lignes_1_2[[#This Row],[Quantité]]*Lignes_1_2[[#This Row],[Heures]]*Lignes_1_2[[#This Row],[Taux horaire]],0)) -> 0 | P11: =IF(Lignes_1_2[[#This Row],[Rôle ou catégorie]]="","",IF(OR(Lignes_1_2[[#This Row],[Type]]="Hors main-d’œuvre",Lignes_1_2[[#This Row],[Type]]="Provision"),Lignes_1_2[[#This Row],[Quantité]]*Lignes_1_2[[#This Row],[Débours unitaire]],0)) -> 0 | Q11: =IF(Lignes_1_2[[#This Row],[Rôle ou catégorie]]="","",Lignes_1_2[[#This Row],[Main-d’œuvre]]+Lignes_1_2[[#This Row],[Débours]]) -> 0 | T11: =IF(Lignes_1_2[[#This Row],[Rôle ou catégorie]]="","",IFERROR(INDEX(Referentiel[[Type de nature]],MATCH(Lignes_1_2[[#This Row],[Rôle ou catégorie]],Referentiel[[Entrée]],0)),"?")) -> 0
B12: =IF(Lignes_1_2[[#This Row],[Tâche]]="","",IFERROR(INDEX(Taches[[Description]],MATCH(Lignes_1_2[[#This Row],[Tâche]],Taches[[Entrée]],0)),"")) -> 0 | J12: =IF(Lignes_1_2[[#This Row],[Rôle ou catégorie]]="","",IFERROR(INDEX(Referentiel[[Nature]],MATCH(Lignes_1_2[[#This Row],[Rôle ou catégorie]],Referentiel[[Entrée]],0)),"?")) -> 0 | K12: =IF(Lignes_1_2[[#This Row],[Rôle ou catégorie]]="","",IFERROR(INDEX(Referentiel[[Code comptable]],MATCH(Lignes_1_2[[#This Row],[Rôle ou catégorie]],Referentiel[[Entrée]],0)),"?")) -> 0 | L12: =IF(Lignes_1_2[[#This Row],[Rôle ou catégorie]]="","",IFERROR(INDEX(Referentiel[[Service]],MATCH(Lignes_1_2[[#This Row],[Rôle ou catégorie]],Referentiel[[Entrée]],0)),"?")&"") -> 0 | M12: =IF(Lignes_1_2[[#This Row],[Rôle ou catégorie]]="","",IFERROR(INDEX(Referentiel[[Taux horaire]],MATCH(Lignes_1_2[[#This Row],[Rôle ou catégorie]],Referentiel[[Entrée]],0)),"?")) -> 0 | N12: =IF(Lignes_1_2[[#This Row],[Rôle ou catégorie]]="","",IF(Lignes_1_2[[#This Row],[Type]]="Main-d’œuvre",Lignes_1_2[[#This Row],[Quantité]]*Lignes_1_2[[#This Row],[Heures]],0)) -> 0 | O12: =IF(Lignes_1_2[[#This Row],[Rôle ou catégorie]]="","",IF(Lignes_1_2[[#This Row],[Type]]="Main-d’œuvre",Lignes_1_2[[#This Row],[Quantité]]*Lignes_1_2[[#This Row],[Heures]]*Lignes_1_2[[#This Row],[Taux horaire]],0)) -> 0 | P12: =IF(Lignes_1_2[[#This Row],[Rôle ou catégorie]]="","",IF(OR(Lignes_1_2[[#This Row],[Type]]="Hors main-d’œuvre",Lignes_1_2[[#This Row],[Type]]="Provision"),Lignes_1_2[[#This Row],[Quantité]]*Lignes_1_2[[#This Row],[Débours unitaire]],0)) -> 0 | Q12: =IF(Lignes_1_2[[#This Row],[Rôle ou catégorie]]="","",Lignes_1_2[[#This Row],[Main-d’œuvre]]+Lignes_1_2[[#This Row],[Débours]]) -> 0 | T12: =IF(Lignes_1_2[[#This Row],[Rôle ou catégorie]]="","",IFERROR(INDEX(Referentiel[[Type de nature]],MATCH(Lignes_1_2[[#This Row],[Rôle ou catégorie]],Referentiel[[Entrée]],0)),"?")) -> 0
B13: =IF(Lignes_1_2[[#This Row],[Tâche]]="","",IFERROR(INDEX(Taches[[Description]],MATCH(Lignes_1_2[[#This Row],[Tâche]],Taches[[Entrée]],0)),"")) -> 0 | J13: =IF(Lignes_1_2[[#This Row],[Rôle ou catégorie]]="","",IFERROR(INDEX(Referentiel[[Nature]],MATCH(Lignes_1_2[[#This Row],[Rôle ou catégorie]],Referentiel[[Entrée]],0)),"?")) -> 0 | K13: =IF(Lignes_1_2[[#This Row],[Rôle ou catégorie]]="","",IFERROR(INDEX(Referentiel[[Code comptable]],MATCH(Lignes_1_2[[#This Row],[Rôle ou catégorie]],Referentiel[[Entrée]],0)),"?")) -> 0 | L13: =IF(Lignes_1_2[[#This Row],[Rôle ou catégorie]]="","",IFERROR(INDEX(Referentiel[[Service]],MATCH(Lignes_1_2[[#This Row],[Rôle ou catégorie]],Referentiel[[Entrée]],0)),"?")&"") -> 0 | M13: =IF(Lignes_1_2[[#This Row],[Rôle ou catégorie]]="","",IFERROR(INDEX(Referentiel[[Taux horaire]],MATCH(Lignes_1_2[[#This Row],[Rôle ou catégorie]],Referentiel[[Entrée]],0)),"?")) -> 0 | N13: =IF(Lignes_1_2[[#This Row],[Rôle ou catégorie]]="","",IF(Lignes_1_2[[#This Row],[Type]]="Main-d’œuvre",Lignes_1_2[[#This Row],[Quantité]]*Lignes_1_2[[#This Row],[Heures]],0)) -> 0 | O13: =IF(Lignes_1_2[[#This Row],[Rôle ou catégorie]]="","",IF(Lignes_1_2[[#This Row],[Type]]="Main-d’œuvre",Lignes_1_2[[#This Row],[Quantité]]*Lignes_1_2[[#This Row],[Heures]]*Lignes_1_2[[#This Row],[Taux horaire]],0)) -> 0 | P13: =IF(Lignes_1_2[[#This Row],[Rôle ou catégorie]]="","",IF(OR(Lignes_1_2[[#This Row],[Type]]="Hors main-d’œuvre",Lignes_1_2[[#This Row],[Type]]="Provision"),Lignes_1_2[[#This Row],[Quantité]]*Lignes_1_2[[#This Row],[Débours unitaire]],0)) -> 0 | Q13: =IF(Lignes_1_2[[#This Row],[Rôle ou catégorie]]="","",Lignes_1_2[[#This Row],[Main-d’œuvre]]+Lignes_1_2[[#This Row],[Débours]]) -> 0 | T13: =IF(Lignes_1_2[[#This Row],[Rôle ou catégorie]]="","",IFERROR(INDEX(Referentiel[[Type de nature]],MATCH(Lignes_1_2[[#This Row],[Rôle ou catégorie]],Referentiel[[Entrée]],0)),"?")) -> 0
B14: =IF(Lignes_1_2[[#This Row],[Tâche]]="","",IFERROR(INDEX(Taches[[Description]],MATCH(Lignes_1_2[[#This Row],[Tâche]],Taches[[Entrée]],0)),"")) -> 0 | J14: =IF(Lignes_1_2[[#This Row],[Rôle ou catégorie]]="","",IFERROR(INDEX(Referentiel[[Nature]],MATCH(Lignes_1_2[[#This Row],[Rôle ou catégorie]],Referentiel[[Entrée]],0)),"?")) -> 0 | K14: =IF(Lignes_1_2[[#This Row],[Rôle ou catégorie]]="","",IFERROR(INDEX(Referentiel[[Code comptable]],MATCH(Lignes_1_2[[#This Row],[Rôle ou catégorie]],Referentiel[[Entrée]],0)),"?")) -> 0 | L14: =IF(Lignes_1_2[[#This Row],[Rôle ou catégorie]]="","",IFERROR(INDEX(Referentiel[[Service]],MATCH(Lignes_1_2[[#This Row],[Rôle ou catégorie]],Referentiel[[Entrée]],0)),"?")&"") -> 0 | M14: =IF(Lignes_1_2[[#This Row],[Rôle ou catégorie]]="","",IFERROR(INDEX(Referentiel[[Taux horaire]],MATCH(Lignes_1_2[[#This Row],[Rôle ou catégorie]],Referentiel[[Entrée]],0)),"?")) -> 0 | N14: =IF(Lignes_1_2[[#This Row],[Rôle ou catégorie]]="","",IF(Lignes_1_2[[#This Row],[Type]]="Main-d’œuvre",Lignes_1_2[[#This Row],[Quantité]]*Lignes_1_2[[#This Row],[Heures]],0)) -> 0 | O14: =IF(Lignes_1_2[[#This Row],[Rôle ou catégorie]]="","",IF(Lignes_1_2[[#This Row],[Type]]="Main-d’œuvre",Lignes_1_2[[#This Row],[Quantité]]*Lignes_1_2[[#This Row],[Heures]]*Lignes_1_2[[#This Row],[Taux horaire]],0)) -> 0 | P14: =IF(Lignes_1_2[[#This Row],[Rôle ou catégorie]]="","",IF(OR(Lignes_1_2[[#This Row],[Type]]="Hors main-d’œuvre",Lignes_1_2[[#This Row],[Type]]="Provision"),Lignes_1_2[[#This Row],[Quantité]]*Lignes_1_2[[#This Row],[Débours unitaire]],0)) -> 0 | Q14: =IF(Lignes_1_2[[#This Row],[Rôle ou catégorie]]="","",Lignes_1_2[[#This Row],[Main-d’œuvre]]+Lignes_1_2[[#This Row],[Débours]]) -> 0 | T14: =IF(Lignes_1_2[[#This Row],[Rôle ou catégorie]]="","",IFERROR(INDEX(Referentiel[[Type de nature]],MATCH(Lignes_1_2[[#This Row],[Rôle ou catégorie]],Referentiel[[Entrée]],0)),"?")) -> 0
B15: =IF(Lignes_1_2[[#This Row],[Tâche]]="","",IFERROR(INDEX(Taches[[Description]],MATCH(Lignes_1_2[[#This Row],[Tâche]],Taches[[Entrée]],0)),"")) -> 0 | J15: =IF(Lignes_1_2[[#This Row],[Rôle ou catégorie]]="","",IFERROR(INDEX(Referentiel[[Nature]],MATCH(Lignes_1_2[[#This Row],[Rôle ou catégorie]],Referentiel[[Entrée]],0)),"?")) -> 0 | K15: =IF(Lignes_1_2[[#This Row],[Rôle ou catégorie]]="","",IFERROR(INDEX(Referentiel[[Code comptable]],MATCH(Lignes_1_2[[#This Row],[Rôle ou catégorie]],Referentiel[[Entrée]],0)),"?")) -> 0 | L15: =IF(Lignes_1_2[[#This Row],[Rôle ou catégorie]]="","",IFERROR(INDEX(Referentiel[[Service]],MATCH(Lignes_1_2[[#This Row],[Rôle ou catégorie]],Referentiel[[Entrée]],0)),"?")&"") -> 0 | M15: =IF(Lignes_1_2[[#This Row],[Rôle ou catégorie]]="","",IFERROR(INDEX(Referentiel[[Taux horaire]],MATCH(Lignes_1_2[[#This Row],[Rôle ou catégorie]],Referentiel[[Entrée]],0)),"?")) -> 0 | N15: =IF(Lignes_1_2[[#This Row],[Rôle ou catégorie]]="","",IF(Lignes_1_2[[#This Row],[Type]]="Main-d’œuvre",Lignes_1_2[[#This Row],[Quantité]]*Lignes_1_2[[#This Row],[Heures]],0)) -> 0 | O15: =IF(Lignes_1_2[[#This Row],[Rôle ou catégorie]]="","",IF(Lignes_1_2[[#This Row],[Type]]="Main-d’œuvre",Lignes_1_2[[#This Row],[Quantité]]*Lignes_1_2[[#This Row],[Heures]]*Lignes_1_2[[#This Row],[Taux horaire]],0)) -> 0 | P15: =IF(Lignes_1_2[[#This Row],[Rôle ou catégorie]]="","",IF(OR(Lignes_1_2[[#This Row],[Type]]="Hors main-d’œuvre",Lignes_1_2[[#This Row],[Type]]="Provision"),Lignes_1_2[[#This Row],[Quantité]]*Lignes_1_2[[#This Row],[Débours unitaire]],0)) -> 0 | Q15: =IF(Lignes_1_2[[#This Row],[Rôle ou catégorie]]="","",Lignes_1_2[[#This Row],[Main-d’œuvre]]+Lignes_1_2[[#This Row],[Débours]]) -> 0 | T15: =IF(Lignes_1_2[[#This Row],[Rôle ou catégorie]]="","",IFERROR(INDEX(Referentiel[[Type de nature]],MATCH(Lignes_1_2[[#This Row],[Rôle ou catégorie]],Referentiel[[Entrée]],0)),"?")) -> 0
B16: =IF(Lignes_1_2[[#This Row],[Tâche]]="","",IFERROR(INDEX(Taches[[Description]],MATCH(Lignes_1_2[[#This Row],[Tâche]],Taches[[Entrée]],0)),"")) -> 0 | J16: =IF(Lignes_1_2[[#This Row],[Rôle ou catégorie]]="","",IFERROR(INDEX(Referentiel[[Nature]],MATCH(Lignes_1_2[[#This Row],[Rôle ou catégorie]],Referentiel[[Entrée]],0)),"?")) -> 0 | K16: =IF(Lignes_1_2[[#This Row],[Rôle ou catégorie]]="","",IFERROR(INDEX(Referentiel[[Code comptable]],MATCH(Lignes_1_2[[#This Row],[Rôle ou catégorie]],Referentiel[[Entrée]],0)),"?")) -> 0 | L16: =IF(Lignes_1_2[[#This Row],[Rôle ou catégorie]]="","",IFERROR(INDEX(Referentiel[[Service]],MATCH(Lignes_1_2[[#This Row],[Rôle ou catégorie]],Referentiel[[Entrée]],0)),"?")&"") -> 0 | M16: =IF(Lignes_1_2[[#This Row],[Rôle ou catégorie]]="","",IFERROR(INDEX(Referentiel[[Taux horaire]],MATCH(Lignes_1_2[[#This Row],[Rôle ou catégorie]],Referentiel[[Entrée]],0)),"?")) -> 0 | N16: =IF(Lignes_1_2[[#This Row],[Rôle ou catégorie]]="","",IF(Lignes_1_2[[#This Row],[Type]]="Main-d’œuvre",Lignes_1_2[[#This Row],[Quantité]]*Lignes_1_2[[#This Row],[Heures]],0)) -> 0 | O16: =IF(Lignes_1_2[[#This Row],[Rôle ou catégorie]]="","",IF(Lignes_1_2[[#This Row],[Type]]="Main-d’œuvre",Lignes_1_2[[#This Row],[Quantité]]*Lignes_1_2[[#This Row],[Heures]]*Lignes_1_2[[#This Row],[Taux horaire]],0)) -> 0 | P16: =IF(Lignes_1_2[[#This Row],[Rôle ou catégorie]]="","",IF(OR(Lignes_1_2[[#This Row],[Type]]="Hors main-d’œuvre",Lignes_1_2[[#This Row],[Type]]="Provision"),Lignes_1_2[[#This Row],[Quantité]]*Lignes_1_2[[#This Row],[Débours unitaire]],0)) -> 0 | Q16: =IF(Lignes_1_2[[#This Row],[Rôle ou catégorie]]="","",Lignes_1_2[[#This Row],[Main-d’œuvre]]+Lignes_1_2[[#This Row],[Débours]]) -> 0 | T16: =IF(Lignes_1_2[[#This Row],[Rôle ou catégorie]]="","",IFERROR(INDEX(Referentiel[[Type de nature]],MATCH(Lignes_1_2[[#This Row],[Rôle ou catégorie]],Referentiel[[Entrée]],0)),"?")) -> 0
... B34: =IF(Lignes_1_2[[#This Row],[Tâche]]="","",IFERROR(INDEX(Taches[[Description]],MATCH(Lignes_1_2[[#This Row],[Tâche]],Taches[[Entrée]],0)),"")) -> 0 | J34: =IF(Lignes_1_2[[#This Row],[Rôle ou catégorie]]="","",IFERROR(INDEX(Referentiel[[Nature]],MATCH(Lignes_1_2[[#This Row],[Rôle ou catégorie]],Referentiel[[Entrée]],0)),"?")) -> 0 | K34: =IF(Lignes_1_2[[#This Row],[Rôle ou catégorie]]="","",IFERROR(INDEX(Referentiel[[Code comptable]],MATCH(Lignes_1_2[[#This Row],[Rôle ou catégorie]],Referentiel[[Entrée]],0)),"?")) -> 0 | L34: =IF(Lignes_1_2[[#This Row],[Rôle ou catégorie]]="","",IFERROR(INDEX(Referentiel[[Service]],MATCH(Lignes_1_2[[#This Row],[Rôle ou catégorie]],Referentiel[[Entrée]],0)),"?")&"") -> 0 | M34: =IF(Lignes_1_2[[#This Row],[Rôle ou catégorie]]="","",IFERROR(INDEX(Referentiel[[Taux horaire]],MATCH(Lignes_1_2[[#This Row],[Rôle ou catégorie]],Referentiel[[Entrée]],0)),"?")) -> 0 | N34: =IF(Lignes_1_2[[#This Row],[Rôle ou catégorie]]="","",IF(Lignes_1_2[[#This Row],[Type]]="Main-d’œuvre",Lignes_1_2[[#This Row],[Quantité]]*Lignes_1_2[[#This Row],[Heures]],0)) -> 0 | O34: =IF(Lignes_1_2[[#This Row],[Rôle ou catégorie]]="","",IF(Lignes_1_2[[#This Row],[Type]]="Main-d’œuvre",Lignes_1_2[[#This Row],[Quantité]]*Lignes_1_2[[#This Row],[Heures]]*Lignes_1_2[[#This Row],[Taux horaire]],0)) -> 0 | P34: =IF(Lignes_1_2[[#This Row],[Rôle ou catégorie]]="","",IF(OR(Lignes_1_2[[#This Row],[Type]]="Hors main-d’œuvre",Lignes_1_2[[#This Row],[Type]]="Provision"),Lignes_1_2[[#This Row],[Quantité]]*Lignes_1_2[[#This Row],[Débours unitaire]],0)) -> 0 | Q34: =IF(Lignes_1_2[[#This Row],[Rôle ou catégorie]]="","",Lignes_1_2[[#This Row],[Main-d’œuvre]]+Lignes_1_2[[#This Row],[Débours]]) -> 0 | T34: =IF(Lignes_1_2[[#This Row],[Rôle ou catégorie]]="","",IFERROR(INDEX(Referentiel[[Type de nature]],MATCH(Lignes_1_2[[#This Row],[Rôle ou catégorie]],Referentiel[[Entrée]],0)),"?")) -> 0
A35: Total | N35: =SUBTOTAL(109,Lignes_1_2[[Heures totales]]) -> 0 | O35: =SUBTOTAL(109,Lignes_1_2[[Main-d’œuvre]]) -> 0 | P35: =SUBTOTAL(109,Lignes_1_2[[Débours]]) -> 0 | Q35: =SUBTOTAL(109,Lignes_1_2[[Montant]]) -> 0 | R35: =SUBTOTAL(109,Lignes_1_2[[Montant Waterfall]]) -> 0

Sheet 1 Contrôle d’accès
A1: Tâche | B1: Description de la tâche | C1: Rôle ou catégorie | D1: Désignation | E1: Quantité | F1: Heures | G1: Débours unitaire | H1: Délai de paiement (j) | I1: Sous-projet | J1: Nature | K1: Code comptable | L1: Service | M1: Taux horaire | N1: Heures totales | O1: Main-d’œuvre | P1: Débours | Q1: Montant | R1: Montant Waterfall | S1: ID ligne | T1: Type
A2: 1.3 Revue de conception | B2: =IF(Lignes_1[[#This Row],[Tâche]]="","",IFERROR(INDEX(Taches[[Description]],MATCH(Lignes_1[[#This Row],[Tâche]],Taches[[Entrée]],0)),"")) -> 0 | C2: Architecte électronique (ARCH-ELEC) | E2: 3 | F2: 7.4 | H2: 0 | J2: =IF(Lignes_1[[#This Row],[Rôle ou catégorie]]="","",IFERROR(INDEX(Referentiel[[Nature]],MATCH(Lignes_1[[#This Row],[Rôle ou catégorie]],Referentiel[[Entrée]],0)),"?")) -> 0 | K2: =IF(Lignes_1[[#This Row],[Rôle ou catégorie]]="","",IFERROR(INDEX(Referentiel[[Code comptable]],MATCH(Lignes_1[[#This Row],[Rôle ou catégorie]],Referentiel[[Entrée]],0)),"?")) -> 0 | L2: =IF(Lignes_1[[#This Row],[Rôle ou catégorie]]="","",IFERROR(INDEX(Referentiel[[Service]],MATCH(Lignes_1[[#This Row],[Rôle ou catégorie]],Referentiel[[Entrée]],0)),"?")&"") -> 0 | M2: =IF(Lignes_1[[#This Row],[Rôle ou catégorie]]="","",IFERROR(INDEX(Referentiel[[Taux horaire]],MATCH(Lignes_1[[#This Row],[Rôle ou catégorie]],Referentiel[[Entrée]],0)),"?")) -> 0 | N2: =IF(Lignes_1[[#This Row],[Rôle ou catégorie]]="","",IF(Lignes_1[[#This Row],[Type]]="Main-d’œuvre",Lignes_1[[#This Row],[Quantité]]*Lignes_1[[#This Row],[Heures]],0)) -> 0 | O2: =IF(Lignes_1[[#This Row],[Rôle ou catégorie]]="","",IF(Lignes_1[[#This Row],[Type]]="Main-d’œuvre",Lignes_1[[#This Row],[Quantité]]*Lignes_1[[#This Row],[Heures]]*Lignes_1[[#This Row],[Taux horaire]],0)) -> 0 | P2: =IF(Lignes_1[[#This Row],[Rôle ou catégorie]]="","",IF(OR(Lignes_1[[#This Row],[Type]]="Hors main-d’œuvre",Lignes_1[[#This Row],[Type]]="Provision"),Lignes_1[[#This Row],[Quantité]]*Lignes_1[[#This Row],[Débours unitaire]],0)) -> 0 | Q2: =IF(Lignes_1[[#This Row],[Rôle ou catégorie]]="","",Lignes_1[[#This Row],[Main-d’œuvre]]+Lignes_1[[#This Row],[Débours]]) -> 0 | R2: 1776 | S2: l-0301 | T2: =IF(Lignes_1[[#This Row],[Rôle ou catégorie]]="","",IFERROR(INDEX(Referentiel[[Type de nature]],MATCH(Lignes_1[[#This Row],[Rôle ou catégorie]],Referentiel[[Entrée]],0)),"?")) -> 0
B3: =IF(Lignes_1[[#This Row],[Tâche]]="","",IFERROR(INDEX(Taches[[Description]],MATCH(Lignes_1[[#This Row],[Tâche]],Taches[[Entrée]],0)),"")) -> 0 | J3: =IF(Lignes_1[[#This Row],[Rôle ou catégorie]]="","",IFERROR(INDEX(Referentiel[[Nature]],MATCH(Lignes_1[[#This Row],[Rôle ou catégorie]],Referentiel[[Entrée]],0)),"?")) -> 0 | K3: =IF(Lignes_1[[#This Row],[Rôle ou catégorie]]="","",IFERROR(INDEX(Referentiel[[Code comptable]],MATCH(Lignes_1[[#This Row],[Rôle ou catégorie]],Referentiel[[Entrée]],0)),"?")) -> 0 | L3: =IF(Lignes_1[[#This Row],[Rôle ou catégorie]]="","",IFERROR(INDEX(Referentiel[[Service]],MATCH(Lignes_1[[#This Row],[Rôle ou catégorie]],Referentiel[[Entrée]],0)),"?")&"") -> 0 | M3: =IF(Lignes_1[[#This Row],[Rôle ou catégorie]]="","",IFERROR(INDEX(Referentiel[[Taux horaire]],MATCH(Lignes_1[[#This Row],[Rôle ou catégorie]],Referentiel[[Entrée]],0)),"?")) -> 0 | N3: =IF(Lignes_1[[#This Row],[Rôle ou catégorie]]="","",IF(Lignes_1[[#This Row],[Type]]="Main-d’œuvre",Lignes_1[[#This Row],[Quantité]]*Lignes_1[[#This Row],[Heures]],0)) -> 0 | O3: =IF(Lignes_1[[#This Row],[Rôle ou catégorie]]="","",IF(Lignes_1[[#This Row],[Type]]="Main-d’œuvre",Lignes_1[[#This Row],[Quantité]]*Lignes_1[[#This Row],[Heures]]*Lignes_1[[#This Row],[Taux horaire]],0)) -> 0 | P3: =IF(Lignes_1[[#This Row],[Rôle ou catégorie]]="","",IF(OR(Lignes_1[[#This Row],[Type]]="Hors main-d’œuvre",Lignes_1[[#This Row],[Type]]="Provision"),Lignes_1[[#This Row],[Quantité]]*Lignes_1[[#This Row],[Débours unitaire]],0)) -> 0 | Q3: =IF(Lignes_1[[#This Row],[Rôle ou catégorie]]="","",Lignes_1[[#This Row],[Main-d’œuvre]]+Lignes_1[[#This Row],[Débours]]) -> 0 | T3: =IF(Lignes_1[[#This Row],[Rôle ou catégorie]]="","",IFERROR(INDEX(Referentiel[[Type de nature]],MATCH(Lignes_1[[#This Row],[Rôle ou catégorie]],Referentiel[[Entrée]],0)),"?")) -> 0
B4: =IF(Lignes_1[[#This Row],[Tâche]]="","",IFERROR(INDEX(Taches[[Description]],MATCH(Lignes_1[[#This Row],[Tâche]],Taches[[Entrée]],0)),"")) -> 0 | J4: =IF(Lignes_1[[#This Row],[Rôle ou catégorie]]="","",IFERROR(INDEX(Referentiel[[Nature]],MATCH(Lignes_1[[#This Row],[Rôle ou catégorie]],Referentiel[[Entrée]],0)),"?")) -> 0 | K4: =IF(Lignes_1[[#This Row],[Rôle ou catégorie]]="","",IFERROR(INDEX(Referentiel[[Code comptable]],MATCH(Lignes_1[[#This Row],[Rôle ou catégorie]],Referentiel[[Entrée]],0)),"?")) -> 0 | L4: =IF(Lignes_1[[#This Row],[Rôle ou catégorie]]="","",IFERROR(INDEX(Referentiel[[Service]],MATCH(Lignes_1[[#This Row],[Rôle ou catégorie]],Referentiel[[Entrée]],0)),"?")&"") -> 0 | M4: =IF(Lignes_1[[#This Row],[Rôle ou catégorie]]="","",IFERROR(INDEX(Referentiel[[Taux horaire]],MATCH(Lignes_1[[#This Row],[Rôle ou catégorie]],Referentiel[[Entrée]],0)),"?")) -> 0 | N4: =IF(Lignes_1[[#This Row],[Rôle ou catégorie]]="","",IF(Lignes_1[[#This Row],[Type]]="Main-d’œuvre",Lignes_1[[#This Row],[Quantité]]*Lignes_1[[#This Row],[Heures]],0)) -> 0 | O4: =IF(Lignes_1[[#This Row],[Rôle ou catégorie]]="","",IF(Lignes_1[[#This Row],[Type]]="Main-d’œuvre",Lignes_1[[#This Row],[Quantité]]*Lignes_1[[#This Row],[Heures]]*Lignes_1[[#This Row],[Taux horaire]],0)) -> 0 | P4: =IF(Lignes_1[[#This Row],[Rôle ou catégorie]]="","",IF(OR(Lignes_1[[#This Row],[Type]]="Hors main-d’œuvre",Lignes_1[[#This Row],[Type]]="Provision"),Lignes_1[[#This Row],[Quantité]]*Lignes_1[[#This Row],[Débours unitaire]],0)) -> 0 | Q4: =IF(Lignes_1[[#This Row],[Rôle ou catégorie]]="","",Lignes_1[[#This Row],[Main-d’œuvre]]+Lignes_1[[#This Row],[Débours]]) -> 0 | T4: =IF(Lignes_1[[#This Row],[Rôle ou catégorie]]="","",IFERROR(INDEX(Referentiel[[Type de nature]],MATCH(Lignes_1[[#This Row],[Rôle ou catégorie]],Referentiel[[Entrée]],0)),"?")) -> 0
B5: =IF(Lignes_1[[#This Row],[Tâche]]="","",IFERROR(INDEX(Taches[[Description]],MATCH(Lignes_1[[#This Row],[Tâche]],Taches[[Entrée]],0)),"")) -> 0 | J5: =IF(Lignes_1[[#This Row],[Rôle ou catégorie]]="","",IFERROR(INDEX(Referentiel[[Nature]],MATCH(Lignes_1[[#This Row],[Rôle ou catégorie]],Referentiel[[Entrée]],0)),"?")) -> 0 | K5: =IF(Lignes_1[[#This Row],[Rôle ou catégorie]]="","",IFERROR(INDEX(Referentiel[[Code comptable]],MATCH(Lignes_1[[#This Row],[Rôle ou catégorie]],Referentiel[[Entrée]],0)),"?")) -> 0 | L5: =IF(Lignes_1[[#This Row],[Rôle ou catégorie]]="","",IFERROR(INDEX(Referentiel[[Service]],MATCH(Lignes_1[[#This Row],[Rôle ou catégorie]],Referentiel[[Entrée]],0)),"?")&"") -> 0 | M5: =IF(Lignes_1[[#This Row],[Rôle ou catégorie]]="","",IFERROR(INDEX(Referentiel[[Taux horaire]],MATCH(Lignes_1[[#This Row],[Rôle ou catégorie]],Referentiel[[Entrée]],0)),"?")) -> 0 | N5: =IF(Lignes_1[[#This Row],[Rôle ou catégorie]]="","",IF(Lignes_1[[#This Row],[Type]]="Main-d’œuvre",Lignes_1[[#This Row],[Quantité]]*Lignes_1[[#This Row],[Heures]],0)) -> 0 | O5: =IF(Lignes_1[[#This Row],[Rôle ou catégorie]]="","",IF(Lignes_1[[#This Row],[Type]]="Main-d’œuvre",Lignes_1[[#This Row],[Quantité]]*Lignes_1[[#This Row],[Heures]]*Lignes_1[[#This Row],[Taux horaire]],0)) -> 0 | P5: =IF(Lignes_1[[#This Row],[Rôle ou catégorie]]="","",IF(OR(Lignes_1[[#This Row],[Type]]="Hors main-d’œuvre",Lignes_1[[#This Row],[Type]]="Provision"),Lignes_1[[#This Row],[Quantité]]*Lignes_1[[#This Row],[Débours unitaire]],0)) -> 0 | Q5: =IF(Lignes_1[[#This Row],[Rôle ou catégorie]]="","",Lignes_1[[#This Row],[Main-d’œuvre]]+Lignes_1[[#This Row],[Débours]]) -> 0 | T5: =IF(Lignes_1[[#This Row],[Rôle ou catégorie]]="","",IFERROR(INDEX(Referentiel[[Type de nature]],MATCH(Lignes_1[[#This Row],[Rôle ou catégorie]],Referentiel[[Entrée]],0)),"?")) -> 0
B6: =IF(Lignes_1[[#This Row],[Tâche]]="","",IFERROR(INDEX(Taches[[Description]],MATCH(Lignes_1[[#This Row],[Tâche]],Taches[[Entrée]],0)),"")) -> 0 | J6: =IF(Lignes_1[[#This Row],[Rôle ou catégorie]]="","",IFERROR(INDEX(Referentiel[[Nature]],MATCH(Lignes_1[[#This Row],[Rôle ou catégorie]],Referentiel[[Entrée]],0)),"?")) -> 0 | K6: =IF(Lignes_1[[#This Row],[Rôle ou catégorie]]="","",IFERROR(INDEX(Referentiel[[Code comptable]],MATCH(Lignes_1[[#This Row],[Rôle ou catégorie]],Referentiel[[Entrée]],0)),"?")) -> 0 | L6: =IF(Lignes_1[[#This Row],[Rôle ou catégorie]]="","",IFERROR(INDEX(Referentiel[[Service]],MATCH(Lignes_1[[#This Row],[Rôle ou catégorie]],Referentiel[[Entrée]],0)),"?")&"") -> 0 | M6: =IF(Lignes_1[[#This Row],[Rôle ou catégorie]]="","",IFERROR(INDEX(Referentiel[[Taux horaire]],MATCH(Lignes_1[[#This Row],[Rôle ou catégorie]],Referentiel[[Entrée]],0)),"?")) -> 0 | N6: =IF(Lignes_1[[#This Row],[Rôle ou catégorie]]="","",IF(Lignes_1[[#This Row],[Type]]="Main-d’œuvre",Lignes_1[[#This Row],[Quantité]]*Lignes_1[[#This Row],[Heures]],0)) -> 0 | O6: =IF(Lignes_1[[#This Row],[Rôle ou catégorie]]="","",IF(Lignes_1[[#This Row],[Type]]="Main-d’œuvre",Lignes_1[[#This Row],[Quantité]]*Lignes_1[[#This Row],[Heures]]*Lignes_1[[#This Row],[Taux horaire]],0)) -> 0 | P6: =IF(Lignes_1[[#This Row],[Rôle ou catégorie]]="","",IF(OR(Lignes_1[[#This Row],[Type]]="Hors main-d’œuvre",Lignes_1[[#This Row],[Type]]="Provision"),Lignes_1[[#This Row],[Quantité]]*Lignes_1[[#This Row],[Débours unitaire]],0)) -> 0 | Q6: =IF(Lignes_1[[#This Row],[Rôle ou catégorie]]="","",Lignes_1[[#This Row],[Main-d’œuvre]]+Lignes_1[[#This Row],[Débours]]) -> 0 | T6: =IF(Lignes_1[[#This Row],[Rôle ou catégorie]]="","",IFERROR(INDEX(Referentiel[[Type de nature]],MATCH(Lignes_1[[#This Row],[Rôle ou catégorie]],Referentiel[[Entrée]],0)),"?")) -> 0
B7: =IF(Lignes_1[[#This Row],[Tâche]]="","",IFERROR(INDEX(Taches[[Description]],MATCH(Lignes_1[[#This Row],[Tâche]],Taches[[Entrée]],0)),"")) -> 0 | J7: =IF(Lignes_1[[#This Row],[Rôle ou catégorie]]="","",IFERROR(INDEX(Referentiel[[Nature]],MATCH(Lignes_1[[#This Row],[Rôle ou catégorie]],Referentiel[[Entrée]],0)),"?")) -> 0 | K7: =IF(Lignes_1[[#This Row],[Rôle ou catégorie]]="","",IFERROR(INDEX(Referentiel[[Code comptable]],MATCH(Lignes_1[[#This Row],[Rôle ou catégorie]],Referentiel[[Entrée]],0)),"?")) -> 0 | L7: =IF(Lignes_1[[#This Row],[Rôle ou catégorie]]="","",IFERROR(INDEX(Referentiel[[Service]],MATCH(Lignes_1[[#This Row],[Rôle ou catégorie]],Referentiel[[Entrée]],0)),"?")&"") -> 0 | M7: =IF(Lignes_1[[#This Row],[Rôle ou catégorie]]="","",IFERROR(INDEX(Referentiel[[Taux horaire]],MATCH(Lignes_1[[#This Row],[Rôle ou catégorie]],Referentiel[[Entrée]],0)),"?")) -> 0 | N7: =IF(Lignes_1[[#This Row],[Rôle ou catégorie]]="","",IF(Lignes_1[[#This Row],[Type]]="Main-d’œuvre",Lignes_1[[#This Row],[Quantité]]*Lignes_1[[#This Row],[Heures]],0)) -> 0 | O7: =IF(Lignes_1[[#This Row],[Rôle ou catégorie]]="","",IF(Lignes_1[[#This Row],[Type]]="Main-d’œuvre",Lignes_1[[#This Row],[Quantité]]*Lignes_1[[#This Row],[Heures]]*Lignes_1[[#This Row],[Taux horaire]],0)) -> 0 | P7: =IF(Lignes_1[[#This Row],[Rôle ou catégorie]]="","",IF(OR(Lignes_1[[#This Row],[Type]]="Hors main-d’œuvre",Lignes_1[[#This Row],[Type]]="Provision"),Lignes_1[[#This Row],[Quantité]]*Lignes_1[[#This Row],[Débours unitaire]],0)) -> 0 | Q7: =IF(Lignes_1[[#This Row],[Rôle ou catégorie]]="","",Lignes_1[[#This Row],[Main-d’œuvre]]+Lignes_1[[#This Row],[Débours]]) -> 0 | T7: =IF(Lignes_1[[#This Row],[Rôle ou catégorie]]="","",IFERROR(INDEX(Referentiel[[Type de nature]],MATCH(Lignes_1[[#This Row],[Rôle ou catégorie]],Referentiel[[Entrée]],0)),"?")) -> 0
B8: =IF(Lignes_1[[#This Row],[Tâche]]="","",IFERROR(INDEX(Taches[[Description]],MATCH(Lignes_1[[#This Row],[Tâche]],Taches[[Entrée]],0)),"")) -> 0 | J8: =IF(Lignes_1[[#This Row],[Rôle ou catégorie]]="","",IFERROR(INDEX(Referentiel[[Nature]],MATCH(Lignes_1[[#This Row],[Rôle ou catégorie]],Referentiel[[Entrée]],0)),"?")) -> 0 | K8: =IF(Lignes_1[[#This Row],[Rôle ou catégorie]]="","",IFERROR(INDEX(Referentiel[[Code comptable]],MATCH(Lignes_1[[#This Row],[Rôle ou catégorie]],Referentiel[[Entrée]],0)),"?")) -> 0 | L8: =IF(Lignes_1[[#This Row],[Rôle ou catégorie]]="","",IFERROR(INDEX(Referentiel[[Service]],MATCH(Lignes_1[[#This Row],[Rôle ou catégorie]],Referentiel[[Entrée]],0)),"?")&"") -> 0 | M8: =IF(Lignes_1[[#This Row],[Rôle ou catégorie]]="","",IFERROR(INDEX(Referentiel[[Taux horaire]],MATCH(Lignes_1[[#This Row],[Rôle ou catégorie]],Referentiel[[Entrée]],0)),"?")) -> 0 | N8: =IF(Lignes_1[[#This Row],[Rôle ou catégorie]]="","",IF(Lignes_1[[#This Row],[Type]]="Main-d’œuvre",Lignes_1[[#This Row],[Quantité]]*Lignes_1[[#This Row],[Heures]],0)) -> 0 | O8: =IF(Lignes_1[[#This Row],[Rôle ou catégorie]]="","",IF(Lignes_1[[#This Row],[Type]]="Main-d’œuvre",Lignes_1[[#This Row],[Quantité]]*Lignes_1[[#This Row],[Heures]]*Lignes_1[[#This Row],[Taux horaire]],0)) -> 0 | P8: =IF(Lignes_1[[#This Row],[Rôle ou catégorie]]="","",IF(OR(Lignes_1[[#This Row],[Type]]="Hors main-d’œuvre",Lignes_1[[#This Row],[Type]]="Provision"),Lignes_1[[#This Row],[Quantité]]*Lignes_1[[#This Row],[Débours unitaire]],0)) -> 0 | Q8: =IF(Lignes_1[[#This Row],[Rôle ou catégorie]]="","",Lignes_1[[#This Row],[Main-d’œuvre]]+Lignes_1[[#This Row],[Débours]]) -> 0 | T8: =IF(Lignes_1[[#This Row],[Rôle ou catégorie]]="","",IFERROR(INDEX(Referentiel[[Type de nature]],MATCH(Lignes_1[[#This Row],[Rôle ou catégorie]],Referentiel[[Entrée]],0)),"?")) -> 0
B9: =IF(Lignes_1[[#This Row],[Tâche]]="","",IFERROR(INDEX(Taches[[Description]],MATCH(Lignes_1[[#This Row],[Tâche]],Taches[[Entrée]],0)),"")) -> 0 | J9: =IF(Lignes_1[[#This Row],[Rôle ou catégorie]]="","",IFERROR(INDEX(Referentiel[[Nature]],MATCH(Lignes_1[[#This Row],[Rôle ou catégorie]],Referentiel[[Entrée]],0)),"?")) -> 0 | K9: =IF(Lignes_1[[#This Row],[Rôle ou catégorie]]="","",IFERROR(INDEX(Referentiel[[Code comptable]],MATCH(Lignes_1[[#This Row],[Rôle ou catégorie]],Referentiel[[Entrée]],0)),"?")) -> 0 | L9: =IF(Lignes_1[[#This Row],[Rôle ou catégorie]]="","",IFERROR(INDEX(Referentiel[[Service]],MATCH(Lignes_1[[#This Row],[Rôle ou catégorie]],Referentiel[[Entrée]],0)),"?")&"") -> 0 | M9: =IF(Lignes_1[[#This Row],[Rôle ou catégorie]]="","",IFERROR(INDEX(Referentiel[[Taux horaire]],MATCH(Lignes_1[[#This Row],[Rôle ou catégorie]],Referentiel[[Entrée]],0)),"?")) -> 0 | N9: =IF(Lignes_1[[#This Row],[Rôle ou catégorie]]="","",IF(Lignes_1[[#This Row],[Type]]="Main-d’œuvre",Lignes_1[[#This Row],[Quantité]]*Lignes_1[[#This Row],[Heures]],0)) -> 0 | O9: =IF(Lignes_1[[#This Row],[Rôle ou catégorie]]="","",IF(Lignes_1[[#This Row],[Type]]="Main-d’œuvre",Lignes_1[[#This Row],[Quantité]]*Lignes_1[[#This Row],[Heures]]*Lignes_1[[#This Row],[Taux horaire]],0)) -> 0 | P9: =IF(Lignes_1[[#This Row],[Rôle ou catégorie]]="","",IF(OR(Lignes_1[[#This Row],[Type]]="Hors main-d’œuvre",Lignes_1[[#This Row],[Type]]="Provision"),Lignes_1[[#This Row],[Quantité]]*Lignes_1[[#This Row],[Débours unitaire]],0)) -> 0 | Q9: =IF(Lignes_1[[#This Row],[Rôle ou catégorie]]="","",Lignes_1[[#This Row],[Main-d’œuvre]]+Lignes_1[[#This Row],[Débours]]) -> 0 | T9: =IF(Lignes_1[[#This Row],[Rôle ou catégorie]]="","",IFERROR(INDEX(Referentiel[[Type de nature]],MATCH(Lignes_1[[#This Row],[Rôle ou catégorie]],Referentiel[[Entrée]],0)),"?")) -> 0
B10: =IF(Lignes_1[[#This Row],[Tâche]]="","",IFERROR(INDEX(Taches[[Description]],MATCH(Lignes_1[[#This Row],[Tâche]],Taches[[Entrée]],0)),"")) -> 0 | J10: =IF(Lignes_1[[#This Row],[Rôle ou catégorie]]="","",IFERROR(INDEX(Referentiel[[Nature]],MATCH(Lignes_1[[#This Row],[Rôle ou catégorie]],Referentiel[[Entrée]],0)),"?")) -> 0 | K10: =IF(Lignes_1[[#This Row],[Rôle ou catégorie]]="","",IFERROR(INDEX(Referentiel[[Code comptable]],MATCH(Lignes_1[[#This Row],[Rôle ou catégorie]],Referentiel[[Entrée]],0)),"?")) -> 0 | L10: =IF(Lignes_1[[#This Row],[Rôle ou catégorie]]="","",IFERROR(INDEX(Referentiel[[Service]],MATCH(Lignes_1[[#This Row],[Rôle ou catégorie]],Referentiel[[Entrée]],0)),"?")&"") -> 0 | M10: =IF(Lignes_1[[#This Row],[Rôle ou catégorie]]="","",IFERROR(INDEX(Referentiel[[Taux horaire]],MATCH(Lignes_1[[#This Row],[Rôle ou catégorie]],Referentiel[[Entrée]],0)),"?")) -> 0 | N10: =IF(Lignes_1[[#This Row],[Rôle ou catégorie]]="","",IF(Lignes_1[[#This Row],[Type]]="Main-d’œuvre",Lignes_1[[#This Row],[Quantité]]*Lignes_1[[#This Row],[Heures]],0)) -> 0 | O10: =IF(Lignes_1[[#This Row],[Rôle ou catégorie]]="","",IF(Lignes_1[[#This Row],[Type]]="Main-d’œuvre",Lignes_1[[#This Row],[Quantité]]*Lignes_1[[#This Row],[Heures]]*Lignes_1[[#This Row],[Taux horaire]],0)) -> 0 | P10: =IF(Lignes_1[[#This Row],[Rôle ou catégorie]]="","",IF(OR(Lignes_1[[#This Row],[Type]]="Hors main-d’œuvre",Lignes_1[[#This Row],[Type]]="Provision"),Lignes_1[[#This Row],[Quantité]]*Lignes_1[[#This Row],[Débours unitaire]],0)) -> 0 | Q10: =IF(Lignes_1[[#This Row],[Rôle ou catégorie]]="","",Lignes_1[[#This Row],[Main-d’œuvre]]+Lignes_1[[#This Row],[Débours]]) -> 0 | T10: =IF(Lignes_1[[#This Row],[Rôle ou catégorie]]="","",IFERROR(INDEX(Referentiel[[Type de nature]],MATCH(Lignes_1[[#This Row],[Rôle ou catégorie]],Referentiel[[Entrée]],0)),"?")) -> 0
B11: =IF(Lignes_1[[#This Row],[Tâche]]="","",IFERROR(INDEX(Taches[[Description]],MATCH(Lignes_1[[#This Row],[Tâche]],Taches[[Entrée]],0)),"")) -> 0 | J11: =IF(Lignes_1[[#This Row],[Rôle ou catégorie]]="","",IFERROR(INDEX(Referentiel[[Nature]],MATCH(Lignes_1[[#This Row],[Rôle ou catégorie]],Referentiel[[Entrée]],0)),"?")) -> 0 | K11: =IF(Lignes_1[[#This Row],[Rôle ou catégorie]]="","",IFERROR(INDEX(Referentiel[[Code comptable]],MATCH(Lignes_1[[#This Row],[Rôle ou catégorie]],Referentiel[[Entrée]],0)),"?")) -> 0 | L11: =IF(Lignes_1[[#This Row],[Rôle ou catégorie]]="","",IFERROR(INDEX(Referentiel[[Service]],MATCH(Lignes_1[[#This Row],[Rôle ou catégorie]],Referentiel[[Entrée]],0)),"?")&"") -> 0 | M11: =IF(Lignes_1[[#This Row],[Rôle ou catégorie]]="","",IFERROR(INDEX(Referentiel[[Taux horaire]],MATCH(Lignes_1[[#This Row],[Rôle ou catégorie]],Referentiel[[Entrée]],0)),"?")) -> 0 | N11: =IF(Lignes_1[[#This Row],[Rôle ou catégorie]]="","",IF(Lignes_1[[#This Row],[Type]]="Main-d’œuvre",Lignes_1[[#This Row],[Quantité]]*Lignes_1[[#This Row],[Heures]],0)) -> 0 | O11: =IF(Lignes_1[[#This Row],[Rôle ou catégorie]]="","",IF(Lignes_1[[#This Row],[Type]]="Main-d’œuvre",Lignes_1[[#This Row],[Quantité]]*Lignes_1[[#This Row],[Heures]]*Lignes_1[[#This Row],[Taux horaire]],0)) -> 0 | P11: =IF(Lignes_1[[#This Row],[Rôle ou catégorie]]="","",IF(OR(Lignes_1[[#This Row],[Type]]="Hors main-d’œuvre",Lignes_1[[#This Row],[Type]]="Provision"),Lignes_1[[#This Row],[Quantité]]*Lignes_1[[#This Row],[Débours unitaire]],0)) -> 0 | Q11: =IF(Lignes_1[[#This Row],[Rôle ou catégorie]]="","",Lignes_1[[#This Row],[Main-d’œuvre]]+Lignes_1[[#This Row],[Débours]]) -> 0 | T11: =IF(Lignes_1[[#This Row],[Rôle ou catégorie]]="","",IFERROR(INDEX(Referentiel[[Type de nature]],MATCH(Lignes_1[[#This Row],[Rôle ou catégorie]],Referentiel[[Entrée]],0)),"?")) -> 0
B12: =IF(Lignes_1[[#This Row],[Tâche]]="","",IFERROR(INDEX(Taches[[Description]],MATCH(Lignes_1[[#This Row],[Tâche]],Taches[[Entrée]],0)),"")) -> 0 | J12: =IF(Lignes_1[[#This Row],[Rôle ou catégorie]]="","",IFERROR(INDEX(Referentiel[[Nature]],MATCH(Lignes_1[[#This Row],[Rôle ou catégorie]],Referentiel[[Entrée]],0)),"?")) -> 0 | K12: =IF(Lignes_1[[#This Row],[Rôle ou catégorie]]="","",IFERROR(INDEX(Referentiel[[Code comptable]],MATCH(Lignes_1[[#This Row],[Rôle ou catégorie]],Referentiel[[Entrée]],0)),"?")) -> 0 | L12: =IF(Lignes_1[[#This Row],[Rôle ou catégorie]]="","",IFERROR(INDEX(Referentiel[[Service]],MATCH(Lignes_1[[#This Row],[Rôle ou catégorie]],Referentiel[[Entrée]],0)),"?")&"") -> 0 | M12: =IF(Lignes_1[[#This Row],[Rôle ou catégorie]]="","",IFERROR(INDEX(Referentiel[[Taux horaire]],MATCH(Lignes_1[[#This Row],[Rôle ou catégorie]],Referentiel[[Entrée]],0)),"?")) -> 0 | N12: =IF(Lignes_1[[#This Row],[Rôle ou catégorie]]="","",IF(Lignes_1[[#This Row],[Type]]="Main-d’œuvre",Lignes_1[[#This Row],[Quantité]]*Lignes_1[[#This Row],[Heures]],0)) -> 0 | O12: =IF(Lignes_1[[#This Row],[Rôle ou catégorie]]="","",IF(Lignes_1[[#This Row],[Type]]="Main-d’œuvre",Lignes_1[[#This Row],[Quantité]]*Lignes_1[[#This Row],[Heures]]*Lignes_1[[#This Row],[Taux horaire]],0)) -> 0 | P12: =IF(Lignes_1[[#This Row],[Rôle ou catégorie]]="","",IF(OR(Lignes_1[[#This Row],[Type]]="Hors main-d’œuvre",Lignes_1[[#This Row],[Type]]="Provision"),Lignes_1[[#This Row],[Quantité]]*Lignes_1[[#This Row],[Débours unitaire]],0)) -> 0 | Q12: =IF(Lignes_1[[#This Row],[Rôle ou catégorie]]="","",Lignes_1[[#This Row],[Main-d’œuvre]]+Lignes_1[[#This Row],[Débours]]) -> 0 | T12: =IF(Lignes_1[[#This Row],[Rôle ou catégorie]]="","",IFERROR(INDEX(Referentiel[[Type de nature]],MATCH(Lignes_1[[#This Row],[Rôle ou catégorie]],Referentiel[[Entrée]],0)),"?")) -> 0
B13: =IF(Lignes_1[[#This Row],[Tâche]]="","",IFERROR(INDEX(Taches[[Description]],MATCH(Lignes_1[[#This Row],[Tâche]],Taches[[Entrée]],0)),"")) -> 0 | J13: =IF(Lignes_1[[#This Row],[Rôle ou catégorie]]="","",IFERROR(INDEX(Referentiel[[Nature]],MATCH(Lignes_1[[#This Row],[Rôle ou catégorie]],Referentiel[[Entrée]],0)),"?")) -> 0 | K13: =IF(Lignes_1[[#This Row],[Rôle ou catégorie]]="","",IFERROR(INDEX(Referentiel[[Code comptable]],MATCH(Lignes_1[[#This Row],[Rôle ou catégorie]],Referentiel[[Entrée]],0)),"?")) -> 0 | L13: =IF(Lignes_1[[#This Row],[Rôle ou catégorie]]="","",IFERROR(INDEX(Referentiel[[Service]],MATCH(Lignes_1[[#This Row],[Rôle ou catégorie]],Referentiel[[Entrée]],0)),"?")&"") -> 0 | M13: =IF(Lignes_1[[#This Row],[Rôle ou catégorie]]="","",IFERROR(INDEX(Referentiel[[Taux horaire]],MATCH(Lignes_1[[#This Row],[Rôle ou catégorie]],Referentiel[[Entrée]],0)),"?")) -> 0 | N13: =IF(Lignes_1[[#This Row],[Rôle ou catégorie]]="","",IF(Lignes_1[[#This Row],[Type]]="Main-d’œuvre",Lignes_1[[#This Row],[Quantité]]*Lignes_1[[#This Row],[Heures]],0)) -> 0 | O13: =IF(Lignes_1[[#This Row],[Rôle ou catégorie]]="","",IF(Lignes_1[[#This Row],[Type]]="Main-d’œuvre",Lignes_1[[#This Row],[Quantité]]*Lignes_1[[#This Row],[Heures]]*Lignes_1[[#This Row],[Taux horaire]],0)) -> 0 | P13: =IF(Lignes_1[[#This Row],[Rôle ou catégorie]]="","",IF(OR(Lignes_1[[#This Row],[Type]]="Hors main-d’œuvre",Lignes_1[[#This Row],[Type]]="Provision"),Lignes_1[[#This Row],[Quantité]]*Lignes_1[[#This Row],[Débours unitaire]],0)) -> 0 | Q13: =IF(Lignes_1[[#This Row],[Rôle ou catégorie]]="","",Lignes_1[[#This Row],[Main-d’œuvre]]+Lignes_1[[#This Row],[Débours]]) -> 0 | T13: =IF(Lignes_1[[#This Row],[Rôle ou catégorie]]="","",IFERROR(INDEX(Referentiel[[Type de nature]],MATCH(Lignes_1[[#This Row],[Rôle ou catégorie]],Referentiel[[Entrée]],0)),"?")) -> 0
B14: =IF(Lignes_1[[#This Row],[Tâche]]="","",IFERROR(INDEX(Taches[[Description]],MATCH(Lignes_1[[#This Row],[Tâche]],Taches[[Entrée]],0)),"")) -> 0 | J14: =IF(Lignes_1[[#This Row],[Rôle ou catégorie]]="","",IFERROR(INDEX(Referentiel[[Nature]],MATCH(Lignes_1[[#This Row],[Rôle ou catégorie]],Referentiel[[Entrée]],0)),"?")) -> 0 | K14: =IF(Lignes_1[[#This Row],[Rôle ou catégorie]]="","",IFERROR(INDEX(Referentiel[[Code comptable]],MATCH(Lignes_1[[#This Row],[Rôle ou catégorie]],Referentiel[[Entrée]],0)),"?")) -> 0 | L14: =IF(Lignes_1[[#This Row],[Rôle ou catégorie]]="","",IFERROR(INDEX(Referentiel[[Service]],MATCH(Lignes_1[[#This Row],[Rôle ou catégorie]],Referentiel[[Entrée]],0)),"?")&"") -> 0 | M14: =IF(Lignes_1[[#This Row],[Rôle ou catégorie]]="","",IFERROR(INDEX(Referentiel[[Taux horaire]],MATCH(Lignes_1[[#This Row],[Rôle ou catégorie]],Referentiel[[Entrée]],0)),"?")) -> 0 | N14: =IF(Lignes_1[[#This Row],[Rôle ou catégorie]]="","",IF(Lignes_1[[#This Row],[Type]]="Main-d’œuvre",Lignes_1[[#This Row],[Quantité]]*Lignes_1[[#This Row],[Heures]],0)) -> 0 | O14: =IF(Lignes_1[[#This Row],[Rôle ou catégorie]]="","",IF(Lignes_1[[#This Row],[Type]]="Main-d’œuvre",Lignes_1[[#This Row],[Quantité]]*Lignes_1[[#This Row],[Heures]]*Lignes_1[[#This Row],[Taux horaire]],0)) -> 0 | P14: =IF(Lignes_1[[#This Row],[Rôle ou catégorie]]="","",IF(OR(Lignes_1[[#This Row],[Type]]="Hors main-d’œuvre",Lignes_1[[#This Row],[Type]]="Provision"),Lignes_1[[#This Row],[Quantité]]*Lignes_1[[#This Row],[Débours unitaire]],0)) -> 0 | Q14: =IF(Lignes_1[[#This Row],[Rôle ou catégorie]]="","",Lignes_1[[#This Row],[Main-d’œuvre]]+Lignes_1[[#This Row],[Débours]]) -> 0 | T14: =IF(Lignes_1[[#This Row],[Rôle ou catégorie]]="","",IFERROR(INDEX(Referentiel[[Type de nature]],MATCH(Lignes_1[[#This Row],[Rôle ou catégorie]],Referentiel[[Entrée]],0)),"?")) -> 0
... B32: =IF(Lignes_1[[#This Row],[Tâche]]="","",IFERROR(INDEX(Taches[[Description]],MATCH(Lignes_1[[#This Row],[Tâche]],Taches[[Entrée]],0)),"")) -> 0 | J32: =IF(Lignes_1[[#This Row],[Rôle ou catégorie]]="","",IFERROR(INDEX(Referentiel[[Nature]],MATCH(Lignes_1[[#This Row],[Rôle ou catégorie]],Referentiel[[Entrée]],0)),"?")) -> 0 | K32: =IF(Lignes_1[[#This Row],[Rôle ou catégorie]]="","",IFERROR(INDEX(Referentiel[[Code comptable]],MATCH(Lignes_1[[#This Row],[Rôle ou catégorie]],Referentiel[[Entrée]],0)),"?")) -> 0 | L32: =IF(Lignes_1[[#This Row],[Rôle ou catégorie]]="","",IFERROR(INDEX(Referentiel[[Service]],MATCH(Lignes_1[[#This Row],[Rôle ou catégorie]],Referentiel[[Entrée]],0)),"?")&"") -> 0 | M32: =IF(Lignes_1[[#This Row],[Rôle ou catégorie]]="","",IFERROR(INDEX(Referentiel[[Taux horaire]],MATCH(Lignes_1[[#This Row],[Rôle ou catégorie]],Referentiel[[Entrée]],0)),"?")) -> 0 | N32: =IF(Lignes_1[[#This Row],[Rôle ou catégorie]]="","",IF(Lignes_1[[#This Row],[Type]]="Main-d’œuvre",Lignes_1[[#This Row],[Quantité]]*Lignes_1[[#This Row],[Heures]],0)) -> 0 | O32: =IF(Lignes_1[[#This Row],[Rôle ou catégorie]]="","",IF(Lignes_1[[#This Row],[Type]]="Main-d’œuvre",Lignes_1[[#This Row],[Quantité]]*Lignes_1[[#This Row],[Heures]]*Lignes_1[[#This Row],[Taux horaire]],0)) -> 0 | P32: =IF(Lignes_1[[#This Row],[Rôle ou catégorie]]="","",IF(OR(Lignes_1[[#This Row],[Type]]="Hors main-d’œuvre",Lignes_1[[#This Row],[Type]]="Provision"),Lignes_1[[#This Row],[Quantité]]*Lignes_1[[#This Row],[Débours unitaire]],0)) -> 0 | Q32: =IF(Lignes_1[[#This Row],[Rôle ou catégorie]]="","",Lignes_1[[#This Row],[Main-d’œuvre]]+Lignes_1[[#This Row],[Débours]]) -> 0 | T32: =IF(Lignes_1[[#This Row],[Rôle ou catégorie]]="","",IFERROR(INDEX(Referentiel[[Type de nature]],MATCH(Lignes_1[[#This Row],[Rôle ou catégorie]],Referentiel[[Entrée]],0)),"?")) -> 0
A33: Total | N33: =SUBTOTAL(109,Lignes_1[[Heures totales]]) -> 0 | O33: =SUBTOTAL(109,Lignes_1[[Main-d’œuvre]]) -> 0 | P33: =SUBTOTAL(109,Lignes_1[[Débours]]) -> 0 | Q33: =SUBTOTAL(109,Lignes_1[[Montant]]) -> 0 | R33: =SUBTOTAL(109,Lignes_1[[Montant Waterfall]]) -> 0

Sheet 2.1 Essais sur site
A1: Tâche | B1: Description de la tâche | C1: Rôle ou catégorie | D1: Désignation | E1: Quantité | F1: Heures | G1: Débours unitaire | H1: Délai de paiement (j) | I1: Sous-projet | J1: Nature | K1: Code comptable | L1: Service | M1: Taux horaire | N1: Heures totales | O1: Main-d’œuvre | P1: Débours | Q1: Montant | R1: Montant Waterfall | S1: ID ligne | T1: Type
A2: 2.1.1 Essais | B2: =IF(Lignes_2_1[[#This Row],[Tâche]]="","",IFERROR(INDEX(Taches[[Description]],MATCH(Lignes_2_1[[#This Row],[Tâche]],Taches[[Entrée]],0)),"")) -> 0 | C2: Ingénieur qualité A1 (IQ-A1) | E2: 10 | F2: 7.4 | H2: 0 | I2: SP-PRE | J2: =IF(Lignes_2_1[[#This Row],[Rôle ou catégorie]]="","",IFERROR(INDEX(Referentiel[[Nature]],MATCH(Lignes_2_1[[#This Row],[Rôle ou catégorie]],Referentiel[[Entrée]],0)),"?")) -> 0 | K2: =IF(Lignes_2_1[[#This Row],[Rôle ou catégorie]]="","",IFERROR(INDEX(Referentiel[[Code comptable]],MATCH(Lignes_2_1[[#This Row],[Rôle ou catégorie]],Referentiel[[Entrée]],0)),"?")) -> 0 | L2: =IF(Lignes_2_1[[#This Row],[Rôle ou catégorie]]="","",IFERROR(INDEX(Referentiel[[Service]],MATCH(Lignes_2_1[[#This Row],[Rôle ou catégorie]],Referentiel[[Entrée]],0)),"?")&"") -> 0 | M2: =IF(Lignes_2_1[[#This Row],[Rôle ou catégorie]]="","",IFERROR(INDEX(Referentiel[[Taux horaire]],MATCH(Lignes_2_1[[#This Row],[Rôle ou catégorie]],Referentiel[[Entrée]],0)),"?")) -> 0 | N2: =IF(Lignes_2_1[[#This Row],[Rôle ou catégorie]]="","",IF(Lignes_2_1[[#This Row],[Type]]="Main-d’œuvre",Lignes_2_1[[#This Row],[Quantité]]*Lignes_2_1[[#This Row],[Heures]],0)) -> 0 | O2: =IF(Lignes_2_1[[#This Row],[Rôle ou catégorie]]="","",IF(Lignes_2_1[[#This Row],[Type]]="Main-d’œuvre",Lignes_2_1[[#This Row],[Quantité]]*Lignes_2_1[[#This Row],[Heures]]*Lignes_2_1[[#This Row],[Taux horaire]],0)) -> 0 | P2: =IF(Lignes_2_1[[#This Row],[Rôle ou catégorie]]="","",IF(OR(Lignes_2_1[[#This Row],[Type]]="Hors main-d’œuvre",Lignes_2_1[[#This Row],[Type]]="Provision"),Lignes_2_1[[#This Row],[Quantité]]*Lignes_2_1[[#This Row],[Débours unitaire]],0)) -> 0 | Q2: =IF(Lignes_2_1[[#This Row],[Rôle ou catégorie]]="","",Lignes_2_1[[#This Row],[Main-d’œuvre]]+Lignes_2_1[[#This Row],[Débours]]) -> 0 | R2: 4528.8 | S2: l-0401 | T2: =IF(Lignes_2_1[[#This Row],[Rôle ou catégorie]]="","",IFERROR(INDEX(Referentiel[[Type de nature]],MATCH(Lignes_2_1[[#This Row],[Rôle ou catégorie]],Referentiel[[Entrée]],0)),"?")) -> 0
A3: 2.1.1 Essais | B3: =IF(Lignes_2_1[[#This Row],[Tâche]]="","",IFERROR(INDEX(Taches[[Description]],MATCH(Lignes_2_1[[#This Row],[Tâche]],Taches[[Entrée]],0)),"")) -> 0 | C3: Ingénieur carte (ING-CARTE) | E3: 10 | F3: 7.4 | H3: 0 | I3: SP-PRE | J3: =IF(Lignes_2_1[[#This Row],[Rôle ou catégorie]]="","",IFERROR(INDEX(Referentiel[[Nature]],MATCH(Lignes_2_1[[#This Row],[Rôle ou catégorie]],Referentiel[[Entrée]],0)),"?")) -> 0 | K3: =IF(Lignes_2_1[[#This Row],[Rôle ou catégorie]]="","",IFERROR(INDEX(Referentiel[[Code comptable]],MATCH(Lignes_2_1[[#This Row],[Rôle ou catégorie]],Referentiel[[Entrée]],0)),"?")) -> 0 | L3: =IF(Lignes_2_1[[#This Row],[Rôle ou catégorie]]="","",IFERROR(INDEX(Referentiel[[Service]],MATCH(Lignes_2_1[[#This Row],[Rôle ou catégorie]],Referentiel[[Entrée]],0)),"?")&"") -> 0 | M3: =IF(Lignes_2_1[[#This Row],[Rôle ou catégorie]]="","",IFERROR(INDEX(Referentiel[[Taux horaire]],MATCH(Lignes_2_1[[#This Row],[Rôle ou catégorie]],Referentiel[[Entrée]],0)),"?")) -> 0 | N3: =IF(Lignes_2_1[[#This Row],[Rôle ou catégorie]]="","",IF(Lignes_2_1[[#This Row],[Type]]="Main-d’œuvre",Lignes_2_1[[#This Row],[Quantité]]*Lignes_2_1[[#This Row],[Heures]],0)) -> 0 | O3: =IF(Lignes_2_1[[#This Row],[Rôle ou catégorie]]="","",IF(Lignes_2_1[[#This Row],[Type]]="Main-d’œuvre",Lignes_2_1[[#This Row],[Quantité]]*Lignes_2_1[[#This Row],[Heures]]*Lignes_2_1[[#This Row],[Taux horaire]],0)) -> 0 | P3: =IF(Lignes_2_1[[#This Row],[Rôle ou catégorie]]="","",IF(OR(Lignes_2_1[[#This Row],[Type]]="Hors main-d’œuvre",Lignes_2_1[[#This Row],[Type]]="Provision"),Lignes_2_1[[#This Row],[Quantité]]*Lignes_2_1[[#This Row],[Débours unitaire]],0)) -> 0 | Q3: =IF(Lignes_2_1[[#This Row],[Rôle ou catégorie]]="","",Lignes_2_1[[#This Row],[Main-d’œuvre]]+Lignes_2_1[[#This Row],[Débours]]) -> 0 | R3: 4528.8 | S3: l-0402 | T3: =IF(Lignes_2_1[[#This Row],[Rôle ou catégorie]]="","",IFERROR(INDEX(Referentiel[[Type de nature]],MATCH(Lignes_2_1[[#This Row],[Rôle ou catégorie]],Referentiel[[Entrée]],0)),"?")) -> 0
B4: =IF(Lignes_2_1[[#This Row],[Tâche]]="","",IFERROR(INDEX(Taches[[Description]],MATCH(Lignes_2_1[[#This Row],[Tâche]],Taches[[Entrée]],0)),"")) -> 0 | J4: =IF(Lignes_2_1[[#This Row],[Rôle ou catégorie]]="","",IFERROR(INDEX(Referentiel[[Nature]],MATCH(Lignes_2_1[[#This Row],[Rôle ou catégorie]],Referentiel[[Entrée]],0)),"?")) -> 0 | K4: =IF(Lignes_2_1[[#This Row],[Rôle ou catégorie]]="","",IFERROR(INDEX(Referentiel[[Code comptable]],MATCH(Lignes_2_1[[#This Row],[Rôle ou catégorie]],Referentiel[[Entrée]],0)),"?")) -> 0 | L4: =IF(Lignes_2_1[[#This Row],[Rôle ou catégorie]]="","",IFERROR(INDEX(Referentiel[[Service]],MATCH(Lignes_2_1[[#This Row],[Rôle ou catégorie]],Referentiel[[Entrée]],0)),"?")&"") -> 0 | M4: =IF(Lignes_2_1[[#This Row],[Rôle ou catégorie]]="","",IFERROR(INDEX(Referentiel[[Taux horaire]],MATCH(Lignes_2_1[[#This Row],[Rôle ou catégorie]],Referentiel[[Entrée]],0)),"?")) -> 0 | N4: =IF(Lignes_2_1[[#This Row],[Rôle ou catégorie]]="","",IF(Lignes_2_1[[#This Row],[Type]]="Main-d’œuvre",Lignes_2_1[[#This Row],[Quantité]]*Lignes_2_1[[#This Row],[Heures]],0)) -> 0 | O4: =IF(Lignes_2_1[[#This Row],[Rôle ou catégorie]]="","",IF(Lignes_2_1[[#This Row],[Type]]="Main-d’œuvre",Lignes_2_1[[#This Row],[Quantité]]*Lignes_2_1[[#This Row],[Heures]]*Lignes_2_1[[#This Row],[Taux horaire]],0)) -> 0 | P4: =IF(Lignes_2_1[[#This Row],[Rôle ou catégorie]]="","",IF(OR(Lignes_2_1[[#This Row],[Type]]="Hors main-d’œuvre",Lignes_2_1[[#This Row],[Type]]="Provision"),Lignes_2_1[[#This Row],[Quantité]]*Lignes_2_1[[#This Row],[Débours unitaire]],0)) -> 0 | Q4: =IF(Lignes_2_1[[#This Row],[Rôle ou catégorie]]="","",Lignes_2_1[[#This Row],[Main-d’œuvre]]+Lignes_2_1[[#This Row],[Débours]]) -> 0 | T4: =IF(Lignes_2_1[[#This Row],[Rôle ou catégorie]]="","",IFERROR(INDEX(Referentiel[[Type de nature]],MATCH(Lignes_2_1[[#This Row],[Rôle ou catégorie]],Referentiel[[Entrée]],0)),"?")) -> 0
B5: =IF(Lignes_2_1[[#This Row],[Tâche]]="","",IFERROR(INDEX(Taches[[Description]],MATCH(Lignes_2_1[[#This Row],[Tâche]],Taches[[Entrée]],0)),"")) -> 0 | J5: =IF(Lignes_2_1[[#This Row],[Rôle ou catégorie]]="","",IFERROR(INDEX(Referentiel[[Nature]],MATCH(Lignes_2_1[[#This Row],[Rôle ou catégorie]],Referentiel[[Entrée]],0)),"?")) -> 0 | K5: =IF(Lignes_2_1[[#This Row],[Rôle ou catégorie]]="","",IFERROR(INDEX(Referentiel[[Code comptable]],MATCH(Lignes_2_1[[#This Row],[Rôle ou catégorie]],Referentiel[[Entrée]],0)),"?")) -> 0 | L5: =IF(Lignes_2_1[[#This Row],[Rôle ou catégorie]]="","",IFERROR(INDEX(Referentiel[[Service]],MATCH(Lignes_2_1[[#This Row],[Rôle ou catégorie]],Referentiel[[Entrée]],0)),"?")&"") -> 0 | M5: =IF(Lignes_2_1[[#This Row],[Rôle ou catégorie]]="","",IFERROR(INDEX(Referentiel[[Taux horaire]],MATCH(Lignes_2_1[[#This Row],[Rôle ou catégorie]],Referentiel[[Entrée]],0)),"?")) -> 0 | N5: =IF(Lignes_2_1[[#This Row],[Rôle ou catégorie]]="","",IF(Lignes_2_1[[#This Row],[Type]]="Main-d’œuvre",Lignes_2_1[[#This Row],[Quantité]]*Lignes_2_1[[#This Row],[Heures]],0)) -> 0 | O5: =IF(Lignes_2_1[[#This Row],[Rôle ou catégorie]]="","",IF(Lignes_2_1[[#This Row],[Type]]="Main-d’œuvre",Lignes_2_1[[#This Row],[Quantité]]*Lignes_2_1[[#This Row],[Heures]]*Lignes_2_1[[#This Row],[Taux horaire]],0)) -> 0 | P5: =IF(Lignes_2_1[[#This Row],[Rôle ou catégorie]]="","",IF(OR(Lignes_2_1[[#This Row],[Type]]="Hors main-d’œuvre",Lignes_2_1[[#This Row],[Type]]="Provision"),Lignes_2_1[[#This Row],[Quantité]]*Lignes_2_1[[#This Row],[Débours unitaire]],0)) -> 0 | Q5: =IF(Lignes_2_1[[#This Row],[Rôle ou catégorie]]="","",Lignes_2_1[[#This Row],[Main-d’œuvre]]+Lignes_2_1[[#This Row],[Débours]]) -> 0 | T5: =IF(Lignes_2_1[[#This Row],[Rôle ou catégorie]]="","",IFERROR(INDEX(Referentiel[[Type de nature]],MATCH(Lignes_2_1[[#This Row],[Rôle ou catégorie]],Referentiel[[Entrée]],0)),"?")) -> 0
B6: =IF(Lignes_2_1[[#This Row],[Tâche]]="","",IFERROR(INDEX(Taches[[Description]],MATCH(Lignes_2_1[[#This Row],[Tâche]],Taches[[Entrée]],0)),"")) -> 0 | J6: =IF(Lignes_2_1[[#This Row],[Rôle ou catégorie]]="","",IFERROR(INDEX(Referentiel[[Nature]],MATCH(Lignes_2_1[[#This Row],[Rôle ou catégorie]],Referentiel[[Entrée]],0)),"?")) -> 0 | K6: =IF(Lignes_2_1[[#This Row],[Rôle ou catégorie]]="","",IFERROR(INDEX(Referentiel[[Code comptable]],MATCH(Lignes_2_1[[#This Row],[Rôle ou catégorie]],Referentiel[[Entrée]],0)),"?")) -> 0 | L6: =IF(Lignes_2_1[[#This Row],[Rôle ou catégorie]]="","",IFERROR(INDEX(Referentiel[[Service]],MATCH(Lignes_2_1[[#This Row],[Rôle ou catégorie]],Referentiel[[Entrée]],0)),"?")&"") -> 0 | M6: =IF(Lignes_2_1[[#This Row],[Rôle ou catégorie]]="","",IFERROR(INDEX(Referentiel[[Taux horaire]],MATCH(Lignes_2_1[[#This Row],[Rôle ou catégorie]],Referentiel[[Entrée]],0)),"?")) -> 0 | N6: =IF(Lignes_2_1[[#This Row],[Rôle ou catégorie]]="","",IF(Lignes_2_1[[#This Row],[Type]]="Main-d’œuvre",Lignes_2_1[[#This Row],[Quantité]]*Lignes_2_1[[#This Row],[Heures]],0)) -> 0 | O6: =IF(Lignes_2_1[[#This Row],[Rôle ou catégorie]]="","",IF(Lignes_2_1[[#This Row],[Type]]="Main-d’œuvre",Lignes_2_1[[#This Row],[Quantité]]*Lignes_2_1[[#This Row],[Heures]]*Lignes_2_1[[#This Row],[Taux horaire]],0)) -> 0 | P6: =IF(Lignes_2_1[[#This Row],[Rôle ou catégorie]]="","",IF(OR(Lignes_2_1[[#This Row],[Type]]="Hors main-d’œuvre",Lignes_2_1[[#This Row],[Type]]="Provision"),Lignes_2_1[[#This Row],[Quantité]]*Lignes_2_1[[#This Row],[Débours unitaire]],0)) -> 0 | Q6: =IF(Lignes_2_1[[#This Row],[Rôle ou catégorie]]="","",Lignes_2_1[[#This Row],[Main-d’œuvre]]+Lignes_2_1[[#This Row],[Débours]]) -> 0 | T6: =IF(Lignes_2_1[[#This Row],[Rôle ou catégorie]]="","",IFERROR(INDEX(Referentiel[[Type de nature]],MATCH(Lignes_2_1[[#This Row],[Rôle ou catégorie]],Referentiel[[Entrée]],0)),"?")) -> 0
B7: =IF(Lignes_2_1[[#This Row],[Tâche]]="","",IFERROR(INDEX(Taches[[Description]],MATCH(Lignes_2_1[[#This Row],[Tâche]],Taches[[Entrée]],0)),"")) -> 0 | J7: =IF(Lignes_2_1[[#This Row],[Rôle ou catégorie]]="","",IFERROR(INDEX(Referentiel[[Nature]],MATCH(Lignes_2_1[[#This Row],[Rôle ou catégorie]],Referentiel[[Entrée]],0)),"?")) -> 0 | K7: =IF(Lignes_2_1[[#This Row],[Rôle ou catégorie]]="","",IFERROR(INDEX(Referentiel[[Code comptable]],MATCH(Lignes_2_1[[#This Row],[Rôle ou catégorie]],Referentiel[[Entrée]],0)),"?")) -> 0 | L7: =IF(Lignes_2_1[[#This Row],[Rôle ou catégorie]]="","",IFERROR(INDEX(Referentiel[[Service]],MATCH(Lignes_2_1[[#This Row],[Rôle ou catégorie]],Referentiel[[Entrée]],0)),"?")&"") -> 0 | M7: =IF(Lignes_2_1[[#This Row],[Rôle ou catégorie]]="","",IFERROR(INDEX(Referentiel[[Taux horaire]],MATCH(Lignes_2_1[[#This Row],[Rôle ou catégorie]],Referentiel[[Entrée]],0)),"?")) -> 0 | N7: =IF(Lignes_2_1[[#This Row],[Rôle ou catégorie]]="","",IF(Lignes_2_1[[#This Row],[Type]]="Main-d’œuvre",Lignes_2_1[[#This Row],[Quantité]]*Lignes_2_1[[#This Row],[Heures]],0)) -> 0 | O7: =IF(Lignes_2_1[[#This Row],[Rôle ou catégorie]]="","",IF(Lignes_2_1[[#This Row],[Type]]="Main-d’œuvre",Lignes_2_1[[#This Row],[Quantité]]*Lignes_2_1[[#This Row],[Heures]]*Lignes_2_1[[#This Row],[Taux horaire]],0)) -> 0 | P7: =IF(Lignes_2_1[[#This Row],[Rôle ou catégorie]]="","",IF(OR(Lignes_2_1[[#This Row],[Type]]="Hors main-d’œuvre",Lignes_2_1[[#This Row],[Type]]="Provision"),Lignes_2_1[[#This Row],[Quantité]]*Lignes_2_1[[#This Row],[Débours unitaire]],0)) -> 0 | Q7: =IF(Lignes_2_1[[#This Row],[Rôle ou catégorie]]="","",Lignes_2_1[[#This Row],[Main-d’œuvre]]+Lignes_2_1[[#This Row],[Débours]]) -> 0 | T7: =IF(Lignes_2_1[[#This Row],[Rôle ou catégorie]]="","",IFERROR(INDEX(Referentiel[[Type de nature]],MATCH(Lignes_2_1[[#This Row],[Rôle ou catégorie]],Referentiel[[Entrée]],0)),"?")) -> 0
B8: =IF(Lignes_2_1[[#This Row],[Tâche]]="","",IFERROR(INDEX(Taches[[Description]],MATCH(Lignes_2_1[[#This Row],[Tâche]],Taches[[Entrée]],0)),"")) -> 0 | J8: =IF(Lignes_2_1[[#This Row],[Rôle ou catégorie]]="","",IFERROR(INDEX(Referentiel[[Nature]],MATCH(Lignes_2_1[[#This Row],[Rôle ou catégorie]],Referentiel[[Entrée]],0)),"?")) -> 0 | K8: =IF(Lignes_2_1[[#This Row],[Rôle ou catégorie]]="","",IFERROR(INDEX(Referentiel[[Code comptable]],MATCH(Lignes_2_1[[#This Row],[Rôle ou catégorie]],Referentiel[[Entrée]],0)),"?")) -> 0 | L8: =IF(Lignes_2_1[[#This Row],[Rôle ou catégorie]]="","",IFERROR(INDEX(Referentiel[[Service]],MATCH(Lignes_2_1[[#This Row],[Rôle ou catégorie]],Referentiel[[Entrée]],0)),"?")&"") -> 0 | M8: =IF(Lignes_2_1[[#This Row],[Rôle ou catégorie]]="","",IFERROR(INDEX(Referentiel[[Taux horaire]],MATCH(Lignes_2_1[[#This Row],[Rôle ou catégorie]],Referentiel[[Entrée]],0)),"?")) -> 0 | N8: =IF(Lignes_2_1[[#This Row],[Rôle ou catégorie]]="","",IF(Lignes_2_1[[#This Row],[Type]]="Main-d’œuvre",Lignes_2_1[[#This Row],[Quantité]]*Lignes_2_1[[#This Row],[Heures]],0)) -> 0 | O8: =IF(Lignes_2_1[[#This Row],[Rôle ou catégorie]]="","",IF(Lignes_2_1[[#This Row],[Type]]="Main-d’œuvre",Lignes_2_1[[#This Row],[Quantité]]*Lignes_2_1[[#This Row],[Heures]]*Lignes_2_1[[#This Row],[Taux horaire]],0)) -> 0 | P8: =IF(Lignes_2_1[[#This Row],[Rôle ou catégorie]]="","",IF(OR(Lignes_2_1[[#This Row],[Type]]="Hors main-d’œuvre",Lignes_2_1[[#This Row],[Type]]="Provision"),Lignes_2_1[[#This Row],[Quantité]]*Lignes_2_1[[#This Row],[Débours unitaire]],0)) -> 0 | Q8: =IF(Lignes_2_1[[#This Row],[Rôle ou catégorie]]="","",Lignes_2_1[[#This Row],[Main-d’œuvre]]+Lignes_2_1[[#This Row],[Débours]]) -> 0 | T8: =IF(Lignes_2_1[[#This Row],[Rôle ou catégorie]]="","",IFERROR(INDEX(Referentiel[[Type de nature]],MATCH(Lignes_2_1[[#This Row],[Rôle ou catégorie]],Referentiel[[Entrée]],0)),"?")) -> 0
B9: =IF(Lignes_2_1[[#This Row],[Tâche]]="","",IFERROR(INDEX(Taches[[Description]],MATCH(Lignes_2_1[[#This Row],[Tâche]],Taches[[Entrée]],0)),"")) -> 0 | J9: =IF(Lignes_2_1[[#This Row],[Rôle ou catégorie]]="","",IFERROR(INDEX(Referentiel[[Nature]],MATCH(Lignes_2_1[[#This Row],[Rôle ou catégorie]],Referentiel[[Entrée]],0)),"?")) -> 0 | K9: =IF(Lignes_2_1[[#This Row],[Rôle ou catégorie]]="","",IFERROR(INDEX(Referentiel[[Code comptable]],MATCH(Lignes_2_1[[#This Row],[Rôle ou catégorie]],Referentiel[[Entrée]],0)),"?")) -> 0 | L9: =IF(Lignes_2_1[[#This Row],[Rôle ou catégorie]]="","",IFERROR(INDEX(Referentiel[[Service]],MATCH(Lignes_2_1[[#This Row],[Rôle ou catégorie]],Referentiel[[Entrée]],0)),"?")&"") -> 0 | M9: =IF(Lignes_2_1[[#This Row],[Rôle ou catégorie]]="","",IFERROR(INDEX(Referentiel[[Taux horaire]],MATCH(Lignes_2_1[[#This Row],[Rôle ou catégorie]],Referentiel[[Entrée]],0)),"?")) -> 0 | N9: =IF(Lignes_2_1[[#This Row],[Rôle ou catégorie]]="","",IF(Lignes_2_1[[#This Row],[Type]]="Main-d’œuvre",Lignes_2_1[[#This Row],[Quantité]]*Lignes_2_1[[#This Row],[Heures]],0)) -> 0 | O9: =IF(Lignes_2_1[[#This Row],[Rôle ou catégorie]]="","",IF(Lignes_2_1[[#This Row],[Type]]="Main-d’œuvre",Lignes_2_1[[#This Row],[Quantité]]*Lignes_2_1[[#This Row],[Heures]]*Lignes_2_1[[#This Row],[Taux horaire]],0)) -> 0 | P9: =IF(Lignes_2_1[[#This Row],[Rôle ou catégorie]]="","",IF(OR(Lignes_2_1[[#This Row],[Type]]="Hors main-d’œuvre",Lignes_2_1[[#This Row],[Type]]="Provision"),Lignes_2_1[[#This Row],[Quantité]]*Lignes_2_1[[#This Row],[Débours unitaire]],0)) -> 0 | Q9: =IF(Lignes_2_1[[#This Row],[Rôle ou catégorie]]="","",Lignes_2_1[[#This Row],[Main-d’œuvre]]+Lignes_2_1[[#This Row],[Débours]]) -> 0 | T9: =IF(Lignes_2_1[[#This Row],[Rôle ou catégorie]]="","",IFERROR(INDEX(Referentiel[[Type de nature]],MATCH(Lignes_2_1[[#This Row],[Rôle ou catégorie]],Referentiel[[Entrée]],0)),"?")) -> 0
B10: =IF(Lignes_2_1[[#This Row],[Tâche]]="","",IFERROR(INDEX(Taches[[Description]],MATCH(Lignes_2_1[[#This Row],[Tâche]],Taches[[Entrée]],0)),"")) -> 0 | J10: =IF(Lignes_2_1[[#This Row],[Rôle ou catégorie]]="","",IFERROR(INDEX(Referentiel[[Nature]],MATCH(Lignes_2_1[[#This Row],[Rôle ou catégorie]],Referentiel[[Entrée]],0)),"?")) -> 0 | K10: =IF(Lignes_2_1[[#This Row],[Rôle ou catégorie]]="","",IFERROR(INDEX(Referentiel[[Code comptable]],MATCH(Lignes_2_1[[#This Row],[Rôle ou catégorie]],Referentiel[[Entrée]],0)),"?")) -> 0 | L10: =IF(Lignes_2_1[[#This Row],[Rôle ou catégorie]]="","",IFERROR(INDEX(Referentiel[[Service]],MATCH(Lignes_2_1[[#This Row],[Rôle ou catégorie]],Referentiel[[Entrée]],0)),"?")&"") -> 0 | M10: =IF(Lignes_2_1[[#This Row],[Rôle ou catégorie]]="","",IFERROR(INDEX(Referentiel[[Taux horaire]],MATCH(Lignes_2_1[[#This Row],[Rôle ou catégorie]],Referentiel[[Entrée]],0)),"?")) -> 0 | N10: =IF(Lignes_2_1[[#This Row],[Rôle ou catégorie]]="","",IF(Lignes_2_1[[#This Row],[Type]]="Main-d’œuvre",Lignes_2_1[[#This Row],[Quantité]]*Lignes_2_1[[#This Row],[Heures]],0)) -> 0 | O10: =IF(Lignes_2_1[[#This Row],[Rôle ou catégorie]]="","",IF(Lignes_2_1[[#This Row],[Type]]="Main-d’œuvre",Lignes_2_1[[#This Row],[Quantité]]*Lignes_2_1[[#This Row],[Heures]]*Lignes_2_1[[#This Row],[Taux horaire]],0)) -> 0 | P10: =IF(Lignes_2_1[[#This Row],[Rôle ou catégorie]]="","",IF(OR(Lignes_2_1[[#This Row],[Type]]="Hors main-d’œuvre",Lignes_2_1[[#This Row],[Type]]="Provision"),Lignes_2_1[[#This Row],[Quantité]]*Lignes_2_1[[#This Row],[Débours unitaire]],0)) -> 0 | Q10: =IF(Lignes_2_1[[#This Row],[Rôle ou catégorie]]="","",Lignes_2_1[[#This Row],[Main-d’œuvre]]+Lignes_2_1[[#This Row],[Débours]]) -> 0 | T10: =IF(Lignes_2_1[[#This Row],[Rôle ou catégorie]]="","",IFERROR(INDEX(Referentiel[[Type de nature]],MATCH(Lignes_2_1[[#This Row],[Rôle ou catégorie]],Referentiel[[Entrée]],0)),"?")) -> 0
B11: =IF(Lignes_2_1[[#This Row],[Tâche]]="","",IFERROR(INDEX(Taches[[Description]],MATCH(Lignes_2_1[[#This Row],[Tâche]],Taches[[Entrée]],0)),"")) -> 0 | J11: =IF(Lignes_2_1[[#This Row],[Rôle ou catégorie]]="","",IFERROR(INDEX(Referentiel[[Nature]],MATCH(Lignes_2_1[[#This Row],[Rôle ou catégorie]],Referentiel[[Entrée]],0)),"?")) -> 0 | K11: =IF(Lignes_2_1[[#This Row],[Rôle ou catégorie]]="","",IFERROR(INDEX(Referentiel[[Code comptable]],MATCH(Lignes_2_1[[#This Row],[Rôle ou catégorie]],Referentiel[[Entrée]],0)),"?")) -> 0 | L11: =IF(Lignes_2_1[[#This Row],[Rôle ou catégorie]]="","",IFERROR(INDEX(Referentiel[[Service]],MATCH(Lignes_2_1[[#This Row],[Rôle ou catégorie]],Referentiel[[Entrée]],0)),"?")&"") -> 0 | M11: =IF(Lignes_2_1[[#This Row],[Rôle ou catégorie]]="","",IFERROR(INDEX(Referentiel[[Taux horaire]],MATCH(Lignes_2_1[[#This Row],[Rôle ou catégorie]],Referentiel[[Entrée]],0)),"?")) -> 0 | N11: =IF(Lignes_2_1[[#This Row],[Rôle ou catégorie]]="","",IF(Lignes_2_1[[#This Row],[Type]]="Main-d’œuvre",Lignes_2_1[[#This Row],[Quantité]]*Lignes_2_1[[#This Row],[Heures]],0)) -> 0 | O11: =IF(Lignes_2_1[[#This Row],[Rôle ou catégorie]]="","",IF(Lignes_2_1[[#This Row],[Type]]="Main-d’œuvre",Lignes_2_1[[#This Row],[Quantité]]*Lignes_2_1[[#This Row],[Heures]]*Lignes_2_1[[#This Row],[Taux horaire]],0)) -> 0 | P11: =IF(Lignes_2_1[[#This Row],[Rôle ou catégorie]]="","",IF(OR(Lignes_2_1[[#This Row],[Type]]="Hors main-d’œuvre",Lignes_2_1[[#This Row],[Type]]="Provision"),Lignes_2_1[[#This Row],[Quantité]]*Lignes_2_1[[#This Row],[Débours unitaire]],0)) -> 0 | Q11: =IF(Lignes_2_1[[#This Row],[Rôle ou catégorie]]="","",Lignes_2_1[[#This Row],[Main-d’œuvre]]+Lignes_2_1[[#This Row],[Débours]]) -> 0 | T11: =IF(Lignes_2_1[[#This Row],[Rôle ou catégorie]]="","",IFERROR(INDEX(Referentiel[[Type de nature]],MATCH(Lignes_2_1[[#This Row],[Rôle ou catégorie]],Referentiel[[Entrée]],0)),"?")) -> 0
B12: =IF(Lignes_2_1[[#This Row],[Tâche]]="","",IFERROR(INDEX(Taches[[Description]],MATCH(Lignes_2_1[[#This Row],[Tâche]],Taches[[Entrée]],0)),"")) -> 0 | J12: =IF(Lignes_2_1[[#This Row],[Rôle ou catégorie]]="","",IFERROR(INDEX(Referentiel[[Nature]],MATCH(Lignes_2_1[[#This Row],[Rôle ou catégorie]],Referentiel[[Entrée]],0)),"?")) -> 0 | K12: =IF(Lignes_2_1[[#This Row],[Rôle ou catégorie]]="","",IFERROR(INDEX(Referentiel[[Code comptable]],MATCH(Lignes_2_1[[#This Row],[Rôle ou catégorie]],Referentiel[[Entrée]],0)),"?")) -> 0 | L12: =IF(Lignes_2_1[[#This Row],[Rôle ou catégorie]]="","",IFERROR(INDEX(Referentiel[[Service]],MATCH(Lignes_2_1[[#This Row],[Rôle ou catégorie]],Referentiel[[Entrée]],0)),"?")&"") -> 0 | M12: =IF(Lignes_2_1[[#This Row],[Rôle ou catégorie]]="","",IFERROR(INDEX(Referentiel[[Taux horaire]],MATCH(Lignes_2_1[[#This Row],[Rôle ou catégorie]],Referentiel[[Entrée]],0)),"?")) -> 0 | N12: =IF(Lignes_2_1[[#This Row],[Rôle ou catégorie]]="","",IF(Lignes_2_1[[#This Row],[Type]]="Main-d’œuvre",Lignes_2_1[[#This Row],[Quantité]]*Lignes_2_1[[#This Row],[Heures]],0)) -> 0 | O12: =IF(Lignes_2_1[[#This Row],[Rôle ou catégorie]]="","",IF(Lignes_2_1[[#This Row],[Type]]="Main-d’œuvre",Lignes_2_1[[#This Row],[Quantité]]*Lignes_2_1[[#This Row],[Heures]]*Lignes_2_1[[#This Row],[Taux horaire]],0)) -> 0 | P12: =IF(Lignes_2_1[[#This Row],[Rôle ou catégorie]]="","",IF(OR(Lignes_2_1[[#This Row],[Type]]="Hors main-d’œuvre",Lignes_2_1[[#This Row],[Type]]="Provision"),Lignes_2_1[[#This Row],[Quantité]]*Lignes_2_1[[#This Row],[Débours unitaire]],0)) -> 0 | Q12: =IF(Lignes_2_1[[#This Row],[Rôle ou catégorie]]="","",Lignes_2_1[[#This Row],[Main-d’œuvre]]+Lignes_2_1[[#This Row],[Débours]]) -> 0 | T12: =IF(Lignes_2_1[[#This Row],[Rôle ou catégorie]]="","",IFERROR(INDEX(Referentiel[[Type de nature]],MATCH(Lignes_2_1[[#This Row],[Rôle ou catégorie]],Referentiel[[Entrée]],0)),"?")) -> 0
B13: =IF(Lignes_2_1[[#This Row],[Tâche]]="","",IFERROR(INDEX(Taches[[Description]],MATCH(Lignes_2_1[[#This Row],[Tâche]],Taches[[Entrée]],0)),"")) -> 0 | J13: =IF(Lignes_2_1[[#This Row],[Rôle ou catégorie]]="","",IFERROR(INDEX(Referentiel[[Nature]],MATCH(Lignes_2_1[[#This Row],[Rôle ou catégorie]],Referentiel[[Entrée]],0)),"?")) -> 0 | K13: =IF(Lignes_2_1[[#This Row],[Rôle ou catégorie]]="","",IFERROR(INDEX(Referentiel[[Code comptable]],MATCH(Lignes_2_1[[#This Row],[Rôle ou catégorie]],Referentiel[[Entrée]],0)),"?")) -> 0 | L13: =IF(Lignes_2_1[[#This Row],[Rôle ou catégorie]]="","",IFERROR(INDEX(Referentiel[[Service]],MATCH(Lignes_2_1[[#This Row],[Rôle ou catégorie]],Referentiel[[Entrée]],0)),"?")&"") -> 0 | M13: =IF(Lignes_2_1[[#This Row],[Rôle ou catégorie]]="","",IFERROR(INDEX(Referentiel[[Taux horaire]],MATCH(Lignes_2_1[[#This Row],[Rôle ou catégorie]],Referentiel[[Entrée]],0)),"?")) -> 0 | N13: =IF(Lignes_2_1[[#This Row],[Rôle ou catégorie]]="","",IF(Lignes_2_1[[#This Row],[Type]]="Main-d’œuvre",Lignes_2_1[[#This Row],[Quantité]]*Lignes_2_1[[#This Row],[Heures]],0)) -> 0 | O13: =IF(Lignes_2_1[[#This Row],[Rôle ou catégorie]]="","",IF(Lignes_2_1[[#This Row],[Type]]="Main-d’œuvre",Lignes_2_1[[#This Row],[Quantité]]*Lignes_2_1[[#This Row],[Heures]]*Lignes_2_1[[#This Row],[Taux horaire]],0)) -> 0 | P13: =IF(Lignes_2_1[[#This Row],[Rôle ou catégorie]]="","",IF(OR(Lignes_2_1[[#This Row],[Type]]="Hors main-d’œuvre",Lignes_2_1[[#This Row],[Type]]="Provision"),Lignes_2_1[[#This Row],[Quantité]]*Lignes_2_1[[#This Row],[Débours unitaire]],0)) -> 0 | Q13: =IF(Lignes_2_1[[#This Row],[Rôle ou catégorie]]="","",Lignes_2_1[[#This Row],[Main-d’œuvre]]+Lignes_2_1[[#This Row],[Débours]]) -> 0 | T13: =IF(Lignes_2_1[[#This Row],[Rôle ou catégorie]]="","",IFERROR(INDEX(Referentiel[[Type de nature]],MATCH(Lignes_2_1[[#This Row],[Rôle ou catégorie]],Referentiel[[Entrée]],0)),"?")) -> 0
B14: =IF(Lignes_2_1[[#This Row],[Tâche]]="","",IFERROR(INDEX(Taches[[Description]],MATCH(Lignes_2_1[[#This Row],[Tâche]],Taches[[Entrée]],0)),"")) -> 0 | J14: =IF(Lignes_2_1[[#This Row],[Rôle ou catégorie]]="","",IFERROR(INDEX(Referentiel[[Nature]],MATCH(Lignes_2_1[[#This Row],[Rôle ou catégorie]],Referentiel[[Entrée]],0)),"?")) -> 0 | K14: =IF(Lignes_2_1[[#This Row],[Rôle ou catégorie]]="","",IFERROR(INDEX(Referentiel[[Code comptable]],MATCH(Lignes_2_1[[#This Row],[Rôle ou catégorie]],Referentiel[[Entrée]],0)),"?")) -> 0 | L14: =IF(Lignes_2_1[[#This Row],[Rôle ou catégorie]]="","",IFERROR(INDEX(Referentiel[[Service]],MATCH(Lignes_2_1[[#This Row],[Rôle ou catégorie]],Referentiel[[Entrée]],0)),"?")&"") -> 0 | M14: =IF(Lignes_2_1[[#This Row],[Rôle ou catégorie]]="","",IFERROR(INDEX(Referentiel[[Taux horaire]],MATCH(Lignes_2_1[[#This Row],[Rôle ou catégorie]],Referentiel[[Entrée]],0)),"?")) -> 0 | N14: =IF(Lignes_2_1[[#This Row],[Rôle ou catégorie]]="","",IF(Lignes_2_1[[#This Row],[Type]]="Main-d’œuvre",Lignes_2_1[[#This Row],[Quantité]]*Lignes_2_1[[#This Row],[Heures]],0)) -> 0 | O14: =IF(Lignes_2_1[[#This Row],[Rôle ou catégorie]]="","",IF(Lignes_2_1[[#This Row],[Type]]="Main-d’œuvre",Lignes_2_1[[#This Row],[Quantité]]*Lignes_2_1[[#This Row],[Heures]]*Lignes_2_1[[#This Row],[Taux horaire]],0)) -> 0 | P14: =IF(Lignes_2_1[[#This Row],[Rôle ou catégorie]]="","",IF(OR(Lignes_2_1[[#This Row],[Type]]="Hors main-d’œuvre",Lignes_2_1[[#This Row],[Type]]="Provision"),Lignes_2_1[[#This Row],[Quantité]]*Lignes_2_1[[#This Row],[Débours unitaire]],0)) -> 0 | Q14: =IF(Lignes_2_1[[#This Row],[Rôle ou catégorie]]="","",Lignes_2_1[[#This Row],[Main-d’œuvre]]+Lignes_2_1[[#This Row],[Débours]]) -> 0 | T14: =IF(Lignes_2_1[[#This Row],[Rôle ou catégorie]]="","",IFERROR(INDEX(Referentiel[[Type de nature]],MATCH(Lignes_2_1[[#This Row],[Rôle ou catégorie]],Referentiel[[Entrée]],0)),"?")) -> 0
B15: =IF(Lignes_2_1[[#This Row],[Tâche]]="","",IFERROR(INDEX(Taches[[Description]],MATCH(Lignes_2_1[[#This Row],[Tâche]],Taches[[Entrée]],0)),"")) -> 0 | J15: =IF(Lignes_2_1[[#This Row],[Rôle ou catégorie]]="","",IFERROR(INDEX(Referentiel[[Nature]],MATCH(Lignes_2_1[[#This Row],[Rôle ou catégorie]],Referentiel[[Entrée]],0)),"?")) -> 0 | K15: =IF(Lignes_2_1[[#This Row],[Rôle ou catégorie]]="","",IFERROR(INDEX(Referentiel[[Code comptable]],MATCH(Lignes_2_1[[#This Row],[Rôle ou catégorie]],Referentiel[[Entrée]],0)),"?")) -> 0 | L15: =IF(Lignes_2_1[[#This Row],[Rôle ou catégorie]]="","",IFERROR(INDEX(Referentiel[[Service]],MATCH(Lignes_2_1[[#This Row],[Rôle ou catégorie]],Referentiel[[Entrée]],0)),"?")&"") -> 0 | M15: =IF(Lignes_2_1[[#This Row],[Rôle ou catégorie]]="","",IFERROR(INDEX(Referentiel[[Taux horaire]],MATCH(Lignes_2_1[[#This Row],[Rôle ou catégorie]],Referentiel[[Entrée]],0)),"?")) -> 0 | N15: =IF(Lignes_2_1[[#This Row],[Rôle ou catégorie]]="","",IF(Lignes_2_1[[#This Row],[Type]]="Main-d’œuvre",Lignes_2_1[[#This Row],[Quantité]]*Lignes_2_1[[#This Row],[Heures]],0)) -> 0 | O15: =IF(Lignes_2_1[[#This Row],[Rôle ou catégorie]]="","",IF(Lignes_2_1[[#This Row],[Type]]="Main-d’œuvre",Lignes_2_1[[#This Row],[Quantité]]*Lignes_2_1[[#This Row],[Heures]]*Lignes_2_1[[#This Row],[Taux horaire]],0)) -> 0 | P15: =IF(Lignes_2_1[[#This Row],[Rôle ou catégorie]]="","",IF(OR(Lignes_2_1[[#This Row],[Type]]="Hors main-d’œuvre",Lignes_2_1[[#This Row],[Type]]="Provision"),Lignes_2_1[[#This Row],[Quantité]]*Lignes_2_1[[#This Row],[Débours unitaire]],0)) -> 0 | Q15: =IF(Lignes_2_1[[#This Row],[Rôle ou catégorie]]="","",Lignes_2_1[[#This Row],[Main-d’œuvre]]+Lignes_2_1[[#This Row],[Débours]]) -> 0 | T15: =IF(Lignes_2_1[[#This Row],[Rôle ou catégorie]]="","",IFERROR(INDEX(Referentiel[[Type de nature]],MATCH(Lignes_2_1[[#This Row],[Rôle ou catégorie]],Referentiel[[Entrée]],0)),"?")) -> 0
... B33: =IF(Lignes_2_1[[#This Row],[Tâche]]="","",IFERROR(INDEX(Taches[[Description]],MATCH(Lignes_2_1[[#This Row],[Tâche]],Taches[[Entrée]],0)),"")) -> 0 | J33: =IF(Lignes_2_1[[#This Row],[Rôle ou catégorie]]="","",IFERROR(INDEX(Referentiel[[Nature]],MATCH(Lignes_2_1[[#This Row],[Rôle ou catégorie]],Referentiel[[Entrée]],0)),"?")) -> 0 | K33: =IF(Lignes_2_1[[#This Row],[Rôle ou catégorie]]="","",IFERROR(INDEX(Referentiel[[Code comptable]],MATCH(Lignes_2_1[[#This Row],[Rôle ou catégorie]],Referentiel[[Entrée]],0)),"?")) -> 0 | L33: =IF(Lignes_2_1[[#This Row],[Rôle ou catégorie]]="","",IFERROR(INDEX(Referentiel[[Service]],MATCH(Lignes_2_1[[#This Row],[Rôle ou catégorie]],Referentiel[[Entrée]],0)),"?")&"") -> 0 | M33: =IF(Lignes_2_1[[#This Row],[Rôle ou catégorie]]="","",IFERROR(INDEX(Referentiel[[Taux horaire]],MATCH(Lignes_2_1[[#This Row],[Rôle ou catégorie]],Referentiel[[Entrée]],0)),"?")) -> 0 | N33: =IF(Lignes_2_1[[#This Row],[Rôle ou catégorie]]="","",IF(Lignes_2_1[[#This Row],[Type]]="Main-d’œuvre",Lignes_2_1[[#This Row],[Quantité]]*Lignes_2_1[[#This Row],[Heures]],0)) -> 0 | O33: =IF(Lignes_2_1[[#This Row],[Rôle ou catégorie]]="","",IF(Lignes_2_1[[#This Row],[Type]]="Main-d’œuvre",Lignes_2_1[[#This Row],[Quantité]]*Lignes_2_1[[#This Row],[Heures]]*Lignes_2_1[[#This Row],[Taux horaire]],0)) -> 0 | P33: =IF(Lignes_2_1[[#This Row],[Rôle ou catégorie]]="","",IF(OR(Lignes_2_1[[#This Row],[Type]]="Hors main-d’œuvre",Lignes_2_1[[#This Row],[Type]]="Provision"),Lignes_2_1[[#This Row],[Quantité]]*Lignes_2_1[[#This Row],[Débours unitaire]],0)) -> 0 | Q33: =IF(Lignes_2_1[[#This Row],[Rôle ou catégorie]]="","",Lignes_2_1[[#This Row],[Main-d’œuvre]]+Lignes_2_1[[#This Row],[Débours]]) -> 0 | T33: =IF(Lignes_2_1[[#This Row],[Rôle ou catégorie]]="","",IFERROR(INDEX(Referentiel[[Type de nature]],MATCH(Lignes_2_1[[#This Row],[Rôle ou catégorie]],Referentiel[[Entrée]],0)),"?")) -> 0
A34: Total | N34: =SUBTOTAL(109,Lignes_2_1[[Heures totales]]) -> 0 | O34: =SUBTOTAL(109,Lignes_2_1[[Main-d’œuvre]]) -> 0 | P34: =SUBTOTAL(109,Lignes_2_1[[Débours]]) -> 0 | Q34: =SUBTOTAL(109,Lignes_2_1[[Montant]]) -> 0 | R34: =SUBTOTAL(109,Lignes_2_1[[Montant Waterfall]]) -> 0

Sheet Hors lot
A1: Tâche | B1: Description de la tâche | C1: Rôle ou catégorie | D1: Désignation | E1: Quantité | F1: Heures | G1: Débours unitaire | H1: Délai de paiement (j) | I1: Sous-projet | J1: Nature | K1: Code comptable | L1: Service | M1: Taux horaire | N1: Heures totales | O1: Main-d’œuvre | P1: Débours | Q1: Montant | R1: Montant Waterfall | S1: ID ligne | T1: Type
A2: 3 Gestion de projet | B2: =IF(Lignes_hors_lot[[#This Row],[Tâche]]="","",IFERROR(INDEX(Taches[[Description]],MATCH(Lignes_hors_lot[[#This Row],[Tâche]],Taches[[Entrée]],0)),"")) -> 0 | C2: Responsable d’affaire A1 (RA-A1) | D2: =1+1 reste une désignation | E2: 20 | F2: 7.4 | H2: 0 | J2: =IF(Lignes_hors_lot[[#This Row],[Rôle ou catégorie]]="","",IFERROR(INDEX(Referentiel[[Nature]],MATCH(Lignes_hors_lot[[#This Row],[Rôle ou catégorie]],Referentiel[[Entrée]],0)),"?")) -> 0 | K2: =IF(Lignes_hors_lot[[#This Row],[Rôle ou catégorie]]="","",IFERROR(INDEX(Referentiel[[Code comptable]],MATCH(Lignes_hors_lot[[#This Row],[Rôle ou catégorie]],Referentiel[[Entrée]],0)),"?")) -> 0 | L2: =IF(Lignes_hors_lot[[#This Row],[Rôle ou catégorie]]="","",IFERROR(INDEX(Referentiel[[Service]],MATCH(Lignes_hors_lot[[#This Row],[Rôle ou catégorie]],Referentiel[[Entrée]],0)),"?")&"") -> 0 | M2: =IF(Lignes_hors_lot[[#This Row],[Rôle ou catégorie]]="","",IFERROR(INDEX(Referentiel[[Taux horaire]],MATCH(Lignes_hors_lot[[#This Row],[Rôle ou catégorie]],Referentiel[[Entrée]],0)),"?")) -> 0 | N2: =IF(Lignes_hors_lot[[#This Row],[Rôle ou catégorie]]="","",IF(Lignes_hors_lot[[#This Row],[Type]]="Main-d’œuvre",Lignes_hors_lot[[#This Row],[Quantité]]*Lignes_hors_lot[[#This Row],[Heures]],0)) -> 0 | O2: =IF(Lignes_hors_lot[[#This Row],[Rôle ou catégorie]]="","",IF(Lignes_hors_lot[[#This Row],[Type]]="Main-d’œuvre",Lignes_hors_lot[[#This Row],[Quantité]]*Lignes_hors_lot[[#This Row],[Heures]]*Lignes_hors_lot[[#This Row],[Taux horaire]],0)) -> 0 | P2: =IF(Lignes_hors_lot[[#This Row],[Rôle ou catégorie]]="","",IF(OR(Lignes_hors_lot[[#This Row],[Type]]="Hors main-d’œuvre",Lignes_hors_lot[[#This Row],[Type]]="Provision"),Lignes_hors_lot[[#This Row],[Quantité]]*Lignes_hors_lot[[#This Row],[Débours unitaire]],0)) -> 0 | Q2: =IF(Lignes_hors_lot[[#This Row],[Rôle ou catégorie]]="","",Lignes_hors_lot[[#This Row],[Main-d’œuvre]]+Lignes_hors_lot[[#This Row],[Débours]]) -> 0 | R2: 14948 | S2: l-0501 | T2: =IF(Lignes_hors_lot[[#This Row],[Rôle ou catégorie]]="","",IFERROR(INDEX(Referentiel[[Type de nature]],MATCH(Lignes_hors_lot[[#This Row],[Rôle ou catégorie]],Referentiel[[Entrée]],0)),"?")) -> 0
B3: =IF(Lignes_hors_lot[[#This Row],[Tâche]]="","",IFERROR(INDEX(Taches[[Description]],MATCH(Lignes_hors_lot[[#This Row],[Tâche]],Taches[[Entrée]],0)),"")) -> 0 | J3: =IF(Lignes_hors_lot[[#This Row],[Rôle ou catégorie]]="","",IFERROR(INDEX(Referentiel[[Nature]],MATCH(Lignes_hors_lot[[#This Row],[Rôle ou catégorie]],Referentiel[[Entrée]],0)),"?")) -> 0 | K3: =IF(Lignes_hors_lot[[#This Row],[Rôle ou catégorie]]="","",IFERROR(INDEX(Referentiel[[Code comptable]],MATCH(Lignes_hors_lot[[#This Row],[Rôle ou catégorie]],Referentiel[[Entrée]],0)),"?")) -> 0 | L3: =IF(Lignes_hors_lot[[#This Row],[Rôle ou catégorie]]="","",IFERROR(INDEX(Referentiel[[Service]],MATCH(Lignes_hors_lot[[#This Row],[Rôle ou catégorie]],Referentiel[[Entrée]],0)),"?")&"") -> 0 | M3: =IF(Lignes_hors_lot[[#This Row],[Rôle ou catégorie]]="","",IFERROR(INDEX(Referentiel[[Taux horaire]],MATCH(Lignes_hors_lot[[#This Row],[Rôle ou catégorie]],Referentiel[[Entrée]],0)),"?")) -> 0 | N3: =IF(Lignes_hors_lot[[#This Row],[Rôle ou catégorie]]="","",IF(Lignes_hors_lot[[#This Row],[Type]]="Main-d’œuvre",Lignes_hors_lot[[#This Row],[Quantité]]*Lignes_hors_lot[[#This Row],[Heures]],0)) -> 0 | O3: =IF(Lignes_hors_lot[[#This Row],[Rôle ou catégorie]]="","",IF(Lignes_hors_lot[[#This Row],[Type]]="Main-d’œuvre",Lignes_hors_lot[[#This Row],[Quantité]]*Lignes_hors_lot[[#This Row],[Heures]]*Lignes_hors_lot[[#This Row],[Taux horaire]],0)) -> 0 | P3: =IF(Lignes_hors_lot[[#This Row],[Rôle ou catégorie]]="","",IF(OR(Lignes_hors_lot[[#This Row],[Type]]="Hors main-d’œuvre",Lignes_hors_lot[[#This Row],[Type]]="Provision"),Lignes_hors_lot[[#This Row],[Quantité]]*Lignes_hors_lot[[#This Row],[Débours unitaire]],0)) -> 0 | Q3: =IF(Lignes_hors_lot[[#This Row],[Rôle ou catégorie]]="","",Lignes_hors_lot[[#This Row],[Main-d’œuvre]]+Lignes_hors_lot[[#This Row],[Débours]]) -> 0 | T3: =IF(Lignes_hors_lot[[#This Row],[Rôle ou catégorie]]="","",IFERROR(INDEX(Referentiel[[Type de nature]],MATCH(Lignes_hors_lot[[#This Row],[Rôle ou catégorie]],Referentiel[[Entrée]],0)),"?")) -> 0
B4: =IF(Lignes_hors_lot[[#This Row],[Tâche]]="","",IFERROR(INDEX(Taches[[Description]],MATCH(Lignes_hors_lot[[#This Row],[Tâche]],Taches[[Entrée]],0)),"")) -> 0 | J4: =IF(Lignes_hors_lot[[#This Row],[Rôle ou catégorie]]="","",IFERROR(INDEX(Referentiel[[Nature]],MATCH(Lignes_hors_lot[[#This Row],[Rôle ou catégorie]],Referentiel[[Entrée]],0)),"?")) -> 0 | K4: =IF(Lignes_hors_lot[[#This Row],[Rôle ou catégorie]]="","",IFERROR(INDEX(Referentiel[[Code comptable]],MATCH(Lignes_hors_lot[[#This Row],[Rôle ou catégorie]],Referentiel[[Entrée]],0)),"?")) -> 0 | L4: =IF(Lignes_hors_lot[[#This Row],[Rôle ou catégorie]]="","",IFERROR(INDEX(Referentiel[[Service]],MATCH(Lignes_hors_lot[[#This Row],[Rôle ou catégorie]],Referentiel[[Entrée]],0)),"?")&"") -> 0 | M4: =IF(Lignes_hors_lot[[#This Row],[Rôle ou catégorie]]="","",IFERROR(INDEX(Referentiel[[Taux horaire]],MATCH(Lignes_hors_lot[[#This Row],[Rôle ou catégorie]],Referentiel[[Entrée]],0)),"?")) -> 0 | N4: =IF(Lignes_hors_lot[[#This Row],[Rôle ou catégorie]]="","",IF(Lignes_hors_lot[[#This Row],[Type]]="Main-d’œuvre",Lignes_hors_lot[[#This Row],[Quantité]]*Lignes_hors_lot[[#This Row],[Heures]],0)) -> 0 | O4: =IF(Lignes_hors_lot[[#This Row],[Rôle ou catégorie]]="","",IF(Lignes_hors_lot[[#This Row],[Type]]="Main-d’œuvre",Lignes_hors_lot[[#This Row],[Quantité]]*Lignes_hors_lot[[#This Row],[Heures]]*Lignes_hors_lot[[#This Row],[Taux horaire]],0)) -> 0 | P4: =IF(Lignes_hors_lot[[#This Row],[Rôle ou catégorie]]="","",IF(OR(Lignes_hors_lot[[#This Row],[Type]]="Hors main-d’œuvre",Lignes_hors_lot[[#This Row],[Type]]="Provision"),Lignes_hors_lot[[#This Row],[Quantité]]*Lignes_hors_lot[[#This Row],[Débours unitaire]],0)) -> 0 | Q4: =IF(Lignes_hors_lot[[#This Row],[Rôle ou catégorie]]="","",Lignes_hors_lot[[#This Row],[Main-d’œuvre]]+Lignes_hors_lot[[#This Row],[Débours]]) -> 0 | T4: =IF(Lignes_hors_lot[[#This Row],[Rôle ou catégorie]]="","",IFERROR(INDEX(Referentiel[[Type de nature]],MATCH(Lignes_hors_lot[[#This Row],[Rôle ou catégorie]],Referentiel[[Entrée]],0)),"?")) -> 0
B5: =IF(Lignes_hors_lot[[#This Row],[Tâche]]="","",IFERROR(INDEX(Taches[[Description]],MATCH(Lignes_hors_lot[[#This Row],[Tâche]],Taches[[Entrée]],0)),"")) -> 0 | J5: =IF(Lignes_hors_lot[[#This Row],[Rôle ou catégorie]]="","",IFERROR(INDEX(Referentiel[[Nature]],MATCH(Lignes_hors_lot[[#This Row],[Rôle ou catégorie]],Referentiel[[Entrée]],0)),"?")) -> 0 | K5: =IF(Lignes_hors_lot[[#This Row],[Rôle ou catégorie]]="","",IFERROR(INDEX(Referentiel[[Code comptable]],MATCH(Lignes_hors_lot[[#This Row],[Rôle ou catégorie]],Referentiel[[Entrée]],0)),"?")) -> 0 | L5: =IF(Lignes_hors_lot[[#This Row],[Rôle ou catégorie]]="","",IFERROR(INDEX(Referentiel[[Service]],MATCH(Lignes_hors_lot[[#This Row],[Rôle ou catégorie]],Referentiel[[Entrée]],0)),"?")&"") -> 0 | M5: =IF(Lignes_hors_lot[[#This Row],[Rôle ou catégorie]]="","",IFERROR(INDEX(Referentiel[[Taux horaire]],MATCH(Lignes_hors_lot[[#This Row],[Rôle ou catégorie]],Referentiel[[Entrée]],0)),"?")) -> 0 | N5: =IF(Lignes_hors_lot[[#This Row],[Rôle ou catégorie]]="","",IF(Lignes_hors_lot[[#This Row],[Type]]="Main-d’œuvre",Lignes_hors_lot[[#This Row],[Quantité]]*Lignes_hors_lot[[#This Row],[Heures]],0)) -> 0 | O5: =IF(Lignes_hors_lot[[#This Row],[Rôle ou catégorie]]="","",IF(Lignes_hors_lot[[#This Row],[Type]]="Main-d’œuvre",Lignes_hors_lot[[#This Row],[Quantité]]*Lignes_hors_lot[[#This Row],[Heures]]*Lignes_hors_lot[[#This Row],[Taux horaire]],0)) -> 0 | P5: =IF(Lignes_hors_lot[[#This Row],[Rôle ou catégorie]]="","",IF(OR(Lignes_hors_lot[[#This Row],[Type]]="Hors main-d’œuvre",Lignes_hors_lot[[#This Row],[Type]]="Provision"),Lignes_hors_lot[[#This Row],[Quantité]]*Lignes_hors_lot[[#This Row],[Débours unitaire]],0)) -> 0 | Q5: =IF(Lignes_hors_lot[[#This Row],[Rôle ou catégorie]]="","",Lignes_hors_lot[[#This Row],[Main-d’œuvre]]+Lignes_hors_lot[[#This Row],[Débours]]) -> 0 | T5: =IF(Lignes_hors_lot[[#This Row],[Rôle ou catégorie]]="","",IFERROR(INDEX(Referentiel[[Type de nature]],MATCH(Lignes_hors_lot[[#This Row],[Rôle ou catégorie]],Referentiel[[Entrée]],0)),"?")) -> 0
B6: =IF(Lignes_hors_lot[[#This Row],[Tâche]]="","",IFERROR(INDEX(Taches[[Description]],MATCH(Lignes_hors_lot[[#This Row],[Tâche]],Taches[[Entrée]],0)),"")) -> 0 | J6: =IF(Lignes_hors_lot[[#This Row],[Rôle ou catégorie]]="","",IFERROR(INDEX(Referentiel[[Nature]],MATCH(Lignes_hors_lot[[#This Row],[Rôle ou catégorie]],Referentiel[[Entrée]],0)),"?")) -> 0 | K6: =IF(Lignes_hors_lot[[#This Row],[Rôle ou catégorie]]="","",IFERROR(INDEX(Referentiel[[Code comptable]],MATCH(Lignes_hors_lot[[#This Row],[Rôle ou catégorie]],Referentiel[[Entrée]],0)),"?")) -> 0 | L6: =IF(Lignes_hors_lot[[#This Row],[Rôle ou catégorie]]="","",IFERROR(INDEX(Referentiel[[Service]],MATCH(Lignes_hors_lot[[#This Row],[Rôle ou catégorie]],Referentiel[[Entrée]],0)),"?")&"") -> 0 | M6: =IF(Lignes_hors_lot[[#This Row],[Rôle ou catégorie]]="","",IFERROR(INDEX(Referentiel[[Taux horaire]],MATCH(Lignes_hors_lot[[#This Row],[Rôle ou catégorie]],Referentiel[[Entrée]],0)),"?")) -> 0 | N6: =IF(Lignes_hors_lot[[#This Row],[Rôle ou catégorie]]="","",IF(Lignes_hors_lot[[#This Row],[Type]]="Main-d’œuvre",Lignes_hors_lot[[#This Row],[Quantité]]*Lignes_hors_lot[[#This Row],[Heures]],0)) -> 0 | O6: =IF(Lignes_hors_lot[[#This Row],[Rôle ou catégorie]]="","",IF(Lignes_hors_lot[[#This Row],[Type]]="Main-d’œuvre",Lignes_hors_lot[[#This Row],[Quantité]]*Lignes_hors_lot[[#This Row],[Heures]]*Lignes_hors_lot[[#This Row],[Taux horaire]],0)) -> 0 | P6: =IF(Lignes_hors_lot[[#This Row],[Rôle ou catégorie]]="","",IF(OR(Lignes_hors_lot[[#This Row],[Type]]="Hors main-d’œuvre",Lignes_hors_lot[[#This Row],[Type]]="Provision"),Lignes_hors_lot[[#This Row],[Quantité]]*Lignes_hors_lot[[#This Row],[Débours unitaire]],0)) -> 0 | Q6: =IF(Lignes_hors_lot[[#This Row],[Rôle ou catégorie]]="","",Lignes_hors_lot[[#This Row],[Main-d’œuvre]]+Lignes_hors_lot[[#This Row],[Débours]]) -> 0 | T6: =IF(Lignes_hors_lot[[#This Row],[Rôle ou catégorie]]="","",IFERROR(INDEX(Referentiel[[Type de nature]],MATCH(Lignes_hors_lot[[#This Row],[Rôle ou catégorie]],Referentiel[[Entrée]],0)),"?")) -> 0
B7: =IF(Lignes_hors_lot[[#This Row],[Tâche]]="","",IFERROR(INDEX(Taches[[Description]],MATCH(Lignes_hors_lot[[#This Row],[Tâche]],Taches[[Entrée]],0)),"")) -> 0 | J7: =IF(Lignes_hors_lot[[#This Row],[Rôle ou catégorie]]="","",IFERROR(INDEX(Referentiel[[Nature]],MATCH(Lignes_hors_lot[[#This Row],[Rôle ou catégorie]],Referentiel[[Entrée]],0)),"?")) -> 0 | K7: =IF(Lignes_hors_lot[[#This Row],[Rôle ou catégorie]]="","",IFERROR(INDEX(Referentiel[[Code comptable]],MATCH(Lignes_hors_lot[[#This Row],[Rôle ou catégorie]],Referentiel[[Entrée]],0)),"?")) -> 0 | L7: =IF(Lignes_hors_lot[[#This Row],[Rôle ou catégorie]]="","",IFERROR(INDEX(Referentiel[[Service]],MATCH(Lignes_hors_lot[[#This Row],[Rôle ou catégorie]],Referentiel[[Entrée]],0)),"?")&"") -> 0 | M7: =IF(Lignes_hors_lot[[#This Row],[Rôle ou catégorie]]="","",IFERROR(INDEX(Referentiel[[Taux horaire]],MATCH(Lignes_hors_lot[[#This Row],[Rôle ou catégorie]],Referentiel[[Entrée]],0)),"?")) -> 0 | N7: =IF(Lignes_hors_lot[[#This Row],[Rôle ou catégorie]]="","",IF(Lignes_hors_lot[[#This Row],[Type]]="Main-d’œuvre",Lignes_hors_lot[[#This Row],[Quantité]]*Lignes_hors_lot[[#This Row],[Heures]],0)) -> 0 | O7: =IF(Lignes_hors_lot[[#This Row],[Rôle ou catégorie]]="","",IF(Lignes_hors_lot[[#This Row],[Type]]="Main-d’œuvre",Lignes_hors_lot[[#This Row],[Quantité]]*Lignes_hors_lot[[#This Row],[Heures]]*Lignes_hors_lot[[#This Row],[Taux horaire]],0)) -> 0 | P7: =IF(Lignes_hors_lot[[#This Row],[Rôle ou catégorie]]="","",IF(OR(Lignes_hors_lot[[#This Row],[Type]]="Hors main-d’œuvre",Lignes_hors_lot[[#This Row],[Type]]="Provision"),Lignes_hors_lot[[#This Row],[Quantité]]*Lignes_hors_lot[[#This Row],[Débours unitaire]],0)) -> 0 | Q7: =IF(Lignes_hors_lot[[#This Row],[Rôle ou catégorie]]="","",Lignes_hors_lot[[#This Row],[Main-d’œuvre]]+Lignes_hors_lot[[#This Row],[Débours]]) -> 0 | T7: =IF(Lignes_hors_lot[[#This Row],[Rôle ou catégorie]]="","",IFERROR(INDEX(Referentiel[[Type de nature]],MATCH(Lignes_hors_lot[[#This Row],[Rôle ou catégorie]],Referentiel[[Entrée]],0)),"?")) -> 0
B8: =IF(Lignes_hors_lot[[#This Row],[Tâche]]="","",IFERROR(INDEX(Taches[[Description]],MATCH(Lignes_hors_lot[[#This Row],[Tâche]],Taches[[Entrée]],0)),"")) -> 0 | J8: =IF(Lignes_hors_lot[[#This Row],[Rôle ou catégorie]]="","",IFERROR(INDEX(Referentiel[[Nature]],MATCH(Lignes_hors_lot[[#This Row],[Rôle ou catégorie]],Referentiel[[Entrée]],0)),"?")) -> 0 | K8: =IF(Lignes_hors_lot[[#This Row],[Rôle ou catégorie]]="","",IFERROR(INDEX(Referentiel[[Code comptable]],MATCH(Lignes_hors_lot[[#This Row],[Rôle ou catégorie]],Referentiel[[Entrée]],0)),"?")) -> 0 | L8: =IF(Lignes_hors_lot[[#This Row],[Rôle ou catégorie]]="","",IFERROR(INDEX(Referentiel[[Service]],MATCH(Lignes_hors_lot[[#This Row],[Rôle ou catégorie]],Referentiel[[Entrée]],0)),"?")&"") -> 0 | M8: =IF(Lignes_hors_lot[[#This Row],[Rôle ou catégorie]]="","",IFERROR(INDEX(Referentiel[[Taux horaire]],MATCH(Lignes_hors_lot[[#This Row],[Rôle ou catégorie]],Referentiel[[Entrée]],0)),"?")) -> 0 | N8: =IF(Lignes_hors_lot[[#This Row],[Rôle ou catégorie]]="","",IF(Lignes_hors_lot[[#This Row],[Type]]="Main-d’œuvre",Lignes_hors_lot[[#This Row],[Quantité]]*Lignes_hors_lot[[#This Row],[Heures]],0)) -> 0 | O8: =IF(Lignes_hors_lot[[#This Row],[Rôle ou catégorie]]="","",IF(Lignes_hors_lot[[#This Row],[Type]]="Main-d’œuvre",Lignes_hors_lot[[#This Row],[Quantité]]*Lignes_hors_lot[[#This Row],[Heures]]*Lignes_hors_lot[[#This Row],[Taux horaire]],0)) -> 0 | P8: =IF(Lignes_hors_lot[[#This Row],[Rôle ou catégorie]]="","",IF(OR(Lignes_hors_lot[[#This Row],[Type]]="Hors main-d’œuvre",Lignes_hors_lot[[#This Row],[Type]]="Provision"),Lignes_hors_lot[[#This Row],[Quantité]]*Lignes_hors_lot[[#This Row],[Débours unitaire]],0)) -> 0 | Q8: =IF(Lignes_hors_lot[[#This Row],[Rôle ou catégorie]]="","",Lignes_hors_lot[[#This Row],[Main-d’œuvre]]+Lignes_hors_lot[[#This Row],[Débours]]) -> 0 | T8: =IF(Lignes_hors_lot[[#This Row],[Rôle ou catégorie]]="","",IFERROR(INDEX(Referentiel[[Type de nature]],MATCH(Lignes_hors_lot[[#This Row],[Rôle ou catégorie]],Referentiel[[Entrée]],0)),"?")) -> 0
B9: =IF(Lignes_hors_lot[[#This Row],[Tâche]]="","",IFERROR(INDEX(Taches[[Description]],MATCH(Lignes_hors_lot[[#This Row],[Tâche]],Taches[[Entrée]],0)),"")) -> 0 | J9: =IF(Lignes_hors_lot[[#This Row],[Rôle ou catégorie]]="","",IFERROR(INDEX(Referentiel[[Nature]],MATCH(Lignes_hors_lot[[#This Row],[Rôle ou catégorie]],Referentiel[[Entrée]],0)),"?")) -> 0 | K9: =IF(Lignes_hors_lot[[#This Row],[Rôle ou catégorie]]="","",IFERROR(INDEX(Referentiel[[Code comptable]],MATCH(Lignes_hors_lot[[#This Row],[Rôle ou catégorie]],Referentiel[[Entrée]],0)),"?")) -> 0 | L9: =IF(Lignes_hors_lot[[#This Row],[Rôle ou catégorie]]="","",IFERROR(INDEX(Referentiel[[Service]],MATCH(Lignes_hors_lot[[#This Row],[Rôle ou catégorie]],Referentiel[[Entrée]],0)),"?")&"") -> 0 | M9: =IF(Lignes_hors_lot[[#This Row],[Rôle ou catégorie]]="","",IFERROR(INDEX(Referentiel[[Taux horaire]],MATCH(Lignes_hors_lot[[#This Row],[Rôle ou catégorie]],Referentiel[[Entrée]],0)),"?")) -> 0 | N9: =IF(Lignes_hors_lot[[#This Row],[Rôle ou catégorie]]="","",IF(Lignes_hors_lot[[#This Row],[Type]]="Main-d’œuvre",Lignes_hors_lot[[#This Row],[Quantité]]*Lignes_hors_lot[[#This Row],[Heures]],0)) -> 0 | O9: =IF(Lignes_hors_lot[[#This Row],[Rôle ou catégorie]]="","",IF(Lignes_hors_lot[[#This Row],[Type]]="Main-d’œuvre",Lignes_hors_lot[[#This Row],[Quantité]]*Lignes_hors_lot[[#This Row],[Heures]]*Lignes_hors_lot[[#This Row],[Taux horaire]],0)) -> 0 | P9: =IF(Lignes_hors_lot[[#This Row],[Rôle ou catégorie]]="","",IF(OR(Lignes_hors_lot[[#This Row],[Type]]="Hors main-d’œuvre",Lignes_hors_lot[[#This Row],[Type]]="Provision"),Lignes_hors_lot[[#This Row],[Quantité]]*Lignes_hors_lot[[#This Row],[Débours unitaire]],0)) -> 0 | Q9: =IF(Lignes_hors_lot[[#This Row],[Rôle ou catégorie]]="","",Lignes_hors_lot[[#This Row],[Main-d’œuvre]]+Lignes_hors_lot[[#This Row],[Débours]]) -> 0 | T9: =IF(Lignes_hors_lot[[#This Row],[Rôle ou catégorie]]="","",IFERROR(INDEX(Referentiel[[Type de nature]],MATCH(Lignes_hors_lot[[#This Row],[Rôle ou catégorie]],Referentiel[[Entrée]],0)),"?")) -> 0
B10: =IF(Lignes_hors_lot[[#This Row],[Tâche]]="","",IFERROR(INDEX(Taches[[Description]],MATCH(Lignes_hors_lot[[#This Row],[Tâche]],Taches[[Entrée]],0)),"")) -> 0 | J10: =IF(Lignes_hors_lot[[#This Row],[Rôle ou catégorie]]="","",IFERROR(INDEX(Referentiel[[Nature]],MATCH(Lignes_hors_lot[[#This Row],[Rôle ou catégorie]],Referentiel[[Entrée]],0)),"?")) -> 0 | K10: =IF(Lignes_hors_lot[[#This Row],[Rôle ou catégorie]]="","",IFERROR(INDEX(Referentiel[[Code comptable]],MATCH(Lignes_hors_lot[[#This Row],[Rôle ou catégorie]],Referentiel[[Entrée]],0)),"?")) -> 0 | L10: =IF(Lignes_hors_lot[[#This Row],[Rôle ou catégorie]]="","",IFERROR(INDEX(Referentiel[[Service]],MATCH(Lignes_hors_lot[[#This Row],[Rôle ou catégorie]],Referentiel[[Entrée]],0)),"?")&"") -> 0 | M10: =IF(Lignes_hors_lot[[#This Row],[Rôle ou catégorie]]="","",IFERROR(INDEX(Referentiel[[Taux horaire]],MATCH(Lignes_hors_lot[[#This Row],[Rôle ou catégorie]],Referentiel[[Entrée]],0)),"?")) -> 0 | N10: =IF(Lignes_hors_lot[[#This Row],[Rôle ou catégorie]]="","",IF(Lignes_hors_lot[[#This Row],[Type]]="Main-d’œuvre",Lignes_hors_lot[[#This Row],[Quantité]]*Lignes_hors_lot[[#This Row],[Heures]],0)) -> 0 | O10: =IF(Lignes_hors_lot[[#This Row],[Rôle ou catégorie]]="","",IF(Lignes_hors_lot[[#This Row],[Type]]="Main-d’œuvre",Lignes_hors_lot[[#This Row],[Quantité]]*Lignes_hors_lot[[#This Row],[Heures]]*Lignes_hors_lot[[#This Row],[Taux horaire]],0)) -> 0 | P10: =IF(Lignes_hors_lot[[#This Row],[Rôle ou catégorie]]="","",IF(OR(Lignes_hors_lot[[#This Row],[Type]]="Hors main-d’œuvre",Lignes_hors_lot[[#This Row],[Type]]="Provision"),Lignes_hors_lot[[#This Row],[Quantité]]*Lignes_hors_lot[[#This Row],[Débours unitaire]],0)) -> 0 | Q10: =IF(Lignes_hors_lot[[#This Row],[Rôle ou catégorie]]="","",Lignes_hors_lot[[#This Row],[Main-d’œuvre]]+Lignes_hors_lot[[#This Row],[Débours]]) -> 0 | T10: =IF(Lignes_hors_lot[[#This Row],[Rôle ou catégorie]]="","",IFERROR(INDEX(Referentiel[[Type de nature]],MATCH(Lignes_hors_lot[[#This Row],[Rôle ou catégorie]],Referentiel[[Entrée]],0)),"?")) -> 0
B11: =IF(Lignes_hors_lot[[#This Row],[Tâche]]="","",IFERROR(INDEX(Taches[[Description]],MATCH(Lignes_hors_lot[[#This Row],[Tâche]],Taches[[Entrée]],0)),"")) -> 0 | J11: =IF(Lignes_hors_lot[[#This Row],[Rôle ou catégorie]]="","",IFERROR(INDEX(Referentiel[[Nature]],MATCH(Lignes_hors_lot[[#This Row],[Rôle ou catégorie]],Referentiel[[Entrée]],0)),"?")) -> 0 | K11: =IF(Lignes_hors_lot[[#This Row],[Rôle ou catégorie]]="","",IFERROR(INDEX(Referentiel[[Code comptable]],MATCH(Lignes_hors_lot[[#This Row],[Rôle ou catégorie]],Referentiel[[Entrée]],0)),"?")) -> 0 | L11: =IF(Lignes_hors_lot[[#This Row],[Rôle ou catégorie]]="","",IFERROR(INDEX(Referentiel[[Service]],MATCH(Lignes_hors_lot[[#This Row],[Rôle ou catégorie]],Referentiel[[Entrée]],0)),"?")&"") -> 0 | M11: =IF(Lignes_hors_lot[[#This Row],[Rôle ou catégorie]]="","",IFERROR(INDEX(Referentiel[[Taux horaire]],MATCH(Lignes_hors_lot[[#This Row],[Rôle ou catégorie]],Referentiel[[Entrée]],0)),"?")) -> 0 | N11: =IF(Lignes_hors_lot[[#This Row],[Rôle ou catégorie]]="","",IF(Lignes_hors_lot[[#This Row],[Type]]="Main-d’œuvre",Lignes_hors_lot[[#This Row],[Quantité]]*Lignes_hors_lot[[#This Row],[Heures]],0)) -> 0 | O11: =IF(Lignes_hors_lot[[#This Row],[Rôle ou catégorie]]="","",IF(Lignes_hors_lot[[#This Row],[Type]]="Main-d’œuvre",Lignes_hors_lot[[#This Row],[Quantité]]*Lignes_hors_lot[[#This Row],[Heures]]*Lignes_hors_lot[[#This Row],[Taux horaire]],0)) -> 0 | P11: =IF(Lignes_hors_lot[[#This Row],[Rôle ou catégorie]]="","",IF(OR(Lignes_hors_lot[[#This Row],[Type]]="Hors main-d’œuvre",Lignes_hors_lot[[#This Row],[Type]]="Provision"),Lignes_hors_lot[[#This Row],[Quantité]]*Lignes_hors_lot[[#This Row],[Débours unitaire]],0)) -> 0 | Q11: =IF(Lignes_hors_lot[[#This Row],[Rôle ou catégorie]]="","",Lignes_hors_lot[[#This Row],[Main-d’œuvre]]+Lignes_hors_lot[[#This Row],[Débours]]) -> 0 | T11: =IF(Lignes_hors_lot[[#This Row],[Rôle ou catégorie]]="","",IFERROR(INDEX(Referentiel[[Type de nature]],MATCH(Lignes_hors_lot[[#This Row],[Rôle ou catégorie]],Referentiel[[Entrée]],0)),"?")) -> 0
B12: =IF(Lignes_hors_lot[[#This Row],[Tâche]]="","",IFERROR(INDEX(Taches[[Description]],MATCH(Lignes_hors_lot[[#This Row],[Tâche]],Taches[[Entrée]],0)),"")) -> 0 | J12: =IF(Lignes_hors_lot[[#This Row],[Rôle ou catégorie]]="","",IFERROR(INDEX(Referentiel[[Nature]],MATCH(Lignes_hors_lot[[#This Row],[Rôle ou catégorie]],Referentiel[[Entrée]],0)),"?")) -> 0 | K12: =IF(Lignes_hors_lot[[#This Row],[Rôle ou catégorie]]="","",IFERROR(INDEX(Referentiel[[Code comptable]],MATCH(Lignes_hors_lot[[#This Row],[Rôle ou catégorie]],Referentiel[[Entrée]],0)),"?")) -> 0 | L12: =IF(Lignes_hors_lot[[#This Row],[Rôle ou catégorie]]="","",IFERROR(INDEX(Referentiel[[Service]],MATCH(Lignes_hors_lot[[#This Row],[Rôle ou catégorie]],Referentiel[[Entrée]],0)),"?")&"") -> 0 | M12: =IF(Lignes_hors_lot[[#This Row],[Rôle ou catégorie]]="","",IFERROR(INDEX(Referentiel[[Taux horaire]],MATCH(Lignes_hors_lot[[#This Row],[Rôle ou catégorie]],Referentiel[[Entrée]],0)),"?")) -> 0 | N12: =IF(Lignes_hors_lot[[#This Row],[Rôle ou catégorie]]="","",IF(Lignes_hors_lot[[#This Row],[Type]]="Main-d’œuvre",Lignes_hors_lot[[#This Row],[Quantité]]*Lignes_hors_lot[[#This Row],[Heures]],0)) -> 0 | O12: =IF(Lignes_hors_lot[[#This Row],[Rôle ou catégorie]]="","",IF(Lignes_hors_lot[[#This Row],[Type]]="Main-d’œuvre",Lignes_hors_lot[[#This Row],[Quantité]]*Lignes_hors_lot[[#This Row],[Heures]]*Lignes_hors_lot[[#This Row],[Taux horaire]],0)) -> 0 | P12: =IF(Lignes_hors_lot[[#This Row],[Rôle ou catégorie]]="","",IF(OR(Lignes_hors_lot[[#This Row],[Type]]="Hors main-d’œuvre",Lignes_hors_lot[[#This Row],[Type]]="Provision"),Lignes_hors_lot[[#This Row],[Quantité]]*Lignes_hors_lot[[#This Row],[Débours unitaire]],0)) -> 0 | Q12: =IF(Lignes_hors_lot[[#This Row],[Rôle ou catégorie]]="","",Lignes_hors_lot[[#This Row],[Main-d’œuvre]]+Lignes_hors_lot[[#This Row],[Débours]]) -> 0 | T12: =IF(Lignes_hors_lot[[#This Row],[Rôle ou catégorie]]="","",IFERROR(INDEX(Referentiel[[Type de nature]],MATCH(Lignes_hors_lot[[#This Row],[Rôle ou catégorie]],Referentiel[[Entrée]],0)),"?")) -> 0
B13: =IF(Lignes_hors_lot[[#This Row],[Tâche]]="","",IFERROR(INDEX(Taches[[Description]],MATCH(Lignes_hors_lot[[#This Row],[Tâche]],Taches[[Entrée]],0)),"")) -> 0 | J13: =IF(Lignes_hors_lot[[#This Row],[Rôle ou catégorie]]="","",IFERROR(INDEX(Referentiel[[Nature]],MATCH(Lignes_hors_lot[[#This Row],[Rôle ou catégorie]],Referentiel[[Entrée]],0)),"?")) -> 0 | K13: =IF(Lignes_hors_lot[[#This Row],[Rôle ou catégorie]]="","",IFERROR(INDEX(Referentiel[[Code comptable]],MATCH(Lignes_hors_lot[[#This Row],[Rôle ou catégorie]],Referentiel[[Entrée]],0)),"?")) -> 0 | L13: =IF(Lignes_hors_lot[[#This Row],[Rôle ou catégorie]]="","",IFERROR(INDEX(Referentiel[[Service]],MATCH(Lignes_hors_lot[[#This Row],[Rôle ou catégorie]],Referentiel[[Entrée]],0)),"?")&"") -> 0 | M13: =IF(Lignes_hors_lot[[#This Row],[Rôle ou catégorie]]="","",IFERROR(INDEX(Referentiel[[Taux horaire]],MATCH(Lignes_hors_lot[[#This Row],[Rôle ou catégorie]],Referentiel[[Entrée]],0)),"?")) -> 0 | N13: =IF(Lignes_hors_lot[[#This Row],[Rôle ou catégorie]]="","",IF(Lignes_hors_lot[[#This Row],[Type]]="Main-d’œuvre",Lignes_hors_lot[[#This Row],[Quantité]]*Lignes_hors_lot[[#This Row],[Heures]],0)) -> 0 | O13: =IF(Lignes_hors_lot[[#This Row],[Rôle ou catégorie]]="","",IF(Lignes_hors_lot[[#This Row],[Type]]="Main-d’œuvre",Lignes_hors_lot[[#This Row],[Quantité]]*Lignes_hors_lot[[#This Row],[Heures]]*Lignes_hors_lot[[#This Row],[Taux horaire]],0)) -> 0 | P13: =IF(Lignes_hors_lot[[#This Row],[Rôle ou catégorie]]="","",IF(OR(Lignes_hors_lot[[#This Row],[Type]]="Hors main-d’œuvre",Lignes_hors_lot[[#This Row],[Type]]="Provision"),Lignes_hors_lot[[#This Row],[Quantité]]*Lignes_hors_lot[[#This Row],[Débours unitaire]],0)) -> 0 | Q13: =IF(Lignes_hors_lot[[#This Row],[Rôle ou catégorie]]="","",Lignes_hors_lot[[#This Row],[Main-d’œuvre]]+Lignes_hors_lot[[#This Row],[Débours]]) -> 0 | T13: =IF(Lignes_hors_lot[[#This Row],[Rôle ou catégorie]]="","",IFERROR(INDEX(Referentiel[[Type de nature]],MATCH(Lignes_hors_lot[[#This Row],[Rôle ou catégorie]],Referentiel[[Entrée]],0)),"?")) -> 0
B14: =IF(Lignes_hors_lot[[#This Row],[Tâche]]="","",IFERROR(INDEX(Taches[[Description]],MATCH(Lignes_hors_lot[[#This Row],[Tâche]],Taches[[Entrée]],0)),"")) -> 0 | J14: =IF(Lignes_hors_lot[[#This Row],[Rôle ou catégorie]]="","",IFERROR(INDEX(Referentiel[[Nature]],MATCH(Lignes_hors_lot[[#This Row],[Rôle ou catégorie]],Referentiel[[Entrée]],0)),"?")) -> 0 | K14: =IF(Lignes_hors_lot[[#This Row],[Rôle ou catégorie]]="","",IFERROR(INDEX(Referentiel[[Code comptable]],MATCH(Lignes_hors_lot[[#This Row],[Rôle ou catégorie]],Referentiel[[Entrée]],0)),"?")) -> 0 | L14: =IF(Lignes_hors_lot[[#This Row],[Rôle ou catégorie]]="","",IFERROR(INDEX(Referentiel[[Service]],MATCH(Lignes_hors_lot[[#This Row],[Rôle ou catégorie]],Referentiel[[Entrée]],0)),"?")&"") -> 0 | M14: =IF(Lignes_hors_lot[[#This Row],[Rôle ou catégorie]]="","",IFERROR(INDEX(Referentiel[[Taux horaire]],MATCH(Lignes_hors_lot[[#This Row],[Rôle ou catégorie]],Referentiel[[Entrée]],0)),"?")) -> 0 | N14: =IF(Lignes_hors_lot[[#This Row],[Rôle ou catégorie]]="","",IF(Lignes_hors_lot[[#This Row],[Type]]="Main-d’œuvre",Lignes_hors_lot[[#This Row],[Quantité]]*Lignes_hors_lot[[#This Row],[Heures]],0)) -> 0 | O14: =IF(Lignes_hors_lot[[#This Row],[Rôle ou catégorie]]="","",IF(Lignes_hors_lot[[#This Row],[Type]]="Main-d’œuvre",Lignes_hors_lot[[#This Row],[Quantité]]*Lignes_hors_lot[[#This Row],[Heures]]*Lignes_hors_lot[[#This Row],[Taux horaire]],0)) -> 0 | P14: =IF(Lignes_hors_lot[[#This Row],[Rôle ou catégorie]]="","",IF(OR(Lignes_hors_lot[[#This Row],[Type]]="Hors main-d’œuvre",Lignes_hors_lot[[#This Row],[Type]]="Provision"),Lignes_hors_lot[[#This Row],[Quantité]]*Lignes_hors_lot[[#This Row],[Débours unitaire]],0)) -> 0 | Q14: =IF(Lignes_hors_lot[[#This Row],[Rôle ou catégorie]]="","",Lignes_hors_lot[[#This Row],[Main-d’œuvre]]+Lignes_hors_lot[[#This Row],[Débours]]) -> 0 | T14: =IF(Lignes_hors_lot[[#This Row],[Rôle ou catégorie]]="","",IFERROR(INDEX(Referentiel[[Type de nature]],MATCH(Lignes_hors_lot[[#This Row],[Rôle ou catégorie]],Referentiel[[Entrée]],0)),"?")) -> 0
... B32: =IF(Lignes_hors_lot[[#This Row],[Tâche]]="","",IFERROR(INDEX(Taches[[Description]],MATCH(Lignes_hors_lot[[#This Row],[Tâche]],Taches[[Entrée]],0)),"")) -> 0 | J32: =IF(Lignes_hors_lot[[#This Row],[Rôle ou catégorie]]="","",IFERROR(INDEX(Referentiel[[Nature]],MATCH(Lignes_hors_lot[[#This Row],[Rôle ou catégorie]],Referentiel[[Entrée]],0)),"?")) -> 0 | K32: =IF(Lignes_hors_lot[[#This Row],[Rôle ou catégorie]]="","",IFERROR(INDEX(Referentiel[[Code comptable]],MATCH(Lignes_hors_lot[[#This Row],[Rôle ou catégorie]],Referentiel[[Entrée]],0)),"?")) -> 0 | L32: =IF(Lignes_hors_lot[[#This Row],[Rôle ou catégorie]]="","",IFERROR(INDEX(Referentiel[[Service]],MATCH(Lignes_hors_lot[[#This Row],[Rôle ou catégorie]],Referentiel[[Entrée]],0)),"?")&"") -> 0 | M32: =IF(Lignes_hors_lot[[#This Row],[Rôle ou catégorie]]="","",IFERROR(INDEX(Referentiel[[Taux horaire]],MATCH(Lignes_hors_lot[[#This Row],[Rôle ou catégorie]],Referentiel[[Entrée]],0)),"?")) -> 0 | N32: =IF(Lignes_hors_lot[[#This Row],[Rôle ou catégorie]]="","",IF(Lignes_hors_lot[[#This Row],[Type]]="Main-d’œuvre",Lignes_hors_lot[[#This Row],[Quantité]]*Lignes_hors_lot[[#This Row],[Heures]],0)) -> 0 | O32: =IF(Lignes_hors_lot[[#This Row],[Rôle ou catégorie]]="","",IF(Lignes_hors_lot[[#This Row],[Type]]="Main-d’œuvre",Lignes_hors_lot[[#This Row],[Quantité]]*Lignes_hors_lot[[#This Row],[Heures]]*Lignes_hors_lot[[#This Row],[Taux horaire]],0)) -> 0 | P32: =IF(Lignes_hors_lot[[#This Row],[Rôle ou catégorie]]="","",IF(OR(Lignes_hors_lot[[#This Row],[Type]]="Hors main-d’œuvre",Lignes_hors_lot[[#This Row],[Type]]="Provision"),Lignes_hors_lot[[#This Row],[Quantité]]*Lignes_hors_lot[[#This Row],[Débours unitaire]],0)) -> 0 | Q32: =IF(Lignes_hors_lot[[#This Row],[Rôle ou catégorie]]="","",Lignes_hors_lot[[#This Row],[Main-d’œuvre]]+Lignes_hors_lot[[#This Row],[Débours]]) -> 0 | T32: =IF(Lignes_hors_lot[[#This Row],[Rôle ou catégorie]]="","",IFERROR(INDEX(Referentiel[[Type de nature]],MATCH(Lignes_hors_lot[[#This Row],[Rôle ou catégorie]],Referentiel[[Entrée]],0)),"?")) -> 0
A33: Total | N33: =SUBTOTAL(109,Lignes_hors_lot[[Heures totales]]) -> 0 | O33: =SUBTOTAL(109,Lignes_hors_lot[[Main-d’œuvre]]) -> 0 | P33: =SUBTOTAL(109,Lignes_hors_lot[[Débours]]) -> 0 | Q33: =SUBTOTAL(109,Lignes_hors_lot[[Montant]]) -> 0 | R33: =SUBTOTAL(109,Lignes_hors_lot[[Montant Waterfall]]) -> 0

Sheet Tâches
A1: Tâches de la structure : la liste de chaque onglet, et l’identifiant que l’import retrouve.
A4: Entrée | B4: ID tâche | C4: N° | D4: Libellé | E4: Onglet | F4: Début | G4: Fin | H4: Description
A5: 1.1 Centrale et logiciel | B5: t-0007 | C5: 1.1 | D5: Centrale et logiciel | E5: 1.1 Centrale et logiciel | F5: 2026-11-02 | G5: 2027-03-26
A6: 1.1.1 Management | B6: t-0011 | C6: 1.1.1 | D6: Management | E6: 1.1 Centrale et logiciel | F6: 2026-11-02 | G6: 2027-03-26 | H6: Pilotage, réunions d’avancement et compte rendu au client
A7: 1.1.2 Développement du logiciel | B7: t-0012 | C7: 1.1.2 | D7: Développement du logiciel | E7: 1.1 Centrale et logiciel | F7: 2026-11-09 | G7: 2027-02-26 | H7: Logiciel de la centrale : gestion des badges et des droits d’accès
A8: 1.1.3 Carte d’interface | B8: t-0013 | C8: 1.1.3 | D8: Carte d’interface | E8: 1.1 Centrale et logiciel | F8: 2026-11-09 | G8: 2027-01-29 | H8: Carte d’interface entre la centrale et les lecteurs
A9: 1.2 Lecteurs et câblage | B9: t-0008 | C9: 1.2 | D9: Lecteurs et câblage | E9: 1.2 Lecteurs et câblage | F9: 2027-01-04 | G9: 2027-04-30
A10: 1.2.1 Approvisionnement des lecteurs | B10: t-0021 | C10: 1.2.1 | D10: Approvisionnement des lecteurs | E10: 1.2 Lecteurs et câblage | F10: 2027-01-04 | G10: 2027-02-26 | H10: Achat et réception des lecteurs de badges
A11: 1.2.2 Câblage | B11: t-0022 | C11: 1.2.2 | D11: Câblage | E11: 1.2 Lecteurs et câblage | F11: 2027-03-01 | G11: 2027-04-30 | H11: Tirage des câbles et raccordement des lecteurs
A12: 1 Contrôle d’accès | B12: t-0003 | C12: 1 | D12: Contrôle d’accès | E12: 1 Contrôle d’accès | F12: 2026-11-02 | G12: 2027-04-30
A13: 1.3 Revue de conception | B13: t-0009 | C13: 1.3 | D13: Revue de conception | E13: 1 Contrôle d’accès | F13: 2026-12-14 | G13: 2026-12-18 | H13: Revue de conception préliminaire avec le client
A14: 2 Mise en service | B14: t-0004 | C14: 2 | D14: Mise en service | E14: 2.1 Essais sur site | F14: 2027-05-03 | G14: 2027-06-25
A15: 2.1 Essais sur site | B15: t-0010 | C15: 2.1 | D15: Essais sur site | E15: 2.1 Essais sur site | F15: 2027-05-03 | G15: 2027-06-25
A16: 2.1.1 Essais | B16: t-0031 | C16: 2.1.1 | D16: Essais | E16: 2.1 Essais sur site | F16: 2027-05-03 | G16: 2027-06-11 | H16: Essais d’intégration et recette sur site
A17: 3 Gestion de projet | B17: t-0005 | C17: 3 | D17: Gestion de projet | E17: Hors lot | F17: 2026-11-02 | G17: 2027-06-25 | H17: Gestion de projet transverse

Sheet Paramètres
A1: Référentiel de la révision : écrit par l’export, ignoré à l’import.
A2: Taux horaires de l’année de référence 2026 retenus par la révision. Les modifier ici ne change aucun taux dans Waterfall.
A4: Entrée | B4: Genre | C4: Code | D4: Libellé | E4: Service | F4: Nature | G4: Type de nature | H4: Code comptable | I4: Taux horaire | K4: Code | L4: Libellé
A5: Responsable d’affaire A1 (RA-A1) | B5: Rôle | C5: RA-A1 | D5: Responsable d’affaire A1 | E5: Affaires › Activité 1 | F5: Main-d’œuvre | G5: Main-d’œuvre | H5: I810 | I5: 100 | K5: SP-MAT | L5: Matériel
A6: Ingénieur qualité A1 (IQ-A1) | B6: Rôle | C6: IQ-A1 | D6: Ingénieur qualité A1 | E6: Affaires › Activité 1 | F6: Main-d’œuvre | G6: Main-d’œuvre | H6: I1M2 | I6: 60 | K6: SP-PRE | L6: Prestations
A7: Architecte logiciel (ARCH-LOG) | B7: Rôle | C7: ARCH-LOG | D7: Architecte logiciel | E7: Ingénierie › Logiciel | F7: Main-d’œuvre | G7: Main-d’œuvre | H7: I329 | I7: 80
A8: Développeur (DEV) | B8: Rôle | C8: DEV | D8: Développeur | E8: Ingénierie › Logiciel | F8: Main-d’œuvre | G8: Main-d’œuvre | H8: I1M2 | I8: 60
A9: Architecte électronique (ARCH-ELEC) | B9: Rôle | C9: ARCH-ELEC | D9: Architecte électronique | E9: Ingénierie › Électronique | F9: Main-d’œuvre | G9: Main-d’œuvre | H9: I329 | I9: 80
A10: Ingénieur carte (ING-CARTE) | B10: Rôle | C10: ING-CARTE | D10: Ingénieur carte | E10: Ingénierie › Électronique | F10: Main-d’œuvre | G10: Main-d’œuvre | H10: I1M2 | I10: 60
A11: Anti-intrusion (fo-AINT) | B11: Catégorie | C11: fo-AINT | D11: Anti-intrusion | F11: Fournitures | G11: Hors main-d’œuvre | H11: fo-AINT
A12: Appareillage (fo-APPA) | B12: Catégorie | C12: fo-APPA | D12: Appareillage | F12: Fournitures | G12: Hors main-d’œuvre | H12: fo-APPA
A13: Pose sur site (st-POSE) | B13: Catégorie | C13: st-POSE | D13: Pose sur site | F13: Sous-traitance | G13: Hors main-d’œuvre | H13: st-POSE
A14: Provision pour risques (PRV) | B14: Catégorie | C14: PRV | D14: Provision pour risques | F14: Provisions pour risques | G14: Provision | H14: PRV
